Workbook

Sheet Summary
A1: EXECUTIVE SUMMARY
A2: =IF(Assumptions!B5=1,"Scenario: 620 sqm (Base)","Scenario: 450 sqm (Compact)") -> Scenario: 620 sqm (Base)
A4: KEY ASSUMPTIONS | F4: SENSITIVITY: 10Y IRR (Data Table)
A5: Clinic Area (sqm) | B5: =Assumptions!D9 -> 620 | F5: ='Cash Flow & DCF'!C21 -> 0.34484329 | G5: 0.7 | H5: 0.8 | I5: 0.9 | J5: 1 | K5: 1.1 | L5: 1.2 | M5: 1.3
A6: Inflation Rate | B6: =Assumptions!B47 -> 0.04 | F6: 0.7 | G6: =$F$5*($F$6^1.8)/G$5 -> 0.25923892 | H6: =$F$5*($F$6^1.8)/H$5 -> 0.22683406 | I6: =$F$5*($F$6^1.8)/I$5 -> 0.20163027 | J6: =$F$5*($F$6^1.8)/J$5 -> 0.18146725 | K6: =$F$5*($F$6^1.8)/K$5 -> 0.16497022 | L6: =$F$5*($F$6^1.8)/L$5 -> 0.1512227 | M6: =$F$5*($F$6^1.8)/M$5 -> 0.13959019
A7: Discount Rate | B7: =Assumptions!B48 -> 0.12 | F7: 0.8 | G7: =$F$5*($F$7^1.8)/G$5 -> 0.32967477 | H7: =$F$5*($F$7^1.8)/H$5 -> 0.28846542 | I7: =$F$5*($F$7^1.8)/I$5 -> 0.25641371 | J7: =$F$5*($F$7^1.8)/J$5 -> 0.23077234 | K7: =$F$5*($F$7^1.8)/K$5 -> 0.20979304 | L7: =$F$5*($F$7^1.8)/L$5 -> 0.19231028 | M7: =$F$5*($F$7^1.8)/M$5 -> 0.17751718
A8: Total Investment | B8: =CapEx!D56 -> 6572160 | F8: 0.9 | G8: =$F$5*($F$8^1.8)/G$5 -> 0.40753063 | H8: =$F$5*($F$8^1.8)/H$5 -> 0.3565893 | I8: =$F$5*($F$8^1.8)/I$5 -> 0.31696827 | J8: =$F$5*($F$8^1.8)/J$5 -> 0.28527144 | K8: =$F$5*($F$8^1.8)/K$5 -> 0.25933767 | L8: =$F$5*($F$8^1.8)/L$5 -> 0.2377262 | M8: =$F$5*($F$8^1.8)/M$5 -> 0.21943957
F9: 1 | G9: =$F$5*($F$9^1.8)/G$5 -> 0.49263327 | H9: =$F$5*($F$9^1.8)/H$5 -> 0.43105411 | I9: =$F$5*($F$9^1.8)/I$5 -> 0.38315921 | J9: =$F$5*($F$9^1.8)/J$5 -> 0.34484329 | K9: =$F$5*($F$9^1.8)/K$5 -> 0.3134939 | L9: =$F$5*($F$9^1.8)/L$5 -> 0.28736941 | M9: =$F$5*($F$9^1.8)/M$5 -> 0.26526407
A10: INVESTMENT RETURNS | F10: 1.1 | G10: =$F$5*($F$10^1.8)/G$5 -> 0.58483125 | H10: =$F$5*($F$10^1.8)/H$5 -> 0.51172734 | I10: =$F$5*($F$10^1.8)/I$5 -> 0.45486875 | J10: =$F$5*($F$10^1.8)/J$5 -> 0.40938187 | K10: =$F$5*($F$10^1.8)/K$5 -> 0.37216534 | L10: =$F$5*($F$10^1.8)/L$5 -> 0.34115156 | M10: =$F$5*($F$10^1.8)/M$5 -> 0.31490913
A11: Metric | B11: 5 Years | C11: 10 Years | F11: 1.2 | G11: =$F$5*($F$11^1.8)/G$5 -> 0.68399036 | H11: =$F$5*($F$11^1.8)/H$5 -> 0.59849156 | I11: =$F$5*($F$11^1.8)/I$5 -> 0.5319925 | J11: =$F$5*($F$11^1.8)/J$5 -> 0.47879325 | K11: =$F$5*($F$11^1.8)/K$5 -> 0.43526659 | L11: =$F$5*($F$11^1.8)/L$5 -> 0.39899437 | M11: =$F$5*($F$11^1.8)/M$5 -> 0.3683025
A12: NPV | B12: ='Cash Flow & DCF'!B20 -> 490890.01 | C12: ='Cash Flow & DCF'!C20 -> 15036380 | F12: 1.3 | G12: =$F$5*($F$12^1.8)/G$5 -> 0.78999032 | H12: =$F$5*($F$12^1.8)/H$5 -> 0.69124153 | I12: =$F$5*($F$12^1.8)/I$5 -> 0.61443691 | J12: =$F$5*($F$12^1.8)/J$5 -> 0.55299322 | K12: =$F$5*($F$12^1.8)/K$5 -> 0.50272111 | L12: =$F$5*($F$12^1.8)/L$5 -> 0.46082769 | M12: =$F$5*($F$12^1.8)/M$5 -> 0.4253794
A13: IRR | B13: ='Cash Flow & DCF'!B21 -> 0.12431843 | C13: ='Cash Flow & DCF'!C21 -> 0.34484329
A14: Payback (years) | B14: ='Cash Flow & DCF'!B22/12 -> 4.0432371
A15: Total Cash Generated | B15: ='Cash Flow & DCF'!B23 -> 3912446.2 | C15: ='Cash Flow & DCF'!C23 -> 38322063
A16: WITH EXIT (8× EBITDA)
A17: IRR with Exit | B17: ='Cash Flow & DCF'!B32 -> 0.49443884 | C17: ='Cash Flow & DCF'!C32 -> 0.42758073
A18: NPV with Exit | B18: ='Cash Flow & DCF'!B31 -> 20057968 | C18: ='Cash Flow & DCF'!C31 -> 37392779
A19: MOIC with Exit | B19: ='Cash Flow & DCF'!B33 -> 5.5532196 | C19: ='Cash Flow & DCF'!C33 -> 15.814058
A20: Total Return (Cash + Exit) | B20: ='Cash Flow & DCF'!B30 -> 36496648 | C20: ='Cash Flow & DCF'!C30 -> 1.0393252e+08
A21: Exit Multiple Assumed | B21: ='Exit Valuation'!B5 -> 8
A23: REVENUE & EBITDA GROWTH
A24: Year | B24: Y1 | C24: Y2 | D24: Y3 | E24: Y4 | F24: Y5 | G24: Y6 | H24: Y7 | I24: Y8 | J24: Y9 | K24: Y10
A25: Revenue | B25: =Revenue!B13 -> 7645200 | C25: =Revenue!C13 -> 12526800 | D25: =Revenue!D13 -> 17853539 | E25: =Revenue!E13 -> 20738218 | F25: =Revenue!F13 -> 23739472 | G25: =Revenue!G13 -> 27649897 | H25: =Revenue!H13 -> 31220228 | I25: =Revenue!I13 -> 32469038 | ... K25: =Revenue!K13 -> 35118511
A26: EBITDA | B26: ='P&L'!B20 -> -321500 | C26: ='P&L'!C20 -> 1177869.2 | D26: ='P&L'!D20 -> 2539293.5 | E26: ='P&L'!E20 -> 3352836.7 | F26: ='P&L'!F20 -> 4389966.6 | G26: ='P&L'!G20 -> 5630139.7 | H26: ='P&L'!H20 -> 6877942.8 | I26: ='P&L'!I20 -> 7737225.8 | ... K26: ='P&L'!K20 -> 8926540.1
A27: EBITDA Margin | B27: =IF(B25<>0,B26/B25,0) -> -0.04205253 | C27: =IF(C25<>0,C26/C25,0) -> 0.094027943 | D27: =IF(D25<>0,D26/D25,0) -> 0.14222914 | E27: =IF(E25<>0,E26/E25,0) -> 0.16167429 | F27: =IF(F25<>0,F26/F25,0) -> 0.18492268 | G27: =IF(G25<>0,G26/G25,0) -> 0.20362244 | H27: =IF(H25<>0,H26/H25,0) -> 0.22030405 | I27: =IF(I25<>0,I26/I25,0) -> 0.23829551 | ... K27: =IF(K25<>0,K26/K25,0) -> 0.25418333
A28: Net Profit | B28: ='P&L'!B28 -> -995214.29 | C28: ='P&L'!C28 -> 492531.01 | D28: ='P&L'!D28 -> 1731427 | E28: ='P&L'!E28 -> 2471751.4 | F28: ='P&L'!F28 -> 3415539.6 | G28: ='P&L'!G28 -> 4544097.1 | H28: ='P&L'!H28 -> 5679597.9 | I28: ='P&L'!I28 -> 7074625.4 | ... K28: ='P&L'!K28 -> 8156901.5
A29: EBITDA Health | B29: =IF(B27>0.15,"🟢",IF(B27>0,"🟡","🔴")) -> 🔴 | C29: =IF(C27>0.15,"🟢",IF(C27>0,"🟡","🔴")) -> 🟡 | D29: =IF(D27>0.15,"🟢",IF(D27>0,"🟡","🔴")) -> 🟡 | E29: =IF(E27>0.15,"🟢",IF(E27>0,"🟡","🔴")) -> 🟢 | F29: =IF(F27>0.15,"🟢",IF(F27>0,"🟡","🔴")) -> 🟢 | G29: =IF(G27>0.15,"🟢",IF(G27>0,"🟡","🔴")) -> 🟢 | H29: =IF(H27>0.15,"🟢",IF(H27>0,"🟡","🔴")) -> 🟢 | I29: =IF(I27>0.15,"🟢",IF(I27>0,"🟡","🔴")) -> 🟢 | ... K29: =IF(K27>0.15,"🟢",IF(K27>0,"🟡","🔴")) -> 🟢
A30: Management Mode | B30: =IF(Assumptions!B6=1,"Self-Managed","External (" & TEXT(Assumptions!B123,"0%") & " fee)") -> Self-Managed
A31: Breakeven Utilization | B31: =B50 -> 0.16888908
A32: Y1 Avg Revenue/Patient (AED) | B32: ='Patient Acquisition'!B41 -> 3690.1274 | F32: THRESHOLD ALERTS
F33: KPI | G33: Actual | H33: Threshold | I33: Status
A34: MODEL INTEGRITY CHECKS | F34: Y1 EBITDA Margin | G34: ='P&L'!B21 -> -0.04205253 | H34: -0.8 | I34: =IF(G34>H34,"✓","✗ DEEP LOSS") -> ✓
A35: Check | B35: Delta | C35: Status | D35: Rule | F35: Y3 EBITDA Margin | G35: ='P&L'!D21 -> 0.14222914 | H35: 0.05 | I35: =IF(G35>H35,"✓","✗ NOT PROFITABLE") -> ✓
A36: Revenue ≡ PA × avg price | B36: =Revenue!B13-'Patient Acquisition'!B22*'Patient Acquisition'!B40 -> 0 | C36: =IF(ABS(B36)<1000,"✓ OK","✗ ERROR") -> ✓ OK | D36: Δ < 1,000 | F36: Y5 EBITDA Margin | G36: ='P&L'!F21 -> 0.18492268 | H36: 0.15 | I36: =IF(G36>H36,"✓","⚠ LOW MARGIN") -> ✓
A37: OpEx total ≡ P&L costs | B37: =OpEx!B31-('P&L'!B5+'P&L'!B10+'P&L'!B11+'P&L'!B12+'P&L'!B16+'P&L'!B17+'P&L'!B18+'P&L'!B19) -> 0 | C37: =IF(ABS(B37)<100,"✓ OK","✗ ERROR") -> ✓ OK | D37: Δ < 100 | F37: 10Y IRR | G37: ='Cash Flow & DCF'!C21 -> 0.34484329 | H37: 0.15 | I37: =IF(G37>=H37,"✓","⚠ BELOW 15%") -> ✓
A38: Monthly ≈ Annual Rev | B38: ='Monthly P&L'!N6-'P&L'!B4 -> 29502.631 | C38: =IF(ABS(B38)<1000,"✓ OK","⚠ WARN") -> ⚠ WARN | D38: Δ < 1,000 | F38: LTV:CAC | G38: ='Patient Acquisition'!B47 -> 7.6877655 | H38: 3 | I38: =IF(G38>=H38,"✓","⚠ LOW") -> ✓
A39: PA dept sum = total | B39: ='Patient Acquisition'!B22-'Patient Acquisition'!B85 -> 0 | C39: =IF(ABS(B39)<10,"✓ OK","✗ ERROR") -> ✓ OK | D39: Must match | F39: Y5 Staff Util | G39: =Capacity!F39 -> 0.66711224 | H39: 1 | I39: =IF(G39<=H39,"✓","✗ OVER") -> ✓
A40: Staff util ≤ 100% | B40: =Capacity!B39 -> 0.36571642 | C40: =IF(B40<=1,"✓ OK",IF(B40<=1.2,"⚠ HIGH","✗ OVER")) -> ✓ OK | D40: ≤ 100% | F40: Y5 Room Util | G40: =Capacity!F42 -> 0.611 | H40: 1 | I40: =IF(G40<=H40,"✓","⚠ EXPAND") -> ✓
A41: Room util ≤ 100% | B41: =Capacity!B42 -> 0.229 | C41: =IF(B41<=1,"✓ OK",IF(B41<=1.2,"⚠ HIGH","✗ OVER")) -> ✓ OK | D41: ≤ 100% | F41: ALERT STATUS | I41: =IF(COUNTIF(I34:I40,"✗*")>0,"✗ ALERTS",IF(COUNTIF(I34:I40,"⚠*")>0,"⚠ WARNINGS","✓ ALL CLEAR")) -> ✓ ALL CLEAR
A42: Seasonality avg = 1.0 | B42: =AVERAGE(Assumptions!B235:M235) -> 1.0000833 | C42: =IF(ABS(B42-1)<0.001,"✓ OK","✗ ERROR") -> ✓ OK | D42: Budget-neutral | F42: 1-VAR SENSITIVITY: Revenue Factor | G42: IRR | H42: NPV | I42: Eq.Mult
A43: LTV:CAC ≥ 3× | B43: ='Patient Acquisition'!B47 -> 7.6877655 | C43: =IF(B43>=3,"✓ OK",IF(B43>=2,"⚠ LOW","✗ BAD")) -> ✓ OK | D43: ≥ 3× | F43: Rev Factor | G43: ='Cash Flow & DCF'!C21 -> 0.34484329 | H43: ='Cash Flow & DCF'!C20 -> 15036380 | I43: ='Cash Flow & DCF'!C24 -> 6.8309693
A44: MASTER STATUS | C44: =IF(COUNTIF(C36:C43,"✗*")>0,"✗ ERRORS",IF(COUNTIF(C36:C43,"⚠*")>0,"⚠ WARNINGS","✓ ALL CLEAR")) -> ⚠ WARNINGS | D44: All checks must pass | F44: 0.6 | G44: =$G$43*($F$44^1.8) -> 0.13749725 | H44: =$H$43*($F$44^1.8) -> 5995363.9 | I44: =$I$43*($F$44^1.8) -> 2.7236706
F45: 0.7 | G45: =$G$43*($F$45^1.8) -> 0.18146725 | H45: =$H$43*($F$45^1.8) -> 7912610.2 | I45: =$I$43*($F$45^1.8) -> 3.5946682
A46: BREAKEVEN ANALYSIS | F46: 0.8 | G46: =$G$43*($F$46^1.8) -> 0.23077234 | H46: =$H$43*($F$46^1.8) -> 10062486 | I46: =$I$43*($F$46^1.8) -> 4.5713483
A47: Metric | B47: Value | C47: Notes | F47: 0.9 | G47: =$G$43*($F$47^1.8) -> 0.28527144 | H47: =$H$43*($F$47^1.8) -> 12438838 | I47: =$I$43*($F$47^1.8) -> 5.650916
A48: Monthly BE Revenue (AED) | B48: =-('P&L'!B16+'P&L'!B17+'P&L'!B18+'P&L'!B19)/'P&L'!B8/12 -> 244505.78 | C48: Fixed Costs ÷ Gross Margin | F48: 1 | G48: =$G$43*($F$48^1.8) -> 0.34484329 | H48: =$H$43*($F$48^1.8) -> 15036380 | I48: =$I$43*($F$48^1.8) -> 6.8309693
A49: BE Visits / Month | B49: =IF('Patient Acquisition'!B40>0,B48/'Patient Acquisition'!B40,0) -> 407.49556 | C49: BE Revenue ÷ Avg Revenue per Visit | F49: 1.1 | G49: =$G$43*($F$49^1.8) -> 0.40938187 | H49: =$H$43*($F$49^1.8) -> 17850490 | I49: =$I$43*($F$49^1.8) -> 8.1094083
A50: Breakeven Utilization (%) | B50: =IF(Assumptions!B190>0,B49*12/Assumptions!B190,0) -> 0.16888908 | C50: BE Visits ÷ Annual Capacity | F50: 1.2 | G50: =$G$43*($F$50^1.8) -> 0.47879325 | H50: =$H$43*($F$50^1.8) -> 20877070 | I50: =$I$43*($F$50^1.8) -> 9.4843719
A51: Months to Operational BE | B51: =IFERROR(MATCH(1,INDEX(('Monthly P&L'!B18:M18>0)*1,,),0),">12") -> 9 | C51: First month with positive EBITDA (Y1 only) | F51: 1.3 | G51: =$G$43*($F$51^1.8) -> 0.55299322 | H51: =$H$43*($F$51^1.8) -> 24112450 | I51: =$I$43*($F$51^1.8) -> 10.954192
A52: Months to Investment Payback | B52: =IF(COUNTIF('Cash Flow & DCF'!C8:L8,">0")=0,"N/A",(MATCH(1,INDEX(('Cash Flow & DCF'!C8:L8>0)*1,,),0)-1)*12+(-INDEX('Cash Flow & DCF'!B8:K8,MATCH(1,INDEX(('Cash Flow & DCF'!C8:L8>0)*1,,),0)))/(INDEX('Cash Flow & DCF'!C8:L8,MATCH(1,INDEX(('Cash Flow & DCF'!C8:L8>0)*1,,),0))-INDEX('Cash Flow & DCF'!B8:K8,MATCH(1,INDEX(('Cash Flow & DCF'!C8:L8>0)*1,,),0)))*12) -> 48.518846 | C52: Interpolated from annual cumulative CF | F52: 1.4 | G52: =$G$43*($F$52^1.8) -> 0.63190565 | H52: =$H$43*($F$52^1.8) -> 27553309 | I52: =$I$43*($F$52^1.8) -> 12.517362
A54: MANAGEMENT MODE IMPACT | F54: ≈ approximation. For exact: select G30:I38 → Data → What-If → Data Table → Column: E38
A55: Metric | B55: Self-Managed | C55: External (7%) | D55: Δ
A56: Y1 Management Fee | B56: 0 | C56: =Revenue!B13*Assumptions!$B$123 -> 535164 | D56: =B56-C56 -> -535164
A57: Y5 Management Fee | B57: 0 | C57: =Revenue!F13*Assumptions!$B$123*(1+Assumptions!$B$124)^4 -> 1695248.4 | D57: =B57-C57 -> -1695248.4
A58: 10Y Cumulative Fee | B58: 0 | C58: =SUM(Revenue!B13:K13)*Assumptions!$B$123*1.025 -> 17415784 | D58: =B58-C58 -> -17415784

Sheet Assumptions
A1: ARISHA MEDICAL CLINIC — UNIFIED FINANCIAL MODEL
A2: Location: Dubai, Studio City | 10-Year Projection
A4: SCENARIO SELECTOR
A5: Active Scenario | B5: 1 | C5: 1 = 620 sqm (Base) | 2 = 450 sqm (Compact)
A6: Management Mode | B6: 1 | C6: 1 = Self-Managed | 2 = External Management (brand fee)
A7: SCENARIO PARAMETERS
A8: Parameter | B8: 620 sqm | C8: 450 sqm | D8: Active Value | E8: Notes
A9: Clinic Area (sqm) | B9: 620 | C9: 450 | D9: =IF($B$5=1,B9,C9) -> 620
A10: Functional Space (%) | B10: 0.71 | C10: 0.65 | D10: =IF($B$5=1,B10,C10) -> 0.71 | E10: 620: 71% | 450: 65%
A11: Functional Area (sqm) | B11: =B9*B10 -> 440.2 | C11: =C9*C10 -> 292.5 | D11: =IF($B$5=1,B11,C11) -> 440.2
A12: Base Rent Rate (AED/sqm/year) | B12: 1320 | C12: 1320 | D12: =IF($B$5=1,B12,C12) -> 1320 | E12: Studio City market rate
A13: Doctor Days per Week | B13: 5 | C13: 5 | D13: =IF($B$5=1,B13,C13) -> 5 | E13: 40h work week, 5-day rotation
A14: Doctor Hours per Day | B14: 8 | C14: 8 | D14: =IF($B$5=1,B14,C14) -> 8 | E14: Excl. 1h lunch break
A15: Doctor Days per Year | B15: =B13*52 -> 260 | C15: =C13*52 -> 260 | D15: =IF($B$5=1,B15,C15) -> 260 | E15: For staff capacity calc
A16: Clinic Days per Week | B16: 7 | C16: 7 | D16: =IF($B$5=1,B16,C16) -> 7 | E16: Open 7 days, staff rotates
A17: Clinic Days per Year | B17: =B16*52 -> 364 | C17: =C16*52 -> 364 | D17: =IF($B$5=1,B17,C17) -> 364 | E17: For room capacity calc
A18: Clinic Hours per Day | B18: 10 | C18: 10 | D18: =IF($B$5=1,B18,C18) -> 10 | E18: Open hours for room utilization
A19: Max Utilization Rate | B19: 0.87 | C19: 0.87 | D19: =IF($B$5=1,B19,C19) -> 0.87
A20: Weekday Target Utilization | B20: 0.87 | C20: 0.87 | D20: =IF($B$5=1,B20,C20) -> 0.87
A21: Weekend Target Utilization | B21: 0.5 | C21: 0.5 | D21: =IF($B$5=1,B21,C21) -> 0.5
A22: Weekdays per Week | B22: 5 | C22: 5 | D22: =IF($B$5=1,B22,C22) -> 5
A23: Blended Target Utilization (max) | B23: =(B22*B20+(B16-B22)*B21)/B16 -> 0.76428571 | C23: =(C22*C20+(C16-C22)*C21)/C16 -> 0.76428571 | D23: =IF($B$5=1,B23,C23) -> 0.76428571
A24: Rent Deposit (months) | B24: 3 | C24: 3 | D24: =IF($B$5=1,B24,C24) -> 3
A25: Renovation Rate (AED/sqm) | B25: 3800 | C25: 3800 | D25: =IF($B$5=1,B25,C25) -> 3800
A26: Depreciation Period (years) | B26: 7 | C26: 7 | D26: =IF($B$5=1,B26,C26) -> 7 | E26: Equipment & fit-out
A28: STAFF CAPACITY (appointments/year)
A29: Department | B29: Cap 620 | C29: Cap 450 | D29: Active Cap | E29: Notes | F29: FTE 620 | G29: FTE 450 | H29: Rate (p/d)
A30: Ortho/Neuro | B30: =F30*$B$15*H30*$D$19 -> 6786 | C30: =G30*$B$15*H30*$D$19 -> 6786 | D30: =IF($B$5=1,B30,C30) -> 6786 | E30: 45min → 10 p/d (8h÷0.75h) | F30: 3 | G30: 3 | H30: 10
A31: Physio | B31: =F31*$B$15*H31*$D$19 -> 12214.8 | C31: =G31*$B$15*H31*$D$19 -> 10857.6 | D31: =IF($B$5=1,B31,C31) -> 12214.8 | E31: 75min → 6 p/d (8h÷1.25h) | F31: 9 | G31: 8 | H31: 6
A32: Dental | B32: =F32*$B$15*H32*$D$19 -> 2714.4 | C32: =G32*$B$15*H32*$D$19 -> 1809.6 | D32: =IF($B$5=1,B32,C32) -> 2714.4 | E32: 100min → 4 p/d (8h÷1.67h) | F32: 3 | G32: 2 | H32: 4
A33: Cosmetology | B33: =F33*$B$15*H33*$D$19 -> 2714.4 | C33: =G33*$B$15*H33*$D$19 -> 1357.2 | D33: =IF($B$5=1,B33,C33) -> 2714.4 | E33: 75min → 6 p/d (8h÷1.25h) | F33: 2 | G33: 1 | H33: 6
A34: Polyclinic (GP+Gynecologist) | B34: =F34*$B$15*H34*$D$19 -> 4524 | C34: =G34*$B$15*H34*$D$19 -> 4524 | D34: =IF($B$5=1,B34,C34) -> 4524 | E34: 45min → 10 p/d (8h÷0.75h) | F34: 2 | G34: 2 | H34: 10
A35: TOTAL Staff Capacity | B35: =SUM(B30:B34) -> 28953.6 | C35: =SUM(C30:C34) -> 25334.4 | D35: =IF($B$5=1,B35,C35) -> 28953.6 | E35: Cap = FTE × DoctorDays × Rate | F35: =SUM(F30:F34) -> 19 | G35: =SUM(G30:G34) -> 16
A37: ROOM CAPACITY (appointments/year)
A38: Department | B38: Cap 620 | C38: Cap 450 | D38: Active Cap | E38: Notes | F38: Rooms 620 | G38: Rooms 450 | H38: Avg Slot (hrs)
A39: Ortho/Neuro | B39: =F39*(($B$22*52)*FLOOR($B$18/H39,1)*$B$20 + (($B$16-$B$22)*52)*FLOOR($B$18/H39,1)*$B$21) -> 7233.2 | C39: =G39*(($C$22*52)*FLOOR($C$18/H39,1)*$C$20 + (($C$16-$C$22)*52)*FLOOR($C$18/H39,1)*$C$21) -> 3616.6 | D39: =IF($B$5=1,B39,C39) -> 7233.2 | E39: ~45 min consult (2 rooms) | F39: 2 | G39: 1 | H39: 0.75
A40: Physio | B40: =F40*(($B$22*52)*FLOOR($B$18/H40,1)*$B$20 + (($B$16-$B$22)*52)*FLOOR($B$18/H40,1)*$B$21) -> 27820 | C40: =G40*(($C$22*52)*FLOOR($C$18/H40,1)*$C$20 + (($C$16-$C$22)*52)*FLOOR($C$18/H40,1)*$C$21) -> 11128 | D40: =IF($B$5=1,B40,C40) -> 27820 | E40: 2 ind. + hall×5 + hall×3 = 10 | F40: 10 | G40: 4 | H40: 1
A41: Dental | B41: =F41*(($B$22*52)*FLOOR($B$18/H41,1)*$B$20 + (($B$16-$B$22)*52)*FLOOR($B$18/H41,1)*$B$21) -> 5007.6 | C41: =G41*(($C$22*52)*FLOOR($C$18/H41,1)*$C$20 + (($C$16-$C$22)*52)*FLOOR($C$18/H41,1)*$C$21) -> 3338.4 | D41: =IF($B$5=1,B41,C41) -> 5007.6 | E41: 3 chairs × 14 sqm each | F41: 3 | G41: 2 | H41: 1.5
A42: Cosmetology | B42: =F42*(($B$22*52)*FLOOR($B$18/H42,1)*$B$20 + (($B$16-$B$22)*52)*FLOOR($B$18/H42,1)*$B$21) -> 8346 | C42: =G42*(($C$22*52)*FLOOR($C$18/H42,1)*$C$20 + (($C$16-$C$22)*52)*FLOOR($C$18/H42,1)*$C$21) -> 2782 | D42: =IF($B$5=1,B42,C42) -> 8346 | E42: Aesthetic + Vital Signs + Derma | F42: 3 | G42: 1 | H42: 1
A43: Polyclinic (GP+Gynecologist) | B43: =F43*(($B$22*52)*FLOOR($B$18/H43,1)*$B$20 + (($B$16-$B$22)*52)*FLOOR($B$18/H43,1)*$B$21) -> 7233.2 | C43: =G43*(($C$22*52)*FLOOR($C$18/H43,1)*$C$20 + (($C$16-$C$22)*52)*FLOOR($C$18/H43,1)*$C$21) -> 7233.2 | D43: =IF($B$5=1,B43,C43) -> 7233.2 | E43: 1 GP + 1 Gyn, ~45 min each | F43: 2 | G43: 2 | H43: 0.75
A44: TOTAL Room Capacity | B44: =SUM(B39:B43) -> 55640 | C44: =SUM(C39:C43) -> 28098.2 | D44: =IF($B$5=1,B44,C44) -> 55640 | E44: Cap = Rooms × ClinicDays × (ClinicHrs/Slot) | F44: =SUM(F39:F43) -> 20 | G44: =SUM(G39:G43) -> 10
A46: INFLATION & DISCOUNT RATE | D46: WHAT-IF DRIVERS
A47: Annual Inflation Rate | B47: 0.04 | D47: Revenue Factor | E47: 1
A48: Discount Rate (WACC) | B48: 0.12 | D48: CapEx Factor | E48: 1
A49: Corporate Tax Rate | B49: 0.09 | D49: Default = 1.00. Used by Data Table.
A50: Tax Threshold (AED) | B50: 375000
A51: Terminal Growth Rate | B51: 0.03
A53: REVENUE SHARING RATES (salary = % of dept revenue)
A54: Physio Clinic | B54: 0.4
A55: Dental | B55: 0.4
A56: Cosmetology / Beauty | B56: 0.4
A57: Polyclinic (GP+Gynecologist) | B57: 0.4
A58: Ortho Injections | B58: 0.2
A59: Rev-Share Start Discount (pp) | B59: -0.1 | D59: Negative = discount from target. Y1 rate = Target + Discount
A60: Rev-Share Ramp Years | B60: 3 | D60: Years to reach target rate (linear ramp)
A61: COGS & OPERATING ASSUMPTIONS
A62: COGS Direct Materials — Dental | B62: 0.23
A63: COGS Direct Materials — Physio | B63: 0.05
A64: COGS Direct Materials — Polyclinic | B64: 0.12
A65: COGS Direct Materials — Cosmetology | B65: 0.2
A66: COGS Direct Materials — Orthotics | B66: 0.2
A67: COGS Direct Materials — Injections | B67: 0.25
A68: COGS Selling Expenses — Acquiring | B68: 0.02
A69: COGS Selling Expenses — Money Return | B69: 0.01
A70: Benefits (% of salaries) | B70: 0.02
A71: Marketing Y1 (% of revenue) | B71: 0.15 | D71: Fallback when B114=0 (legacy %-of-revenue)
A72: Marketing Y2+ (% of revenue) | B72: 0.1 | D72: Fallback when B114=0 (legacy %-of-revenue)
A73: R&D (% of revenue) | B73: 0.02
A75: GENERAL ADMINISTRATIVE EXPENSES (AED/year) | B75: 620 sqm | C75: 450 sqm | D75: Active | E75: Scaling Logic
A76: Utilities | B76: 48000 | C76: 36000 | D76: =IF($B$5=1,B76,C76) -> 48000 | E76: Area-proportional (×0.73)
A77: Fire & Safety Security | B77: 24000 | C77: 20000 | D77: =IF($B$5=1,B77,C77) -> 24000 | E77: Slightly less (fewer zones)
A78: Internet & Telephone | B78: 12000 | C78: 12000 | D78: =IF($B$5=1,B78,C78) -> 12000 | E78: Fixed — same infrastructure
A79: Repairs & Maintenance | B79: 18000 | C79: 14000 | D79: =IF($B$5=1,B79,C79) -> 18000 | E79: Area-proportional
A80: Water Maintenance | B80: 18000 | C80: 14000 | D80: =IF($B$5=1,B80,C80) -> 18000 | E80: Area-proportional
A81: Insurance | B81: 42000 | C81: 35000 | D81: =IF($B$5=1,B81,C81) -> 42000 | E81: Lower coverage (smaller space)
A82: Transportation | B82: 12000 | C82: 12000 | D82: =IF($B$5=1,B82,C82) -> 12000 | E82: Fixed
A83: Clinic Manager | B83: 180000 | C83: 180000 | D83: =IF($B$5=1,B83,C83) -> 180000 | E83: Fixed — same role
A84: Head of Dept 1 (after Y2) | B84: 60000 | C84: 60000 | D84: =IF($B$5=1,B84,C84) -> 60000 | E84: Fixed — same role
A85: Head of Dept 2 (after Y2) | B85: 60000 | C85: 0 | D85: =IF($B$5=1,B85,C85) -> 60000 | E85: 450 sqm: 1 HoD only (not 2)
A86: Admin Staff (×2) | B86: 168000 | C86: 84000 | D86: =IF($B$5=1,B86,C86) -> 168000 | E86: 450 sqm: ×1 admin (not ×2)
A87: IT Support (outsource) | B87: 24000 | C87: 24000 | D87: =IF($B$5=1,B87,C87) -> 24000 | E87: Fixed — outsourced
... A98: Consumables | B98: 12000 | C98: 10000 | D98: =IF($B$5=1,B98,C98) -> 12000 | E98: Lower patient volume
A99: TOTAL Administrative | B99: =SUM(B76:B98) -> 1538000 | C99: =SUM(C76:C98) -> 1237000 | D99: =IF($B$5=1,B99,C99) -> 1538000 | E99: Scenario-driven
A105: WORKING CAPITAL PARAMETERS
A106: Days Inventory (medications) | B106: 45
A107: Days Inventory (food/retail) | B107: 30
A108: Days Receivable | B108: 5
A109: Days Payable | B109: 30
A110: COGS Medications (%) | B110: 0.25
A111: COGS Food/Retail (%) | B111: 0.55
A113: OWN VS LEASE PARAMETERS
A114: Property Purchase Price (AED) | B114: 6200000 | C114: 4500000 | D114: =IF($B$5=1,B114,C114) -> 6200000
A115: Down Payment (%) | B115: 0.25 | C115: 0.25 | D115: =IF($B$5=1,B115,C115) -> 0.25
A116: Mortgage Rate (%) | B116: 0.045 | C116: 0.045 | D116: =IF($B$5=1,B116,C116) -> 0.045
A117: Mortgage Term (years) | B117: 20 | C117: 20 | D117: =IF($B$5=1,B117,C117) -> 20
A118: Property Appreciation (%/year) | B118: 0.03 | C118: 0.03 | D118: =IF($B$5=1,B118,C118) -> 0.03
A119: Maintenance Cost (%/year of value) | B119: 0.01 | C119: 0.01 | D119: =IF($B$5=1,B119,C119) -> 0.01
A121: MANAGEMENT FEE PARAMETERS
A122: Parameter | B122: Value | C122: Notes
A123: External Mgmt Fee (% of Revenue) | B123: 0.07 | C123: Dubai market: 5-10% for branded clinics
...

Sheet Price List
A1: PRICE LIST & SERVICE VOLUMES
A2: Note: Prices increase by inflation rate annually. Volumes scale by scenario.
A4: Hrs/Slot | B4: Service/Product | C4: Base Price | D4: Qty Y1/mo | E4: Qty Y2/mo | F4: Qty Y3/mo | G4: Qty Y4/mo | H4: Qty Y5/mo | I4: Qty Y6/mo | J4: Qty Y7/mo | K4: Qty Y8/mo | L4: Qty Y9/mo | M4: Qty Y10/mo
A5: Physio Clinic
A6: 0.5 | B6: Specialist Consultation | C6: 700 | D6: =ROUND('Patient Acquisition'!B55/12*Assumptions!$B$303,0) -> 93 | E6: =ROUND('Patient Acquisition'!C55/12*Assumptions!$B$303,0) -> 147 | F6: =ROUND('Patient Acquisition'!D55/12*Assumptions!$B$303,0) -> 202 | G6: =ROUND('Patient Acquisition'!E55/12*Assumptions!$B$303,0) -> 225 | H6: =ROUND('Patient Acquisition'!F55/12*Assumptions!$B$303,0) -> 248 | I6: =ROUND('Patient Acquisition'!G55/12*Assumptions!$B$303,0) -> 280 | J6: =ROUND('Patient Acquisition'!H55/12*Assumptions!$B$303,0) -> 310 | K6: =ROUND('Patient Acquisition'!I55/12*Assumptions!$B$303,0) -> 310 | ... M6: =ROUND('Patient Acquisition'!K55/12*Assumptions!$B$303,0) -> 310
A7: 1 | B7: Personal Rehabilitation Session | C7: 600 | D7: =ROUND('Patient Acquisition'!B55/12*Assumptions!$B$304,0) -> 447 | E7: =ROUND('Patient Acquisition'!C55/12*Assumptions!$B$304,0) -> 708 | F7: =ROUND('Patient Acquisition'!D55/12*Assumptions!$B$304,0) -> 969 | G7: =ROUND('Patient Acquisition'!E55/12*Assumptions!$B$304,0) -> 1080 | H7: =ROUND('Patient Acquisition'!F55/12*Assumptions!$B$304,0) -> 1192 | I7: =ROUND('Patient Acquisition'!G55/12*Assumptions!$B$304,0) -> 1342 | J7: =ROUND('Patient Acquisition'!H55/12*Assumptions!$B$304,0) -> 1490 | K7: =ROUND('Patient Acquisition'!I55/12*Assumptions!$B$304,0) -> 1490 | ... M7: =ROUND('Patient Acquisition'!K55/12*Assumptions!$B$304,0) -> 1490
A8: 0.5 | B8: Follow Up Consultation | C8: 350 | D8: =ROUND('Patient Acquisition'!B55/12*Assumptions!$B$305,0) -> 51 | E8: =ROUND('Patient Acquisition'!C55/12*Assumptions!$B$305,0) -> 80 | F8: =ROUND('Patient Acquisition'!D55/12*Assumptions!$B$305,0) -> 110 | G8: =ROUND('Patient Acquisition'!E55/12*Assumptions!$B$305,0) -> 123 | H8: =ROUND('Patient Acquisition'!F55/12*Assumptions!$B$305,0) -> 135 | I8: =ROUND('Patient Acquisition'!G55/12*Assumptions!$B$305,0) -> 152 | J8: =ROUND('Patient Acquisition'!H55/12*Assumptions!$B$305,0) -> 169 | K8: =ROUND('Patient Acquisition'!I55/12*Assumptions!$B$305,0) -> 169 | ... M8: =ROUND('Patient Acquisition'!K55/12*Assumptions!$B$305,0) -> 169
A9: 0.5 | B9: Injections | C9: 700 | D9: =ROUND('Patient Acquisition'!B55/12*Assumptions!$B$306,0) -> 9 | E9: =ROUND('Patient Acquisition'!C55/12*Assumptions!$B$306,0) -> 15 | F9: =ROUND('Patient Acquisition'!D55/12*Assumptions!$B$306,0) -> 20 | G9: =ROUND('Patient Acquisition'!E55/12*Assumptions!$B$306,0) -> 23 | H9: =ROUND('Patient Acquisition'!F55/12*Assumptions!$B$306,0) -> 25 | I9: =ROUND('Patient Acquisition'!G55/12*Assumptions!$B$306,0) -> 28 | J9: =ROUND('Patient Acquisition'!H55/12*Assumptions!$B$306,0) -> 31 | K9: =ROUND('Patient Acquisition'!I55/12*Assumptions!$B$306,0) -> 31 | ... M9: =ROUND('Patient Acquisition'!K55/12*Assumptions!$B$306,0) -> 31
A10: 1 | B10: Orthotics | C10: 1000 | D10: =ROUND('Patient Acquisition'!B55/12*Assumptions!$B$307,0) -> 5 | E10: =ROUND('Patient Acquisition'!C55/12*Assumptions!$B$307,0) -> 7 | F10: =ROUND('Patient Acquisition'!D55/12*Assumptions!$B$307,0) -> 10 | G10: =ROUND('Patient Acquisition'!E55/12*Assumptions!$B$307,0) -> 11 | H10: =ROUND('Patient Acquisition'!F55/12*Assumptions!$B$307,0) -> 12 | I10: =ROUND('Patient Acquisition'!G55/12*Assumptions!$B$307,0) -> 14 | J10: =ROUND('Patient Acquisition'!H55/12*Assumptions!$B$307,0) -> 16 | K10: =ROUND('Patient Acquisition'!I55/12*Assumptions!$B$307,0) -> 16 | ... M10: =ROUND('Patient Acquisition'!K55/12*Assumptions!$B$307,0) -> 16
A11: Dental Clinic
A12: 0.5 | B12: Hygiene | C12: 350 | D12: =ROUND('Patient Acquisition'!B61/12*Assumptions!$B$309,0) -> 39 | E12: =ROUND('Patient Acquisition'!C61/12*Assumptions!$B$309,0) -> 61 | F12: =ROUND('Patient Acquisition'!D61/12*Assumptions!$B$309,0) -> 84 | G12: =ROUND('Patient Acquisition'!E61/12*Assumptions!$B$309,0) -> 94 | H12: =ROUND('Patient Acquisition'!F61/12*Assumptions!$B$309,0) -> 103 | I12: =ROUND('Patient Acquisition'!G61/12*Assumptions!$B$309,0) -> 116 | J12: =ROUND('Patient Acquisition'!H61/12*Assumptions!$B$309,0) -> 125 | K12: =ROUND('Patient Acquisition'!I61/12*Assumptions!$B$309,0) -> 125 | ... M12: =ROUND('Patient Acquisition'!K61/12*Assumptions!$B$309,0) -> 125
A13: 1 | B13: Restorative | C13: 500 | D13: =ROUND('Patient Acquisition'!B61/12*Assumptions!$B$310,0) -> 52 | E13: =ROUND('Patient Acquisition'!C61/12*Assumptions!$B$310,0) -> 82 | F13: =ROUND('Patient Acquisition'!D61/12*Assumptions!$B$310,0) -> 112 | G13: =ROUND('Patient Acquisition'!E61/12*Assumptions!$B$310,0) -> 125 | H13: =ROUND('Patient Acquisition'!F61/12*Assumptions!$B$310,0) -> 138 | I13: =ROUND('Patient Acquisition'!G61/12*Assumptions!$B$310,0) -> 155 | J13: =ROUND('Patient Acquisition'!H61/12*Assumptions!$B$310,0) -> 167 | K13: =ROUND('Patient Acquisition'!I61/12*Assumptions!$B$310,0) -> 167 | ... M13: =ROUND('Patient Acquisition'!K61/12*Assumptions!$B$310,0) -> 167
A14: 2 | B14: Implantology | C14: 3500 | D14: =ROUND('Patient Acquisition'!B61/12*Assumptions!$B$311,0) -> 7 | E14: =ROUND('Patient Acquisition'!C61/12*Assumptions!$B$311,0) -> 10 | F14: =ROUND('Patient Acquisition'!D61/12*Assumptions!$B$311,0) -> 14 | G14: =ROUND('Patient Acquisition'!E61/12*Assumptions!$B$311,0) -> 16 | H14: =ROUND('Patient Acquisition'!F61/12*Assumptions!$B$311,0) -> 17 | I14: =ROUND('Patient Acquisition'!G61/12*Assumptions!$B$311,0) -> 20 | J14: =ROUND('Patient Acquisition'!H61/12*Assumptions!$B$311,0) -> 21 | K14: =ROUND('Patient Acquisition'!I61/12*Assumptions!$B$311,0) -> 21 | ... M14: =ROUND('Patient Acquisition'!K61/12*Assumptions!$B$311,0) -> 21
A15: 1.5 | B15: Aesthetic Dentistry | C15: 2200 | D15: =ROUND('Patient Acquisition'!B61/12*Assumptions!$B$312,0) -> 13 | E15: =ROUND('Patient Acquisition'!C61/12*Assumptions!$B$312,0) -> 21 | F15: =ROUND('Patient Acquisition'!D61/12*Assumptions!$B$312,0) -> 28 | G15: =ROUND('Patient Acquisition'!E61/12*Assumptions!$B$312,0) -> 32 | H15: =ROUND('Patient Acquisition'!F61/12*Assumptions!$B$312,0) -> 35 | I15: =ROUND('Patient Acquisition'!G61/12*Assumptions!$B$312,0) -> 39 | J15: =ROUND('Patient Acquisition'!H61/12*Assumptions!$B$312,0) -> 42 | K15: =ROUND('Patient Acquisition'!I61/12*Assumptions!$B$312,0) -> 42 | ... M15: =ROUND('Patient Acquisition'!K61/12*Assumptions!$B$312,0) -> 42
A16: 0.5 | B16: Follow Up Consultation | C16: 250 | D16: =ROUND('Patient Acquisition'!B61/12*Assumptions!$B$313,0) -> 20 | E16: =ROUND('Patient Acquisition'!C61/12*Assumptions!$B$313,0) -> 31 | F16: =ROUND('Patient Acquisition'!D61/12*Assumptions!$B$313,0) -> 42 | G16: =ROUND('Patient Acquisition'!E61/12*Assumptions!$B$313,0) -> 47 | H16: =ROUND('Patient Acquisition'!F61/12*Assumptions!$B$313,0) -> 52 | I16: =ROUND('Patient Acquisition'!G61/12*Assumptions!$B$313,0) -> 59 | J16: =ROUND('Patient Acquisition'!H61/12*Assumptions!$B$313,0) -> 63 | K16: =ROUND('Patient Acquisition'!I61/12*Assumptions!$B$313,0) -> 63 | ... M16: =ROUND('Patient Acquisition'!K61/12*Assumptions!$B$313,0) -> 63
A17: Polyclinic
A18: 0.5 | B18: GP | C18: 600 | D18: =ROUND('Patient Acquisition'!B67/12,0) -> 43 | E18: =ROUND('Patient Acquisition'!C67/12,0) -> 68 | F18: =ROUND('Patient Acquisition'!D67/12,0) -> 94 | G18: =ROUND('Patient Acquisition'!E67/12,0) -> 104 | H18: =ROUND('Patient Acquisition'!F67/12,0) -> 115 | I18: =ROUND('Patient Acquisition'!G67/12,0) -> 130 | J18: =ROUND('Patient Acquisition'!H67/12,0) -> 144 | K18: =ROUND('Patient Acquisition'!I67/12,0) -> 144 | ... M18: =ROUND('Patient Acquisition'!K67/12,0) -> 144
A19: 0.5 | B19: Gynecology | C19: 600 | D19: =ROUND('Patient Acquisition'!B73/12,0) -> 43 | E19: =ROUND('Patient Acquisition'!C73/12,0) -> 68 | F19: =ROUND('Patient Acquisition'!D73/12,0) -> 94 | G19: =ROUND('Patient Acquisition'!E73/12,0) -> 104 | H19: =ROUND('Patient Acquisition'!F73/12,0) -> 115 | I19: =ROUND('Patient Acquisition'!G73/12,0) -> 130 | J19: =ROUND('Patient Acquisition'!H73/12,0) -> 144 | K19: =ROUND('Patient Acquisition'!I73/12,0) -> 144 | ... M19: =ROUND('Patient Acquisition'!K73/12,0) -> 144
A20: 0.25 | B20: Blood Tests (lab partner) | C20: 300 | D20: =ROUND(('Patient Acquisition'!B67+'Patient Acquisition'!B73)/12*Assumptions!$B$319,0) -> 35 | E20: =ROUND(('Patient Acquisition'!C67+'Patient Acquisition'!C73)/12*Assumptions!$B$319,0) -> 55 | F20: =ROUND(('Patient Acquisition'!D67+'Patient Acquisition'!D73)/12*Assumptions!$B$319,0) -> 75 | G20: =ROUND(('Patient Acquisition'!E67+'Patient Acquisition'!E73)/12*Assumptions!$B$319,0) -> 84 | H20: =ROUND(('Patient Acquisition'!F67+'Patient Acquisition'!F73)/12*Assumptions!$B$319,0) -> 92 | I20: =ROUND(('Patient Acquisition'!G67+'Patient Acquisition'!G73)/12*Assumptions!$B$319,0) -> 104 | J20: =ROUND(('Patient Acquisition'!H67+'Patient Acquisition'!H73)/12*Assumptions!$B$319,0) -> 115 | K20: =ROUND(('Patient Acquisition'!I67+'Patient Acquisition'!I73)/12*Assumptions!$B$319,0) -> 115 | ... M20: =ROUND(('Patient Acquisition'!K67+'Patient Acquisition'!K73)/12*Assumptions!$B$319,0) -> 115
A21: 0.5 | B21: X-Ray | C21: 500 | D21: =ROUND(('Patient Acquisition'!B55/12*Assumptions!$B$303+'Patient Acquisition'!B67/12)*Assumptions!$B$320,0) -> 3 | E21: =ROUND(('Patient Acquisition'!C55/12*Assumptions!$B$303+'Patient Acquisition'!C67/12)*Assumptions!$B$320,0) -> 4 | F21: =ROUND(('Patient Acquisition'!D55/12*Assumptions!$B$303+'Patient Acquisition'!D67/12)*Assumptions!$B$320,0) -> 6 | G21: =ROUND(('Patient Acquisition'!E55/12*Assumptions!$B$303+'Patient Acquisition'!E67/12)*Assumptions!$B$320,0) -> 7 | H21: =ROUND(('Patient Acquisition'!F55/12*Assumptions!$B$303+'Patient Acquisition'!F67/12)*Assumptions!$B$320,0) -> 7 | I21: =ROUND(('Patient Acquisition'!G55/12*Assumptions!$B$303+'Patient Acquisition'!G67/12)*Assumptions!$B$320,0) -> 8 | J21: =ROUND(('Patient Acquisition'!H55/12*Assumptions!$B$303+'Patient Acquisition'!H67/12)*Assumptions!$B$320,0) -> 9 | K21: =ROUND(('Patient Acquisition'!I55/12*Assumptions!$B$303+'Patient Acquisition'!I67/12)*Assumptions!$B$320,0) -> 9 | ... M21: =ROUND(('Patient Acquisition'!K55/12*Assumptions!$B$303+'Patient Acquisition'!K67/12)*Assumptions!$B$320,0) -> 9
A22: 0.5 | B22: Ultrasound | C22: 400 | D22: =ROUND('Patient Acquisition'!B73/12*Assumptions!$B$321,0) -> 11 | E22: =ROUND('Patient Acquisition'!C73/12*Assumptions!$B$321,0) -> 17 | F22: =ROUND('Patient Acquisition'!D73/12*Assumptions!$B$321,0) -> 23 | G22: =ROUND('Patient Acquisition'!E73/12*Assumptions!$B$321,0) -> 26 | H22: =ROUND('Patient Acquisition'!F73/12*Assumptions!$B$321,0) -> 29 | I22: =ROUND('Patient Acquisition'!G73/12*Assumptions!$B$321,0) -> 32 | J22: =ROUND('Patient Acquisition'!H73/12*Assumptions!$B$321,0) -> 36 | K22: =ROUND('Patient Acquisition'!I73/12*Assumptions!$B$321,0) -> 36 | ... M22: =ROUND('Patient Acquisition'!K73/12*Assumptions!$B$321,0) -> 36
A23: Cosmetology
A24: 1 | B24: Session | C24: 450 | D24: =ROUND('Patient Acquisition'!B79/12*Assumptions!$B$323,0) -> 242 | E24: =ROUND('Patient Acquisition'!C79/12*Assumptions!$B$323,0) -> 383 | F24: =ROUND('Patient Acquisition'!D79/12*Assumptions!$B$323,0) -> 525 | G24: =ROUND('Patient Acquisition'!E79/12*Assumptions!$B$323,0) -> 585 | H24: =ROUND('Patient Acquisition'!F79/12*Assumptions!$B$323,0) -> 645 | I24: =ROUND('Patient Acquisition'!G79/12*Assumptions!$B$323,0) -> 696 | J24: =ROUND('Patient Acquisition'!H79/12*Assumptions!$B$323,0) -> 696 | K24: =ROUND('Patient Acquisition'!I79/12*Assumptions!$B$323,0) -> 696 | ... M24: =ROUND('Patient Acquisition'!K79/12*Assumptions!$B$323,0) -> 696
A25: Wellness Packages
B26: Essential Package | C26: 1200
B27: Premium Package | C27: 2200
B28: Elite Package | C28: 3800

Sheet Revenue
A1: REVENUE PROJECTION (10 YEARS)
A2: Prices adjusted annually by inflation rate
A4: Category | B4: Year 1 | C4: Year 2 | D4: Year 3 | E4: Year 4 | F4: Year 5 | G4: Year 6 | H4: Year 7 | I4: Year 8 | J4: Year 9 | K4: Year 10
A5: Inflation Factor | B5: =1 -> 1 | C5: =B5*(1+Assumptions!$B$47) -> 1.04 | D5: =C5*(1+Assumptions!$B$47) -> 1.0816 | E5: =D5*(1+Assumptions!$B$47) -> 1.124864 | F5: =E5*(1+Assumptions!$B$47) -> 1.1698586 | G5: =F5*(1+Assumptions!$B$47) -> 1.2166529 | H5: =G5*(1+Assumptions!$B$47) -> 1.265319 | I5: =H5*(1+Assumptions!$B$47) -> 1.3159318 | J5: =I5*(1+Assumptions!$B$47) -> 1.3685691 | K5: =J5*(1+Assumptions!$B$47) -> 1.4233118
A6: Utilization Factor (Organic + Marketing) | B6: 1 | C6: 1 | D6: 1 | E6: 1 | F6: 1 | G6: 1 | H6: 1 | I6: 1 | J6: 1 | K6: 1
A8: Physio Clinic | B8: ='Price List'!D6*12*'Price List'!C6*B5*B6+'Price List'!D7*12*'Price List'!C7*B5*B6+'Price List'!D8*12*'Price List'!C8*B5*B6+'Price List'!D9*12*'Price List'!C9*B5*B6+'Price List'!D10*12*'Price List'!C10*B5*B6 -> 4349400 | C8: ='Price List'!E6*12*'Price List'!C6*C5*C6+'Price List'!E7*12*'Price List'!C7*C5*C6+'Price List'!E8*12*'Price List'!C8*C5*C6+'Price List'!E9*12*'Price List'!C9*C5*C6+'Price List'!E10*12*'Price List'!C10*C5*C6 -> 7153536 | D8: ='Price List'!F6*12*'Price List'!C6*D5*D6+'Price List'!F7*12*'Price List'!C7*D5*D6+'Price List'!F8*12*'Price List'!C8*D5*D6+'Price List'!F9*12*'Price List'!C9*D5*D6+'Price List'!F10*12*'Price List'!C10*D5*D6 -> 10192566 | E8: ='Price List'!G6*12*'Price List'!C6*E5*E6+'Price List'!G7*12*'Price List'!C7*E5*E6+'Price List'!G8*12*'Price List'!C8*E5*E6+'Price List'!G9*12*'Price List'!C9*E5*E6+'Price List'!G10*12*'Price List'!C10*E5*E6 -> 11819846 | F8: ='Price List'!H6*12*'Price List'!C6*F5*F6+'Price List'!H7*12*'Price List'!C7*F5*F6+'Price List'!H8*12*'Price List'!C8*F5*F6+'Price List'!H9*12*'Price List'!C9*F5*F6+'Price List'!H10*12*'Price List'!C10*F5*F6 -> 13554683 | G8: ='Price List'!I6*12*'Price List'!C6*G5*G6+'Price List'!I7*12*'Price List'!C7*G5*G6+'Price List'!I8*12*'Price List'!C8*G5*G6+'Price List'!I9*12*'Price List'!C9*G5*G6+'Price List'!I10*12*'Price List'!C10*G5*G6 -> 15884620 | H8: ='Price List'!J6*12*'Price List'!C6*H5*H6+'Price List'!J7*12*'Price List'!C7*H5*H6+'Price List'!J8*12*'Price List'!C8*H5*H6+'Price List'!J9*12*'Price List'!C9*H5*H6+'Price List'!J10*12*'Price List'!C10*H5*H6 -> 18339787 | I8: ='Price List'!K6*12*'Price List'!C6*I5*I6+'Price List'!K7*12*'Price List'!C7*I5*I6+'Price List'!K8*12*'Price List'!C8*I5*I6+'Price List'!K9*12*'Price List'!C9*I5*I6+'Price List'!K10*12*'Price List'!C10*I5*I6 -> 19073378 | J8: ='Price List'!L6*12*'Price List'!C6*J5*J6+'Price List'!L7*12*'Price List'!C7*J5*J6+'Price List'!L8*12*'Price List'!C8*J5*J6+'Price List'!L9*12*'Price List'!C9*J5*J6+'Price List'!L10*12*'Price List'!C10*J5*J6 -> 19836314 | K8: ='Price List'!M6*12*'Price List'!C6*K5*K6+'Price List'!M7*12*'Price List'!C7*K5*K6+'Price List'!M8*12*'Price List'!C8*K5*K6+'Price List'!M9*12*'Price List'!C9*K5*K6+'Price List'!M10*12*'Price List'!C10*K5*K6 -> 20629766
A9: Dental Clinic | B9: ='Price List'!D12*12*'Price List'!C12*B5*B6+'Price List'!D13*12*'Price List'!C13*B5*B6+'Price List'!D14*12*'Price List'!C14*B5*B6+'Price List'!D15*12*'Price List'!C15*B5*B6+'Price List'!D16*12*'Price List'!C16*B5*B6 -> 1173000 | C9: ='Price List'!E12*12*'Price List'!C12*C5*C6+'Price List'!E13*12*'Price List'!C13*C5*C6+'Price List'!E14*12*'Price List'!C14*C5*C6+'Price List'!E15*12*'Price List'!C15*C5*C6+'Price List'!E16*12*'Price List'!C16*C5*C6 -> 1888224 | D9: ='Price List'!F12*12*'Price List'!C12*D5*D6+'Price List'!F13*12*'Price List'!C13*D5*D6+'Price List'!F14*12*'Price List'!C14*D5*D6+'Price List'!F15*12*'Price List'!C15*D5*D6+'Price List'!F16*12*'Price List'!C16*D5*D6 -> 2680204.8 | E9: ='Price List'!G12*12*'Price List'!C12*E5*E6+'Price List'!G13*12*'Price List'!C13*E5*E6+'Price List'!G14*12*'Price List'!C14*E5*E6+'Price List'!G15*12*'Price List'!C15*E5*E6+'Price List'!G16*12*'Price List'!C16*E5*E6 -> 3152543.8 | F9: ='Price List'!H12*12*'Price List'!C12*F5*F6+'Price List'!H13*12*'Price List'!C13*F5*F6+'Price List'!H14*12*'Price List'!C14*F5*F6+'Price List'!H15*12*'Price List'!C15*F5*F6+'Price List'!H16*12*'Price List'!C16*F5*F6 -> 3573450 | G9: ='Price List'!I12*12*'Price List'!C12*G5*G6+'Price List'!I13*12*'Price List'!C13*G5*G6+'Price List'!I14*12*'Price List'!C14*G5*G6+'Price List'!I15*12*'Price List'!C15*G5*G6+'Price List'!I16*12*'Price List'!C16*G5*G6 -> 4214242.3 | H9: ='Price List'!J12*12*'Price List'!C12*H5*H6+'Price List'!J13*12*'Price List'!C13*H5*H6+'Price List'!J14*12*'Price List'!C14*H5*H6+'Price List'!J15*12*'Price List'!C15*H5*H6+'Price List'!J16*12*'Price List'!C16*H5*H6 -> 4690284.5 | I9: ='Price List'!K12*12*'Price List'!C12*I5*I6+'Price List'!K13*12*'Price List'!C13*I5*I6+'Price List'!K14*12*'Price List'!C14*I5*I6+'Price List'!K15*12*'Price List'!C15*I5*I6+'Price List'!K16*12*'Price List'!C16*I5*I6 -> 4877895.9 | J9: ='Price List'!L12*12*'Price List'!C12*J5*J6+'Price List'!L13*12*'Price List'!C13*J5*J6+'Price List'!L14*12*'Price List'!C14*J5*J6+'Price List'!L15*12*'Price List'!C15*J5*J6+'Price List'!L16*12*'Price List'!C16*J5*J6 -> 5073011.8 | K9: ='Price List'!M12*12*'Price List'!C12*K5*K6+'Price List'!M13*12*'Price List'!C13*K5*K6+'Price List'!M14*12*'Price List'!C14*K5*K6+'Price List'!M15*12*'Price List'!C15*K5*K6+'Price List'!M16*12*'Price List'!C16*K5*K6 -> 5275932.2
A10: Polyclinic | B10: ='Price List'!D18*12*'Price List'!C18*B5*B6+'Price List'!D19*12*'Price List'!C19*B5*B6+'Price List'!D20*12*'Price List'!C20*B5*B6+'Price List'!D21*12*'Price List'!C21*B5*B6+'Price List'!D22*12*'Price List'!C22*B5*B6 -> 816000 | C10: ='Price List'!E18*12*'Price List'!C18*C5*C6+'Price List'!E19*12*'Price List'!C19*C5*C6+'Price List'!E20*12*'Price List'!C20*C5*C6+'Price List'!E21*12*'Price List'!C21*C5*C6+'Price List'!E22*12*'Price List'!C22*C5*C6 -> 1334112 | D10: ='Price List'!F18*12*'Price List'!C18*D5*D6+'Price List'!F19*12*'Price List'!C19*D5*D6+'Price List'!F20*12*'Price List'!C20*D5*D6+'Price List'!F21*12*'Price List'!C21*D5*D6+'Price List'!F22*12*'Price List'!C22*D5*D6 -> 1914432 | E10: ='Price List'!G18*12*'Price List'!C18*E5*E6+'Price List'!G19*12*'Price List'!C19*E5*E6+'Price List'!G20*12*'Price List'!C20*E5*E6+'Price List'!G21*12*'Price List'!C21*E5*E6+'Price List'!G22*12*'Price List'!C22*E5*E6 -> 2212382.5 | F10: ='Price List'!H18*12*'Price List'!C18*F5*F6+'Price List'!H19*12*'Price List'!C19*F5*F6+'Price List'!H20*12*'Price List'!C20*F5*F6+'Price List'!H21*12*'Price List'!C21*F5*F6+'Price List'!H22*12*'Price List'!C22*F5*F6 -> 2536721.3 | G10: ='Price List'!I18*12*'Price List'!C18*G5*G6+'Price List'!I19*12*'Price List'!C19*G5*G6+'Price List'!I20*12*'Price List'!C20*G5*G6+'Price List'!I21*12*'Price List'!C21*G5*G6+'Price List'!I22*12*'Price List'!C22*G5*G6 -> 2978366.3 | H10: ='Price List'!J18*12*'Price List'!C18*H5*H6+'Price List'!J19*12*'Price List'!C19*H5*H6+'Price List'!J20*12*'Price List'!C20*H5*H6+'Price List'!J21*12*'Price List'!C21*H5*H6+'Price List'!J22*12*'Price List'!C22*H5*H6 -> 3434581.9 | I10: ='Price List'!K18*12*'Price List'!C18*I5*I6+'Price List'!K19*12*'Price List'!C19*I5*I6+'Price List'!K20*12*'Price List'!C20*I5*I6+'Price List'!K21*12*'Price List'!C21*I5*I6+'Price List'!K22*12*'Price List'!C22*I5*I6 -> 3571965.2 | J10: ='Price List'!L18*12*'Price List'!C18*J5*J6+'Price List'!L19*12*'Price List'!C19*J5*J6+'Price List'!L20*12*'Price List'!C20*J5*J6+'Price List'!L21*12*'Price List'!C21*J5*J6+'Price List'!L22*12*'Price List'!C22*J5*J6 -> 3714843.8 | K10: ='Price List'!M18*12*'Price List'!C18*K5*K6+'Price List'!M19*12*'Price List'!C19*K5*K6+'Price List'!M20*12*'Price List'!C20*K5*K6+'Price List'!M21*12*'Price List'!C21*K5*K6+'Price List'!M22*12*'Price List'!C22*K5*K6 -> 3863437.6
A11: Cosmetology | B11: ='Price List'!D24*12*'Price List'!C24*B5*B6 -> 1306800 | C11: ='Price List'!E24*12*'Price List'!C24*C5*C6 -> 2150928 | D11: ='Price List'!F24*12*'Price List'!C24*D5*D6 -> 3066336 | E11: ='Price List'!G24*12*'Price List'!C24*E5*E6 -> 3553445.4 | F11: ='Price List'!H24*12*'Price List'!C24*F5*F6 -> 4074617.4 | G11: ='Price List'!I24*12*'Price List'!C24*G5*G6 -> 4572668.3 | H11: ='Price List'!J24*12*'Price List'!C24*H5*H6 -> 4755575 | I11: ='Price List'!K24*12*'Price List'!C24*I5*I6 -> 4945798 | J11: ='Price List'!L24*12*'Price List'!C24*J5*J6 -> 5143629.9 | K11: ='Price List'!M24*12*'Price List'!C24*K5*K6 -> 5349375.1
A12: Wellness Packages | B12: 0 | C12: 0 | D12: 0 | E12: 0 | F12: 0 | G12: 0 | H12: 0 | I12: 0 | J12: 0 | K12: 0
A13: TOTAL REVENUE | B13: =SUM(B8:B12) -> 7645200 | C13: =SUM(C8:C12) -> 12526800 | D13: =SUM(D8:D12) -> 17853539 | E13: =SUM(E8:E12) -> 20738218 | F13: =SUM(F8:F12) -> 23739472 | G13: =SUM(G8:G12) -> 27649897 | H13: =SUM(H8:H12) -> 31220228 | I13: =SUM(I8:I12) -> 32469038 | ... K13: =SUM(K8:K12) -> 35118511
A14: YoY Growth | B14: - | C14: =C13/B13-1 -> 0.63851829 | D14: =D13/C13-1 -> 0.4252274 | E14: =E13/D13-1 -> 0.16157464 | F14: =F13/E13-1 -> 0.14472093 | G14: =G13/F13-1 -> 0.16472251 | H14: =H13/G13-1 -> 0.12912638 | I14: =I13/H13-1 -> 0.04 | J14: =J13/I13-1 -> 0.04 | K14: =K13/J13-1 -> 0.04
A15: AVG Monthly Revenue | B15: =B13/12 -> 637100 | C15: =C13/12 -> 1043900 | D15: =D13/12 -> 1487794.9 | E15: =E13/12 -> 1728184.8 | F15: =F13/12 -> 1978289.3 | G15: =G13/12 -> 2304158.1 | H15: =H13/12 -> 2601685.7 | I15: =I13/12 -> 2705753.1 | ... K15: =K13/12 -> 2926542.6
A17: (Channel efficiency metrics → see Patient Acquisition sheet, rows 38-50)

Sheet Capacity
A1: CAPACITY ANALYSIS
A3: Metric | B3: Year 1 | C3: Year 2 | D3: Year 3 | E3: Year 4 | F3: Year 5 | G3: Year 6 | H3: Year 7 | I3: Year 8 | J3: Year 9 | K3: Year 10
A4: Volume Factor | B4: =Revenue!B6 -> 1 | C4: =Revenue!C6 -> 1 | D4: =Revenue!D6 -> 1 | E4: =Revenue!E6 -> 1 | F4: =Revenue!F6 -> 1 | G4: =Revenue!G6 -> 1 | H4: =Revenue!H6 -> 1 | I4: =Revenue!I6 -> 1 | ... K4: =Revenue!K6 -> 1
A6: Physio Clinic
A7: Annual Visits | B7: ='Patient Acquisition'!B55 -> 7251.2943 | C7: ='Patient Acquisition'!C55 -> 11494.41 | D7: ='Patient Acquisition'!D55 -> 15737.525 | E7: ='Patient Acquisition'!E55 -> 17542.433 | F7: ='Patient Acquisition'!F55 -> 19347.34 | G7: ='Patient Acquisition'!G55 -> 21785.548 | H7: ='Patient Acquisition'!H55 -> 24192.091 | I7: ='Patient Acquisition'!I55 -> 24192.091 | ... K7: ='Patient Acquisition'!K55 -> 24192.091
A8: Staff Utilization | B8: =IF(Assumptions!C186>0,B7/(Assumptions!C186/Assumptions!$D$19),0) -> 0.51647395 | C8: =IF(Assumptions!D186>0,C7/(Assumptions!D186/Assumptions!$D$19),0) -> 0.81869015 | D8: =IF(Assumptions!E186>0,D7/(Assumptions!E186/Assumptions!$D$19),0) -> 0.84067977 | E8: =IF(Assumptions!F186>0,E7/(Assumptions!F186/Assumptions!$D$19),0) -> 0.86501147 | F8: =IF(Assumptions!G186>0,F7/(Assumptions!G186/Assumptions!$D$19),0) -> 0.82680939 | G8: =IF(Assumptions!H186>0,G7/(Assumptions!H186/Assumptions!$D$19),0) -> 0.82147617 | H8: =IF(Assumptions!I186>0,H7/(Assumptions!I186/Assumptions!$D$19),0) -> 0.8615417 | I8: =IF(Assumptions!J186>0,I7/(Assumptions!J186/Assumptions!$D$19),0) -> 0.8615417 | ... K8: =IF(Assumptions!L186>0,K7/(Assumptions!L186/Assumptions!$D$19),0) -> 0.8161974
A9: Room Utilization | B9: =IF(Assumptions!$D$40>0,B7/Assumptions!$D$40,0) -> 0.26065041 | C9: =IF(Assumptions!$D$40>0,C7/Assumptions!$D$40,0) -> 0.41317073 | D9: =IF(Assumptions!$D$40>0,D7/Assumptions!$D$40,0) -> 0.56569106 | E9: =IF(Assumptions!$D$40>0,E7/Assumptions!$D$40,0) -> 0.63056911 | F9: =IF(Assumptions!$D$40>0,F7/Assumptions!$D$40,0) -> 0.69544715 | G9: =IF(Assumptions!$D$40>0,G7/Assumptions!$D$40,0) -> 0.78308943 | H9: =IF(Assumptions!$D$40>0,H7/Assumptions!$D$40,0) -> 0.8695935 | I9: =IF(Assumptions!$D$40>0,I7/Assumptions!$D$40,0) -> 0.8695935 | ... K9: =IF(Assumptions!$D$40>0,K7/Assumptions!$D$40,0) -> 0.8695935
A11: Dental Clinic
A12: Annual Visits | B12: ='Patient Acquisition'!B61 -> 1553.8488 | C12: ='Patient Acquisition'!C61 -> 2463.0878 | D12: ='Patient Acquisition'!D61 -> 3372.3268 | E12: ='Patient Acquisition'!E61 -> 3759.0927 | F12: ='Patient Acquisition'!F61 -> 4145.8585 | G12: ='Patient Acquisition'!G61 -> 4668.3317 | H12: ='Patient Acquisition'!H61 -> 5007.6 | I12: ='Patient Acquisition'!I61 -> 5007.6 | ... K12: ='Patient Acquisition'!K61 -> 5007.6
A13: Staff Utilization | B13: =IF(Assumptions!C187>0,B12/(Assumptions!C187/Assumptions!$D$19),0) -> 0.49802846 | C13: =IF(Assumptions!D187>0,C12/(Assumptions!D187/Assumptions!$D$19),0) -> 0.78945122 | D13: =IF(Assumptions!E187>0,D12/(Assumptions!E187/Assumptions!$D$19),0) -> 0.81065549 | E13: =IF(Assumptions!F187>0,E12/(Assumptions!F187/Assumptions!$D$19),0) -> 0.72290244 | F13: =IF(Assumptions!G187>0,F12/(Assumptions!G187/Assumptions!$D$19),0) -> 0.79728049 | G13: =IF(Assumptions!H187>0,G12/(Assumptions!H187/Assumptions!$D$19),0) -> 0.74813008 | H13: =IF(Assumptions!I187>0,H12/(Assumptions!I187/Assumptions!$D$19),0) -> 0.8025 | I13: =IF(Assumptions!J187>0,I12/(Assumptions!J187/Assumptions!$D$19),0) -> 0.8025 | ... K13: =IF(Assumptions!L187>0,K12/(Assumptions!L187/Assumptions!$D$19),0) -> 0.8025
A14: Room Utilization | B14: =IF(Assumptions!$D$41>0,B12/Assumptions!$D$41,0) -> 0.3102981 | C14: =IF(Assumptions!$D$41>0,C12/Assumptions!$D$41,0) -> 0.49186992 | D14: =IF(Assumptions!$D$41>0,D12/Assumptions!$D$41,0) -> 0.67344173 | E14: =IF(Assumptions!$D$41>0,E12/Assumptions!$D$41,0) -> 0.75067751 | F14: =IF(Assumptions!$D$41>0,F12/Assumptions!$D$41,0) -> 0.82791328 | G14: =IF(Assumptions!$D$41>0,G12/Assumptions!$D$41,0) -> 0.93224932 | H14: =IF(Assumptions!$D$41>0,H12/Assumptions!$D$41,0) -> 1 | I14: =IF(Assumptions!$D$41>0,I12/Assumptions!$D$41,0) -> 1 | ... K14: =IF(Assumptions!$D$41>0,K12/Assumptions!$D$41,0) -> 1
A16: GP
A17: Annual Visits | B17: ='Patient Acquisition'!B67 -> 517.94959 | C17: ='Patient Acquisition'!C67 -> 821.02927 | D17: ='Patient Acquisition'!D67 -> 1124.1089 | E17: ='Patient Acquisition'!E67 -> 1253.0309 | F17: ='Patient Acquisition'!F67 -> 1381.9528 | G17: ='Patient Acquisition'!G67 -> 1556.1106 | H17: ='Patient Acquisition'!H67 -> 1728.0065 | I17: ='Patient Acquisition'!I67 -> 1728.0065 | ... K17: ='Patient Acquisition'!K67 -> 1728.0065
A18: Staff Utilization | B18: =IF(Assumptions!C189*Assumptions!$B$315>0,B17/(Assumptions!C189*Assumptions!$B$315/Assumptions!$D$19),0) -> 0.19921138 | C18: =IF(Assumptions!D189*Assumptions!$B$315>0,C17/(Assumptions!D189*Assumptions!$B$315/Assumptions!$D$19),0) -> 0.31578049 | D18: =IF(Assumptions!E189*Assumptions!$B$315>0,D17/(Assumptions!E189*Assumptions!$B$315/Assumptions!$D$19),0) -> 0.43234959 | E18: =IF(Assumptions!F189*Assumptions!$B$315>0,E17/(Assumptions!F189*Assumptions!$B$315/Assumptions!$D$19),0) -> 0.48193496 | F18: =IF(Assumptions!G189*Assumptions!$B$315>0,F17/(Assumptions!G189*Assumptions!$B$315/Assumptions!$D$19),0) -> 0.53152033 | G18: =IF(Assumptions!H189*Assumptions!$B$315>0,G17/(Assumptions!H189*Assumptions!$B$315/Assumptions!$D$19),0) -> 0.59850407 | H18: =IF(Assumptions!I189*Assumptions!$B$315>0,H17/(Assumptions!I189*Assumptions!$B$315/Assumptions!$D$19),0) -> 0.66461789 | I18: =IF(Assumptions!J189*Assumptions!$B$315>0,I17/(Assumptions!J189*Assumptions!$B$315/Assumptions!$D$19),0) -> 0.66461789 | ... K18: =IF(Assumptions!L189*Assumptions!$B$315>0,K17/(Assumptions!L189*Assumptions!$B$315/Assumptions!$D$19),0) -> 0.66461789
A19: Room Utilization | B19: =IF(Assumptions!$D$43*Assumptions!$B$315>0,B17/(Assumptions!$D$43*Assumptions!$B$315),0) -> 0.14321451 | C19: =IF(Assumptions!$D$43*Assumptions!$B$315>0,C17/(Assumptions!$D$43*Assumptions!$B$315),0) -> 0.22701689 | D19: =IF(Assumptions!$D$43*Assumptions!$B$315>0,D17/(Assumptions!$D$43*Assumptions!$B$315),0) -> 0.31081926 | E19: =IF(Assumptions!$D$43*Assumptions!$B$315>0,E17/(Assumptions!$D$43*Assumptions!$B$315),0) -> 0.34646654 | F19: =IF(Assumptions!$D$43*Assumptions!$B$315>0,F17/(Assumptions!$D$43*Assumptions!$B$315),0) -> 0.38211382 | G19: =IF(Assumptions!$D$43*Assumptions!$B$315>0,G17/(Assumptions!$D$43*Assumptions!$B$315),0) -> 0.43026892 | H19: =IF(Assumptions!$D$43*Assumptions!$B$315>0,H17/(Assumptions!$D$43*Assumptions!$B$315),0) -> 0.47779862 | I19: =IF(Assumptions!$D$43*Assumptions!$B$315>0,I17/(Assumptions!$D$43*Assumptions!$B$315),0) -> 0.47779862 | ... K19: =IF(Assumptions!$D$43*Assumptions!$B$315>0,K17/(Assumptions!$D$43*Assumptions!$B$315),0) -> 0.47779862
A21: Gynecology
A22: Annual Visits | B22: ='Patient Acquisition'!B73 -> 517.94959 | C22: ='Patient Acquisition'!C73 -> 821.02927 | D22: ='Patient Acquisition'!D73 -> 1124.1089 | E22: ='Patient Acquisition'!E73 -> 1253.0309 | F22: ='Patient Acquisition'!F73 -> 1381.9528 | G22: ='Patient Acquisition'!G73 -> 1556.1106 | H22: ='Patient Acquisition'!H73 -> 1728.0065 | I22: ='Patient Acquisition'!I73 -> 1728.0065 | ... K22: ='Patient Acquisition'!K73 -> 1728.0065
A23: Staff Utilization | B23: =IF(Assumptions!C189*Assumptions!$B$316>0,B22/(Assumptions!C189*Assumptions!$B$316/Assumptions!$D$19),0) -> 0.19921138 | C23: =IF(Assumptions!D189*Assumptions!$B$316>0,C22/(Assumptions!D189*Assumptions!$B$316/Assumptions!$D$19),0) -> 0.31578049 | D23: =IF(Assumptions!E189*Assumptions!$B$316>0,D22/(Assumptions!E189*Assumptions!$B$316/Assumptions!$D$19),0) -> 0.43234959 | E23: =IF(Assumptions!F189*Assumptions!$B$316>0,E22/(Assumptions!F189*Assumptions!$B$316/Assumptions!$D$19),0) -> 0.48193496 | F23: =IF(Assumptions!G189*Assumptions!$B$316>0,F22/(Assumptions!G189*Assumptions!$B$316/Assumptions!$D$19),0) -> 0.53152033 | G23: =IF(Assumptions!H189*Assumptions!$B$316>0,G22/(Assumptions!H189*Assumptions!$B$316/Assumptions!$D$19),0) -> 0.59850407 | H23: =IF(Assumptions!I189*Assumptions!$B$316>0,H22/(Assumptions!I189*Assumptions!$B$316/Assumptions!$D$19),0) -> 0.66461789 | I23: =IF(Assumptions!J189*Assumptions!$B$316>0,I22/(Assumptions!J189*Assumptions!$B$316/Assumptions!$D$19),0) -> 0.66461789 | ... K23: =IF(Assumptions!L189*Assumptions!$B$316>0,K22/(Assumptions!L189*Assumptions!$B$316/Assumptions!$D$19),0) -> 0.66461789
A24: Room Utilization | B24: =IF(Assumptions!$D$43*Assumptions!$B$316>0,B22/(Assumptions!$D$43*Assumptions!$B$316),0) -> 0.14321451 | C24: =IF(Assumptions!$D$43*Assumptions!$B$316>0,C22/(Assumptions!$D$43*Assumptions!$B$316),0) -> 0.22701689 | D24: =IF(Assumptions!$D$43*Assumptions!$B$316>0,D22/(Assumptions!$D$43*Assumptions!$B$316),0) -> 0.31081926 | E24: =IF(Assumptions!$D$43*Assumptions!$B$316>0,E22/(Assumptions!$D$43*Assumptions!$B$316),0) -> 0.34646654 | F24: =IF(Assumptions!$D$43*Assumptions!$B$316>0,F22/(Assumptions!$D$43*Assumptions!$B$316),0) -> 0.38211382 | G24: =IF(Assumptions!$D$43*Assumptions!$B$316>0,G22/(Assumptions!$D$43*Assumptions!$B$316),0) -> 0.43026892 | H24: =IF(Assumptions!$D$43*Assumptions!$B$316>0,H22/(Assumptions!$D$43*Assumptions!$B$316),0) -> 0.47779862 | I24: =IF(Assumptions!$D$43*Assumptions!$B$316>0,I22/(Assumptions!$D$43*Assumptions!$B$316),0) -> 0.47779862 | ... K24: =IF(Assumptions!$D$43*Assumptions!$B$316>0,K22/(Assumptions!$D$43*Assumptions!$B$316),0) -> 0.47779862
A25: Cosmetology
A26: Annual Visits | B26: ='Patient Acquisition'!B79 -> 2900.5177 | C26: ='Patient Acquisition'!C79 -> 4597.7639 | D26: ='Patient Acquisition'!D79 -> 6295.0101 | E26: ='Patient Acquisition'!E79 -> 7016.973 | F26: ='Patient Acquisition'!F79 -> 7738.9359 | G26: ='Patient Acquisition'!G79 -> 8346 | H26: ='Patient Acquisition'!H79 -> 8346 | I26: ='Patient Acquisition'!I79 -> 8346 | ... K26: ='Patient Acquisition'!K79 -> 8346
A27: Staff Utilization | B27: =IF(Assumptions!C188>0,B26/(Assumptions!C188/Assumptions!$D$19),0) -> 0.61976874 | C27: =IF(Assumptions!D188>0,C26/(Assumptions!D188/Assumptions!$D$19),0) -> 0.73682114 | D27: =IF(Assumptions!E188>0,D26/(Assumptions!E188/Assumptions!$D$19),0) -> 0.80705257 | E27: =IF(Assumptions!F188>0,E26/(Assumptions!F188/Assumptions!$D$19),0) -> 0.7496766 | F27: =IF(Assumptions!G188>0,F26/(Assumptions!G188/Assumptions!$D$19),0) -> 0.82680939 | G27: =IF(Assumptions!H188>0,G26/(Assumptions!H188/Assumptions!$D$19),0) -> 0.76428571 | H27: =IF(Assumptions!I188>0,H26/(Assumptions!I188/Assumptions!$D$19),0) -> 0.76428571 | I27: =IF(Assumptions!J188>0,I26/(Assumptions!J188/Assumptions!$D$19),0) -> 0.76428571 | ... K27: =IF(Assumptions!L188>0,K26/(Assumptions!L188/Assumptions!$D$19),0) -> 0.76428571
A28: Room Utilization | B28: =IF(Assumptions!$D$42>0,B26/Assumptions!$D$42,0) -> 0.34753388 | C28: =IF(Assumptions!$D$42>0,C26/Assumptions!$D$42,0) -> 0.55089431 | D28: =IF(Assumptions!$D$42>0,D26/Assumptions!$D$42,0) -> 0.75425474 | E28: =IF(Assumptions!$D$42>0,E26/Assumptions!$D$42,0) -> 0.84075881 | F28: =IF(Assumptions!$D$42>0,F26/Assumptions!$D$42,0) -> 0.92726287 | G28: =IF(Assumptions!$D$42>0,G26/Assumptions!$D$42,0) -> 1 | H28: =IF(Assumptions!$D$42>0,H26/Assumptions!$D$42,0) -> 1 | I28: =IF(Assumptions!$D$42>0,I26/Assumptions!$D$42,0) -> 1 | ... K28: =IF(Assumptions!$D$42>0,K26/Assumptions!$D$42,0) -> 1
A30: Ortho/Neuro (within Physio dept)
A31: Staff Capacity (annual) | B31: =Assumptions!$D$30 -> 6786 | C31: =Assumptions!$D$30 -> 6786 | D31: =Assumptions!$D$30 -> 6786 | E31: =Assumptions!$D$30 -> 6786 | F31: =Assumptions!$D$30 -> 6786 | G31: =Assumptions!$D$30 -> 6786 | H31: =Assumptions!$D$30 -> 6786 | I31: =Assumptions!$D$30 -> 6786 | ... K31: =Assumptions!$D$30 -> 6786
A32: Room Capacity (annual) | B32: =Assumptions!$D$39 -> 7233.2 | C32: =Assumptions!$D$39 -> 7233.2 | D32: =Assumptions!$D$39 -> 7233.2 | E32: =Assumptions!$D$39 -> 7233.2 | F32: =Assumptions!$D$39 -> 7233.2 | G32: =Assumptions!$D$39 -> 7233.2 | H32: =Assumptions!$D$39 -> 7233.2 | I32: =Assumptions!$D$39 -> 7233.2 | ... K32: =Assumptions!$D$39 -> 7233.2
A34: OVERALL CLINIC UTILIZATION
A35: Metric | B35: Year 1 | C35: Year 2 | D35: Year 3 | E35: Year 4 | F35: Year 5 | G35: Year 6 | H35: Year 7 | I35: Year 8 | J35: Year 9 | K35: Year 10
A36: Total Visits (from PA) | B36: ='Patient Acquisition'!B85 -> 12741.56 | C36: ='Patient Acquisition'!C85 -> 20197.32 | D36: ='Patient Acquisition'!D85 -> 27653.08 | E36: ='Patient Acquisition'!E85 -> 30824.56 | F36: ='Patient Acquisition'!F85 -> 33996.04 | G36: ='Patient Acquisition'!G85 -> 37912.101 | H36: ='Patient Acquisition'!H85 -> 41001.704 | I36: ='Patient Acquisition'!I85 -> 41001.704 | ... K36: ='Patient Acquisition'!K85 -> 41001.704
A37: Total Staff Capacity | B37: =Assumptions!C190 -> 30310.8 | C37: =Assumptions!D190 -> 31668 | D37: =Assumptions!E190 -> 38001.6 | E37: =Assumptions!F190 -> 41620.8 | F37: =Assumptions!G190 -> 44335.2 | G37: =Assumptions!H190 -> 49311.6 | H37: =Assumptions!I190 -> 50668.8 | I37: =Assumptions!J190 -> 50668.8 | ... K37: =Assumptions!L190 -> 52026
A38: Total Room Capacity | B38: =Assumptions!$D$44 -> 55640 | C38: =Assumptions!$D$44 -> 55640 | D38: =Assumptions!$D$44 -> 55640 | E38: =Assumptions!$D$44 -> 55640 | F38: =Assumptions!$D$44 -> 55640 | G38: =Assumptions!$D$44 -> 55640 | H38: =Assumptions!$D$44 -> 55640 | I38: =Assumptions!$D$44 -> 55640 | ... K38: =Assumptions!$D$44 -> 55640
A39: STAFF Utilization | B39: =IF(B37>0,B36/(B37/Assumptions!$D$19),0) -> 0.36571642 | C39: =IF(C37>0,C36/(C37/Assumptions!$D$19),0) -> 0.55487143 | D39: =IF(D37>0,D36/(D37/Assumptions!$D$19),0) -> 0.63308333 | E39: =IF(E37>0,E36/(E37/Assumptions!$D$19),0) -> 0.64432609 | F39: =IF(F37>0,F36/(F37/Assumptions!$D$19),0) -> 0.66711224 | G39: =IF(G37>0,G36/(G37/Assumptions!$D$19),0) -> 0.66887969 | H39: =IF(H37>0,H36/(H37/Assumptions!$D$19),0) -> 0.70401278 | I39: =IF(I37>0,I36/(I37/Assumptions!$D$19),0) -> 0.70401278 | ... K39: =IF(K37>0,K36/(K37/Assumptions!$D$19),0) -> 0.68564723
A40: Target (mgmt input) | B40: =Assumptions!C159 -> 0.229 | C40: =Assumptions!D159 -> 0.363 | D40: =Assumptions!E159 -> 0.497 | E40: =Assumptions!F159 -> 0.554 | F40: =Assumptions!G159 -> 0.611 | G40: =Assumptions!H159 -> 0.688 | H40: =Assumptions!I159 -> 0.764 | I40: =Assumptions!J159 -> 0.764 | ... K40: =Assumptions!L159 -> 0.764
A41: Gap (Actual − Demand) | B41: =B42-B40 -> 0 | C41: =C42-C40 -> 0 | D41: =D42-D40 -> 0 | E41: =E42-E40 -> 0 | F41: =F42-F40 -> 0 | G41: =G42-G40 -> -0.0066178862 | H41: =H42-H40 -> -0.027089431 | I41: =I42-I40 -> -0.027089431 | ... K41: =K42-K40 -> -0.027089431
A42: ROOM Utilization | B42: =IF(B38>0,B36/B38,0) -> 0.229 | C42: =IF(C38>0,C36/C38,0) -> 0.363 | D42: =IF(D38>0,D36/D38,0) -> 0.497 | E42: =IF(E38>0,E36/E38,0) -> 0.554 | F42: =IF(F38>0,F36/F38,0) -> 0.611 | G42: =IF(G38>0,G36/G38,0) -> 0.68138211 | H42: =IF(H38>0,H36/H38,0) -> 0.73691057 | I42: =IF(I38>0,I36/I38,0) -> 0.73691057 | ... K42: =IF(K38>0,K36/K38,0) -> 0.73691057
A43: Binding Constraint | B43: =IF(B39>B42,"Staff","Room") -> Staff | C43: =IF(C39>C42,"Staff","Room") -> Staff | D43: =IF(D39>D42,"Staff","Room") -> Staff | E43: =IF(E39>E42,"Staff","Room") -> Staff | F43: =IF(F39>F42,"Staff","Room") -> Staff | G43: =IF(G39>G42,"Staff","Room") -> Room | H43: =IF(H39>H42,"Staff","Room") -> Room | I43: =IF(I39>I42,"Staff","Room") -> Room | ... K43: =IF(K39>K42,"Staff","Room") -> Room
A44: Spare Capacity (slots/year) | B44: =MIN(B37,B38)-B36 -> 17569.24 | C44: =MIN(C37,C38)-C36 -> 11470.68 | D44: =MIN(D37,D38)-D36 -> 10348.52 | E44: =MIN(E37,E38)-E36 -> 10796.24 | F44: =MIN(F37,F38)-F36 -> 10339.16 | G44: =MIN(G37,G38)-G36 -> 11399.499 | H44: =MIN(H37,H38)-H36 -> 9667.0959 | I44: =MIN(I37,I38)-I36 -> 9667.0959 | ... K44: =MIN(K37,K38)-K36 -> 11024.296
A45: Revenue per Visit (AED) | B45: =IF(B36>0,Revenue!B13/B36,0) -> 600.02072 | C45: =IF(C36>0,Revenue!C13/C36,0) -> 620.2209 | D45: =IF(D36>0,Revenue!D13/D36,0) -> 645.62568 | E45: =IF(E36>0,Revenue!E13/E36,0) -> 672.78228 | F45: =IF(F36>0,Revenue!F13/F36,0) -> 698.30109 | G45: =IF(G36>0,Revenue!G13/G36,0) -> 729.31588 | H45: =IF(H36>0,Revenue!H13/H36,0) -> 761.43734 | I45: =IF(I36>0,Revenue!I13/I36,0) -> 791.89483 | ... K45: =IF(K36>0,Revenue!K13/K36,0) -> 856.51345
A46: VISITS PER SPECIALIST (annual) | B46: Year 1 | C46: Year 2 | D46: Year 3 | E46: Year 4 | F46: Year 5 | G46: Year 6 | H46: Year 7 | I46: Year 8 | J46: Year 9 | K46: Year 10
A47: Physio Clinic | B47: =IF(Assumptions!C179>0,B7/Assumptions!C179,0) -> 805.69937 | C47: =IF(Assumptions!D179>0,C7/Assumptions!D179,0) -> 1277.1566 | D47: =IF(Assumptions!E179>0,D7/Assumptions!E179,0) -> 1311.4604 | E47: =IF(Assumptions!F179>0,E7/Assumptions!F179,0) -> 1349.4179 | F47: =IF(Assumptions!G179>0,F7/Assumptions!G179,0) -> 1289.8227 | G47: =IF(Assumptions!H179>0,G7/Assumptions!H179,0) -> 1281.5028 | H47: =IF(Assumptions!I179>0,H7/Assumptions!I179,0) -> 1344.0051 | I47: =IF(Assumptions!J179>0,I7/Assumptions!J179,0) -> 1344.0051 | ... K47: =IF(Assumptions!L179>0,K7/Assumptions!L179,0) -> 1273.268
A48: Dental Clinic | B48: =IF(Assumptions!C180>0,B12/Assumptions!C180,0) -> 517.94959 | C48: =IF(Assumptions!D180>0,C12/Assumptions!D180,0) -> 821.02927 | D48: =IF(Assumptions!E180>0,D12/Assumptions!E180,0) -> 843.08171 | E48: =IF(Assumptions!F180>0,E12/Assumptions!F180,0) -> 751.81854 | F48: =IF(Assumptions!G180>0,F12/Assumptions!G180,0) -> 829.17171 | G48: =IF(Assumptions!H180>0,G12/Assumptions!H180,0) -> 778.05528 | H48: =IF(Assumptions!I180>0,H12/Assumptions!I180,0) -> 834.6 | I48: =IF(Assumptions!J180>0,I12/Assumptions!J180,0) -> 834.6 | ... K48: =IF(Assumptions!L180>0,K12/Assumptions!L180,0) -> 834.6
A49: GP | B49: =IF(Assumptions!C182*Assumptions!$B$315>0,B17/(Assumptions!C182*Assumptions!$B$315),0) -> 517.94959 | C49: =IF(Assumptions!D182*Assumptions!$B$315>0,C17/(Assumptions!D182*Assumptions!$B$315),0) -> 821.02927 | D49: =IF(Assumptions!E182*Assumptions!$B$315>0,D17/(Assumptions!E182*Assumptions!$B$315),0) -> 1124.1089 | E49: =IF(Assumptions!F182*Assumptions!$B$315>0,E17/(Assumptions!F182*Assumptions!$B$315),0) -> 1253.0309 | F49: =IF(Assumptions!G182*Assumptions!$B$315>0,F17/(Assumptions!G182*Assumptions!$B$315),0) -> 1381.9528 | G49: =IF(Assumptions!H182*Assumptions!$B$315>0,G17/(Assumptions!H182*Assumptions!$B$315),0) -> 1556.1106 | H49: =IF(Assumptions!I182*Assumptions!$B$315>0,H17/(Assumptions!I182*Assumptions!$B$315),0) -> 1728.0065 | I49: =IF(Assumptions!J182*Assumptions!$B$315>0,I17/(Assumptions!J182*Assumptions!$B$315),0) -> 1728.0065 | ... K49: =IF(Assumptions!L182*Assumptions!$B$315>0,K17/(Assumptions!L182*Assumptions!$B$315),0) -> 1728.0065
A50: Gynecology | B50: =IF(Assumptions!C182*Assumptions!$B$316>0,B22/(Assumptions!C182*Assumptions!$B$316),0) -> 517.94959 | C50: =IF(Assumptions!D182*Assumptions!$B$316>0,C22/(Assumptions!D182*Assumptions!$B$316),0) -> 821.02927 | D50: =IF(Assumptions!E182*Assumptions!$B$316>0,D22/(Assumptions!E182*Assumptions!$B$316),0) -> 1124.1089 | E50: =IF(Assumptions!F182*Assumptions!$B$316>0,E22/(Assumptions!F182*Assumptions!$B$316),0) -> 1253.0309 | F50: =IF(Assumptions!G182*Assumptions!$B$316>0,F22/(Assumptions!G182*Assumptions!$B$316),0) -> 1381.9528 | G50: =IF(Assumptions!H182*Assumptions!$B$316>0,G22/(Assumptions!H182*Assumptions!$B$316),0) -> 1556.1106 | H50: =IF(Assumptions!I182*Assumptions!$B$316>0,H22/(Assumptions!I182*Assumptions!$B$316),0) -> 1728.0065 | I50: =IF(Assumptions!J182*Assumptions!$B$316>0,I22/(Assumptions!J182*Assumptions!$B$316),0) -> 1728.0065 | ... K50: =IF(Assumptions!L182*Assumptions!$B$316>0,K22/(Assumptions!L182*Assumptions!$B$316),0) -> 1728.0065
A51: Cosmetology | B51: =IF(Assumptions!C181>0,B26/Assumptions!C181,0) -> 966.83924 | C51: =IF(Assumptions!D181>0,C26/Assumptions!D181,0) -> 1149.441 | D51: =IF(Assumptions!E181>0,D26/Assumptions!E181,0) -> 1259.002 | E51: =IF(Assumptions!F181>0,E26/Assumptions!F181,0) -> 1169.4955 | F51: =IF(Assumptions!G181>0,F26/Assumptions!G181,0) -> 1289.8227 | G51: =IF(Assumptions!H181>0,G26/Assumptions!H181,0) -> 1192.2857 | H51: =IF(Assumptions!I181>0,H26/Assumptions!I181,0) -> 1192.2857 | I51: =IF(Assumptions!J181>0,I26/Assumptions!J181,0) -> 1192.2857 | ... K51: =IF(Assumptions!L181>0,K26/Assumptions!L181,0) -> 1192.2857
A52: Ortho/Neuro | B52: =IF(Assumptions!C178>0,(B7*Assumptions!$D$39/Assumptions!$D$40)/Assumptions!C178,0) -> 628.44551 | C52: =IF(Assumptions!D178>0,(C7*Assumptions!$D$39/Assumptions!$D$40)/Assumptions!D178,0) -> 996.18218 | D52: =IF(Assumptions!E178>0,(D7*Assumptions!$D$39/Assumptions!$D$40)/Assumptions!E178,0) -> 1363.9189 | E52: =IF(Assumptions!F178>0,(E7*Assumptions!$D$39/Assumptions!$D$40)/Assumptions!F178,0) -> 1520.3442 | F52: =IF(Assumptions!G178>0,(F7*Assumptions!$D$39/Assumptions!$D$40)/Assumptions!G178,0) -> 1676.7695 | G52: =IF(Assumptions!H178>0,(G7*Assumptions!$D$39/Assumptions!$D$40)/Assumptions!H178,0) -> 1888.0808 | H52: =IF(Assumptions!I178>0,(H7*Assumptions!$D$39/Assumptions!$D$40)/Assumptions!I178,0) -> 2096.6479 | I52: =IF(Assumptions!J178>0,(I7*Assumptions!$D$39/Assumptions!$D$40)/Assumptions!J178,0) -> 2096.6479 | ... K52: =IF(Assumptions!L178>0,(K7*Assumptions!$D$39/Assumptions!$D$40)/Assumptions!L178,0) -> 2096.6479
A53: Polyclinic (GP+Gyno) | B53: =IF(Assumptions!C182>0,(B17+B22)/Assumptions!C182,0) -> 517.94959 | C53: =IF(Assumptions!D182>0,(C17+C22)/Assumptions!D182,0) -> 821.02927 | D53: =IF(Assumptions!E182>0,(D17+D22)/Assumptions!E182,0) -> 1124.1089 | E53: =IF(Assumptions!F182>0,(E17+E22)/Assumptions!F182,0) -> 1253.0309 | F53: =IF(Assumptions!G182>0,(F17+F22)/Assumptions!G182,0) -> 1381.9528 | G53: =IF(Assumptions!H182>0,(G17+G22)/Assumptions!H182,0) -> 1556.1106 | H53: =IF(Assumptions!I182>0,(H17+H22)/Assumptions!I182,0) -> 1728.0065 | I53: =IF(Assumptions!J182>0,(I17+I22)/Assumptions!J182,0) -> 1728.0065 | ... K53: =IF(Assumptions!L182>0,(K17+K22)/Assumptions!L182,0) -> 1728.0065
A54: CLINIC AVERAGE | B54: =IF(Assumptions!C183>0,B36/Assumptions!C183,0) -> 637.078 | C54: =IF(Assumptions!D183>0,C36/Assumptions!D183,0) -> 961.77714 | D54: =IF(Assumptions!E183>0,D36/Assumptions!E183,0) -> 1063.58 | E54: =IF(Assumptions!F183>0,E36/Assumptions!F183,0) -> 1062.9159 | F54: =IF(Assumptions!G183>0,F36/Assumptions!G183,0) -> 1096.6465 | G54: =IF(Assumptions!H183>0,G36/Assumptions!H183,0) -> 1083.2029 | H54: =IF(Assumptions!I183>0,H36/Assumptions!I183,0) -> 1138.9362 | I54: =IF(Assumptions!J183>0,I36/Assumptions!J183,0) -> 1138.9362 | ... K54: =IF(Assumptions!L183>0,K36/Assumptions!L183,0) -> 1108.1542
A55: Revenue per sqm (AED) | B55: =Revenue!B13/Assumptions!$D$9 -> 12330.968 | C55: =Revenue!C13/Assumptions!$D$9 -> 20204.516 | D55: =Revenue!D13/Assumptions!$D$9 -> 28796.03 | E55: =Revenue!E13/Assumptions!$D$9 -> 33448.738 | F55: =Revenue!F13/Assumptions!$D$9 -> 38289.471 | G55: =Revenue!G13/Assumptions!$D$9 -> 44596.608 | H55: =Revenue!H13/Assumptions!$D$9 -> 50355.207 | I55: =Revenue!I13/Assumptions!$D$9 -> 52369.415 | ... K55: =Revenue!K13/Assumptions!$D$9 -> 56642.76
A57: UTILIZATION BY CHANNEL
A58: Retained Patient Utilization | B58: =IF(B38>0,'Patient Acquisition'!B33/B38,0) -> 0 | C58: =IF(C38>0,'Patient Acquisition'!C33/C38,0) -> 0.100302 | D58: =IF(D38>0,'Patient Acquisition'!D33/D38,0) -> 0.163713 | E58: =IF(E38>0,'Patient Acquisition'!E33/E38,0) -> 0.230608 | F58: =IF(F38>0,'Patient Acquisition'!F33/F38,0) -> 0.264258 | G58: =IF(G38>0,'Patient Acquisition'!G33/G38,0) -> 0.29939 | H58: =IF(H38>0,'Patient Acquisition'!H33/H38,0) -> 0.34187771 | I58: =IF(I38>0,'Patient Acquisition'!I33/I38,0) -> 0.37386343 | ... K58: =IF(K38>0,'Patient Acquisition'!K33/K38,0) -> 0.39262686
A59: Organic + Referral Utilization | B59: =IF(B38>0,'Patient Acquisition'!B34/B38,0) -> 0.090636233 | C59: =IF(C38>0,'Patient Acquisition'!C34/C38,0) -> 0.14555197 | D59: =IF(D38>0,'Patient Acquisition'!D34/D38,0) -> 0.17385209 | E59: =IF(E38>0,'Patient Acquisition'!E34/E38,0) -> 0.20368006 | F59: =IF(F38>0,'Patient Acquisition'!F34/F38,0) -> 0.22182712 | G59: =IF(G38>0,'Patient Acquisition'!G34/G38,0) -> 0.24080936 | H59: =IF(H38>0,'Patient Acquisition'!H34/H38,0) -> 0.26275638 | I59: =IF(I38>0,'Patient Acquisition'!I34/I38,0) -> 0.28125526 | ... K59: =IF(K38>0,'Patient Acquisition'!K34/K38,0) -> 0.3030432
A60: Marketing Utilization | B60: =IF(B38>0,'Patient Acquisition'!B35/B38,0) -> 0.13836377 | C60: =IF(C38>0,'Patient Acquisition'!C35/C38,0) -> 0.11714603 | D60: =IF(D38>0,'Patient Acquisition'!D35/D38,0) -> 0.15943491 | E60: =IF(E38>0,'Patient Acquisition'!E35/E38,0) -> 0.11971194 | F60: =IF(F38>0,'Patient Acquisition'!F35/F38,0) -> 0.12491488 | G60: =IF(G38>0,'Patient Acquisition'!G35/G38,0) -> 0.14780064 | H60: =IF(H38>0,'Patient Acquisition'!H35/H38,0) -> 0.1593659 | I60: =IF(I38>0,'Patient Acquisition'!I35/I38,0) -> 0.10888131 | ... K60: =IF(K38>0,'Patient Acquisition'!K35/K38,0) -> 0.068329947
A61: Marketing Dependency (%) | B61: =IF('Patient Acquisition'!B85>0,'Patient Acquisition'!B35/'Patient Acquisition'!B85,0) -> 0.60420859 | C61: =IF('Patient Acquisition'!C85>0,'Patient Acquisition'!C35/'Patient Acquisition'!C85,0) -> 0.32271633 | D61: =IF('Patient Acquisition'!D85>0,'Patient Acquisition'!D35/'Patient Acquisition'!D85,0) -> 0.32079458 | E61: =IF('Patient Acquisition'!E85>0,'Patient Acquisition'!E35/'Patient Acquisition'!E85,0) -> 0.21608653 | F61: =IF('Patient Acquisition'!F85>0,'Patient Acquisition'!F35/'Patient Acquisition'!F85,0) -> 0.20444333 | G61: =IF('Patient Acquisition'!G85>0,'Patient Acquisition'!G35/'Patient Acquisition'!G85,0) -> 0.21691301 | H61: =IF('Patient Acquisition'!H85>0,'Patient Acquisition'!H35/'Patient Acquisition'!H85,0) -> 0.21626221 | I61: =IF('Patient Acquisition'!I85>0,'Patient Acquisition'!I35/'Patient Acquisition'!I85,0) -> 0.14775377 | ... K61: =IF('Patient Acquisition'!K85>0,'Patient Acquisition'!K35/'Patient Acquisition'!K85,0) -> 0.092724884
A63: FTE REQUIREMENTS (demand-based)
A64: Position | B64: Year 1 | C64: Year 2 | D64: Year 3 | E64: Year 4 | F64: Year 5 | G64: Year 6 | H64: Year 7 | I64: Year 8 | J64: Year 9 | K64: Year 10 | L64: Rate (p/d)
A65: Physiotherapists | B65: =IFERROR('Patient Acquisition'!B55/(Assumptions!$B$15*Assumptions!$H$31),0) -> 4.6482656 | C65: =IFERROR('Patient Acquisition'!C55/(Assumptions!$B$15*Assumptions!$H$31),0) -> 7.3682114 | D65: =IFERROR('Patient Acquisition'!D55/(Assumptions!$B$15*Assumptions!$H$31),0) -> 10.088157 | E65: =IFERROR('Patient Acquisition'!E55/(Assumptions!$B$15*Assumptions!$H$31),0) -> 11.245149 | F65: =IFERROR('Patient Acquisition'!F55/(Assumptions!$B$15*Assumptions!$H$31),0) -> 12.402141 | G65: =IFERROR('Patient Acquisition'!G55/(Assumptions!$B$15*Assumptions!$H$31),0) -> 13.965095 | H65: =IFERROR('Patient Acquisition'!H55/(Assumptions!$B$15*Assumptions!$H$31),0) -> 15.507751 | I65: =IFERROR('Patient Acquisition'!I55/(Assumptions!$B$15*Assumptions!$H$31),0) -> 15.507751 | ... K65: =IFERROR('Patient Acquisition'!K55/(Assumptions!$B$15*Assumptions!$H$31),0) -> 15.507751 | L65: =Assumptions!H31 -> 6
A66: Dentists | B66: =IFERROR('Patient Acquisition'!B61/(Assumptions!$B$15*Assumptions!$H$32),0) -> 1.4940854 | C66: =IFERROR('Patient Acquisition'!C61/(Assumptions!$B$15*Assumptions!$H$32),0) -> 2.3683537 | D66: =IFERROR('Patient Acquisition'!D61/(Assumptions!$B$15*Assumptions!$H$32),0) -> 3.242622 | E66: =IFERROR('Patient Acquisition'!E61/(Assumptions!$B$15*Assumptions!$H$32),0) -> 3.6145122 | F66: =IFERROR('Patient Acquisition'!F61/(Assumptions!$B$15*Assumptions!$H$32),0) -> 3.9864024 | G66: =IFERROR('Patient Acquisition'!G61/(Assumptions!$B$15*Assumptions!$H$32),0) -> 4.4887805 | H66: =IFERROR('Patient Acquisition'!H61/(Assumptions!$B$15*Assumptions!$H$32),0) -> 4.815 | I66: =IFERROR('Patient Acquisition'!I61/(Assumptions!$B$15*Assumptions!$H$32),0) -> 4.815 | ... K66: =IFERROR('Patient Acquisition'!K61/(Assumptions!$B$15*Assumptions!$H$32),0) -> 4.815 | L66: =Assumptions!H32 -> 4
A67: GP / Specialist | B67: =IFERROR(('Patient Acquisition'!B67+'Patient Acquisition'!B73)/(Assumptions!$B$15*Assumptions!$H$34),0) -> 0.39842276 | C67: =IFERROR(('Patient Acquisition'!C67+'Patient Acquisition'!C73)/(Assumptions!$B$15*Assumptions!$H$34),0) -> 0.63156098 | D67: =IFERROR(('Patient Acquisition'!D67+'Patient Acquisition'!D73)/(Assumptions!$B$15*Assumptions!$H$34),0) -> 0.86469919 | E67: =IFERROR(('Patient Acquisition'!E67+'Patient Acquisition'!E73)/(Assumptions!$B$15*Assumptions!$H$34),0) -> 0.96386992 | F67: =IFERROR(('Patient Acquisition'!F67+'Patient Acquisition'!F73)/(Assumptions!$B$15*Assumptions!$H$34),0) -> 1.0630407 | G67: =IFERROR(('Patient Acquisition'!G67+'Patient Acquisition'!G73)/(Assumptions!$B$15*Assumptions!$H$34),0) -> 1.1970081 | H67: =IFERROR(('Patient Acquisition'!H67+'Patient Acquisition'!H73)/(Assumptions!$B$15*Assumptions!$H$34),0) -> 1.3292358 | I67: =IFERROR(('Patient Acquisition'!I67+'Patient Acquisition'!I73)/(Assumptions!$B$15*Assumptions!$H$34),0) -> 1.3292358 | ... K67: =IFERROR(('Patient Acquisition'!K67+'Patient Acquisition'!K73)/(Assumptions!$B$15*Assumptions!$H$34),0) -> 1.3292358 | L67: =Assumptions!H34 -> 10
A68: Cosmetologist | B68: =IFERROR('Patient Acquisition'!B79/(Assumptions!$B$15*Assumptions!$H$33),0) -> 1.8593062 | C68: =IFERROR('Patient Acquisition'!C79/(Assumptions!$B$15*Assumptions!$H$33),0) -> 2.9472846 | D68: =IFERROR('Patient Acquisition'!D79/(Assumptions!$B$15*Assumptions!$H$33),0) -> 4.0352629 | E68: =IFERROR('Patient Acquisition'!E79/(Assumptions!$B$15*Assumptions!$H$33),0) -> 4.4980596 | F68: =IFERROR('Patient Acquisition'!F79/(Assumptions!$B$15*Assumptions!$H$33),0) -> 4.9608564 | G68: =IFERROR('Patient Acquisition'!G79/(Assumptions!$B$15*Assumptions!$H$33),0) -> 5.35 | H68: =IFERROR('Patient Acquisition'!H79/(Assumptions!$B$15*Assumptions!$H$33),0) -> 5.35 | I68: =IFERROR('Patient Acquisition'!I79/(Assumptions!$B$15*Assumptions!$H$33),0) -> 5.35 | ... K68: =IFERROR('Patient Acquisition'!K79/(Assumptions!$B$15*Assumptions!$H$33),0) -> 5.35 | L68: =Assumptions!H33 -> 6
A69: TOTAL Required FTE | B69: =SUM(B65:B68) -> 8.4000799 | C69: =SUM(C65:C68) -> 13.315411 | D69: =SUM(D65:D68) -> 18.230741 | E69: =SUM(E65:E68) -> 20.321591 | F69: =SUM(F65:F68) -> 22.41244 | G69: =SUM(G65:G68) -> 25.000883 | H69: =SUM(H65:H68) -> 27.001986 | I69: =SUM(I65:I68) -> 27.001986 | ... K69: =SUM(K65:K68) -> 27.001986
A70: Actual FTE (from Hiring Plan) | B70: =Assumptions!C183 -> 20 | C70: =Assumptions!D183 -> 21 | D70: =Assumptions!E183 -> 26 | E70: =Assumptions!F183 -> 29 | F70: =Assumptions!G183 -> 31 | G70: =Assumptions!H183 -> 35 | H70: =Assumptions!I183 -> 36 | I70: =Assumptions!J183 -> 36 | ... K70: =Assumptions!L183 -> 37
A72: FTE Surplus / (Deficit) | B72: =B70-B69 -> 11.59992 | C72: =C70-C69 -> 7.6845894 | D72: =D70-D69 -> 7.7692588 | E72: =E70-E69 -> 8.6784092 | F72: =F70-F69 -> 8.5875596 | G72: =G70-G69 -> 9.9991165 | H72: =H70-H69 -> 8.9980136 | I72: =I70-I69 -> 8.9980136 | ... K72: =K70-K69 -> 9.9980136

Sheet Sales Plan
A1: SALES PLAN — Dual Validation
A3: Revenue Stream | B3: Y1 | C3: Y2 | D3: Y3 | E3: Y4 | F3: Y5 | G3: Y6 | H3: Y7 | I3: Y8 | J3: Y9 | K3: Y10
A4: 1. BOTTOM-UP REVENUE (from Price List × Qty × Inflation)
A5: Physio Clinic | B5: =Revenue!B8 -> 4349400 | C5: =Revenue!C8 -> 7153536 | D5: =Revenue!D8 -> 10192566 | E5: =Revenue!E8 -> 11819846 | F5: =Revenue!F8 -> 13554683 | G5: =Revenue!G8 -> 15884620 | H5: =Revenue!H8 -> 18339787 | I5: =Revenue!I8 -> 19073378 | ... K5: =Revenue!K8 -> 20629766
A6: Dental Clinic | B6: =Revenue!B9 -> 1173000 | C6: =Revenue!C9 -> 1888224 | D6: =Revenue!D9 -> 2680204.8 | E6: =Revenue!E9 -> 3152543.8 | F6: =Revenue!F9 -> 3573450 | G6: =Revenue!G9 -> 4214242.3 | H6: =Revenue!H9 -> 4690284.5 | I6: =Revenue!I9 -> 4877895.9 | ... K6: =Revenue!K9 -> 5275932.2
A7: Polyclinic | B7: =Revenue!B10 -> 816000 | C7: =Revenue!C10 -> 1334112 | D7: =Revenue!D10 -> 1914432 | E7: =Revenue!E10 -> 2212382.5 | F7: =Revenue!F10 -> 2536721.3 | G7: =Revenue!G10 -> 2978366.3 | H7: =Revenue!H10 -> 3434581.9 | I7: =Revenue!I10 -> 3571965.2 | ... K7: =Revenue!K10 -> 3863437.6
A8: Cosmetology | B8: =Revenue!B11 -> 1306800 | C8: =Revenue!C11 -> 2150928 | D8: =Revenue!D11 -> 3066336 | E8: =Revenue!E11 -> 3553445.4 | F8: =Revenue!F11 -> 4074617.4 | G8: =Revenue!G11 -> 4572668.3 | H8: =Revenue!H11 -> 4755575 | I8: =Revenue!I11 -> 4945798 | ... K8: =Revenue!K11 -> 5349375.1
A9: Wellness Packages | B9: =Revenue!B12 -> 0 | C9: =Revenue!C12 -> 0 | D9: =Revenue!D12 -> 0 | E9: =Revenue!E12 -> 0 | F9: =Revenue!F12 -> 0 | G9: =Revenue!G12 -> 0 | H9: =Revenue!H12 -> 0 | I9: =Revenue!I12 -> 0 | ... K9: =Revenue!K12 -> 0
A10: TOTAL BOTTOM-UP | B10: =SUM(B5:B9) -> 7645200 | C10: =SUM(C5:C9) -> 12526800 | D10: =SUM(D5:D9) -> 17853539 | E10: =SUM(E5:E9) -> 20738218 | F10: =SUM(F5:F9) -> 23739472 | G10: =SUM(G5:G9) -> 27649897 | H10: =SUM(H5:H9) -> 31220228 | I10: =SUM(I5:I9) -> 32469038 | ... K10: =SUM(K5:K9) -> 35118511
A12: 2. TOP-DOWN TARGETS (Revenue at Full Capacity)
A13: Physio Clinic | B13: =IFERROR(B5/Assumptions!B242,0) -> 14498000 | C13: =IFERROR(C5/Assumptions!C242,0) -> 10735553 | D13: =IFERROR(D5/Assumptions!D242,0) -> 11672413 | E13: =IFERROR(E5/Assumptions!E242,0) -> 14571921 | F13: =IFERROR(F5/Assumptions!F242,0) -> 16594779 | G13: =IFERROR(G5/Assumptions!G242,0) -> 18397125 | H13: =IFERROR(H5/Assumptions!H242,0) -> 21274673 | I13: =IFERROR(I5/Assumptions!I242,0) -> 22734623 | ... K13: =IFERROR(K5/Assumptions!K242,0) -> 24589769
A14: Dental Clinic | B14: =IFERROR(B6/Assumptions!B242,0) -> 3910000 | C14: =IFERROR(C6/Assumptions!C242,0) -> 2833721.5 | D14: =IFERROR(D6/Assumptions!D242,0) -> 3069340.8 | E14: =IFERROR(E6/Assumptions!E242,0) -> 3886566.8 | F14: =IFERROR(F6/Assumptions!F242,0) -> 4374916.8 | G14: =IFERROR(G6/Assumptions!G242,0) -> 4880818 | H14: =IFERROR(H6/Assumptions!H242,0) -> 5440863.2 | I14: =IFERROR(I6/Assumptions!I242,0) -> 5814236.2 | ... K14: =IFERROR(K6/Assumptions!K242,0) -> 6288677.8
A15: Polyclinic | B15: =IFERROR(B7/Assumptions!B242,0) -> 2720000 | C15: =IFERROR(C7/Assumptions!C242,0) -> 2002146.9 | D15: =IFERROR(D7/Assumptions!D242,0) -> 2192386.3 | E15: =IFERROR(E7/Assumptions!E242,0) -> 2727502.9 | F15: =IFERROR(F7/Assumptions!F242,0) -> 3105666.7 | G15: =IFERROR(G7/Assumptions!G242,0) -> 3449460.9 | H15: =IFERROR(H7/Assumptions!H242,0) -> 3984212.5 | I15: =IFERROR(I7/Assumptions!I242,0) -> 4257624.5 | ... K15: =IFERROR(K7/Assumptions!K242,0) -> 4605046.7
A16: Cosmetology | B16: =IFERROR(B8/Assumptions!B242,0) -> 4356000 | C16: =IFERROR(C8/Assumptions!C242,0) -> 3227970.3 | D16: =IFERROR(D8/Assumptions!D242,0) -> 3511533.9 | E16: =IFERROR(E8/Assumptions!E242,0) -> 4380812.2 | F16: =IFERROR(F8/Assumptions!F242,0) -> 4988487.9 | G16: =IFERROR(G8/Assumptions!G242,0) -> 5295937 | H16: =IFERROR(H8/Assumptions!H242,0) -> 5516602 | I16: =IFERROR(I8/Assumptions!I242,0) -> 5895172.4 | ... K16: =IFERROR(K8/Assumptions!K242,0) -> 6376218.5
A17: Wellness Packages | B17: =IFERROR(B9/Assumptions!B242,0) -> 0 | C17: =IFERROR(C9/Assumptions!C242,0) -> 0 | D17: =IFERROR(D9/Assumptions!D242,0) -> 0 | E17: =IFERROR(E9/Assumptions!E242,0) -> 0 | F17: =IFERROR(F9/Assumptions!F242,0) -> 0 | G17: =IFERROR(G9/Assumptions!G242,0) -> 0 | H17: =IFERROR(H9/Assumptions!H242,0) -> 0 | I17: =IFERROR(I9/Assumptions!I242,0) -> 0 | ... K17: =IFERROR(K9/Assumptions!K242,0) -> 0
A18: TOTAL TARGET | B18: =SUM(B13:B17) -> 25484000 | C18: =SUM(C13:C17) -> 18799392 | D18: =SUM(D13:D17) -> 20445674 | E18: =SUM(E13:E17) -> 25566803 | F18: =SUM(F13:F17) -> 29063850 | G18: =SUM(G13:G17) -> 32023341 | H18: =SUM(H13:H17) -> 36216351 | I18: =SUM(I13:I17) -> 38701657 | ... K18: =SUM(K13:K17) -> 41859712
A19: Full capacity = Bottom-Up ÷ Utilization Factor (from cohort model)
A20: 3. GAP ANALYSIS (Target − Bottom-Up)
A21: Total Gap (AED) | B21: =B18-B10 -> 17838800 | C21: =C18-C10 -> 6272591.7 | D21: =D18-D10 -> 2592135.5 | E21: =E18-E10 -> 4828585.3 | F21: =F18-F10 -> 5324378.2 | G21: =G18-G10 -> 4373443.3 | H21: =H18-H10 -> 4996122.6 | I21: =I18-I10 -> 6232619 | ... K21: =K18-K10 -> 6741200.7
A22: Gap (%) | B22: =IF(B10<>0,(B18-B10)/B10,0) -> 2.3333333 | C22: =IF(C10<>0,(C18-C10)/C10,0) -> 0.50073376 | D22: =IF(D10<>0,(D18-D10)/D10,0) -> 0.14518889 | E22: =IF(E10<>0,(E18-E10)/E10,0) -> 0.23283512 | F22: =IF(F10<>0,(F18-F10)/F10,0) -> 0.22428377 | G22: =IF(G10<>0,(G18-G10)/G10,0) -> 0.15817214 | H22: =IF(H10<>0,(H18-H10)/H10,0) -> 0.16002838 | I22: =IF(I10<>0,(I18-I10)/I10,0) -> 0.19195577 | ... K22: =IF(K10<>0,(K18-K10)/K10,0) -> 0.19195577
A23: GAP Interpretation: positive = marketing needed to reach target
A24: 4. REVENUE MIX (% of Total)
A25: Physio Clinic | B25: =IF(B10<>0,B5/B10,0) -> 0.56890598 | C25: =IF(C10<>0,C5/C10,0) -> 0.57105853 | D25: =IF(D10<>0,D5/D10,0) -> 0.57089891 | E25: =IF(E10<>0,E5/E10,0) -> 0.56995476 | F25: =IF(F10<>0,F5/F10,0) -> 0.57097661 | G25: =IF(G10<>0,G5/G10,0) -> 0.57449112 | H25: =IF(H10<>0,H5/H10,0) -> 0.58743282 | I25: =IF(I10<>0,I5/I10,0) -> 0.58743282 | ... K25: =IF(K10<>0,K5/K10,0) -> 0.58743282
A26: Dental Clinic | B26: =IF(B10<>0,B6/B10,0) -> 0.1534296 | C26: =IF(C10<>0,C6/C10,0) -> 0.15073474 | D26: =IF(D10<>0,D6/D10,0) -> 0.15012177 | E26: =IF(E10<>0,E6/E10,0) -> 0.15201614 | F26: =IF(F10<>0,F6/F10,0) -> 0.15052778 | G26: =IF(G10<>0,G6/G10,0) -> 0.15241439 | H26: =IF(H10<>0,H6/H10,0) -> 0.15023223 | I26: =IF(I10<>0,I6/I10,0) -> 0.15023223 | ... K26: =IF(K10<>0,K6/K10,0) -> 0.15023223
A27: Polyclinic | B27: =IF(B10<>0,B7/B10,0) -> 0.10673364 | C27: =IF(C10<>0,C7/C10,0) -> 0.10650062 | D27: =IF(D10<>0,D7/D10,0) -> 0.10722984 | E27: =IF(E10<>0,E7/E10,0) -> 0.10668142 | F27: =IF(F10<>0,F7/F10,0) -> 0.10685669 | G27: =IF(G10<>0,G7/G10,0) -> 0.10771708 | H27: =IF(H10<>0,H7/H10,0) -> 0.11001143 | I27: =IF(I10<>0,I7/I10,0) -> 0.11001143 | ... K27: =IF(K10<>0,K7/K10,0) -> 0.11001143
A28: Cosmetology | B28: =IF(B10<>0,B8/B10,0) -> 0.17093078 | C28: =IF(C10<>0,C8/C10,0) -> 0.1717061 | D28: =IF(D10<>0,D8/D10,0) -> 0.17174948 | E28: =IF(E10<>0,E8/E10,0) -> 0.17134767 | F28: =IF(F10<>0,F8/F10,0) -> 0.17163892 | G28: =IF(G10<>0,G8/G10,0) -> 0.16537741 | H28: =IF(H10<>0,H8/H10,0) -> 0.15232352 | I28: =IF(I10<>0,I8/I10,0) -> 0.15232352 | ... K28: =IF(K10<>0,K8/K10,0) -> 0.15232352
A29: Wellness Packages | B29: =IF(B10<>0,B9/B10,0) -> 0 | C29: =IF(C10<>0,C9/C10,0) -> 0 | D29: =IF(D10<>0,D9/D10,0) -> 0 | E29: =IF(E10<>0,E9/E10,0) -> 0 | F29: =IF(F10<>0,F9/F10,0) -> 0 | G29: =IF(G10<>0,G9/G10,0) -> 0 | H29: =IF(H10<>0,H9/H10,0) -> 0 | I29: =IF(I10<>0,I9/I10,0) -> 0 | ... K29: =IF(K10<>0,K9/K10,0) -> 0
A31: 5. REVENUE PER SQM
A32: Total Revenue / sqm | B32: =B10/Assumptions!$D$9 -> 12330.968 | C32: =C10/Assumptions!$D$9 -> 20204.516 | D32: =D10/Assumptions!$D$9 -> 28796.03 | E32: =E10/Assumptions!$D$9 -> 33448.738 | F32: =F10/Assumptions!$D$9 -> 38289.471 | G32: =G10/Assumptions!$D$9 -> 44596.608 | H32: =H10/Assumptions!$D$9 -> 50355.207 | I32: =I10/Assumptions!$D$9 -> 52369.415 | ... K32: =K10/Assumptions!$D$9 -> 56642.76
A34: 6. PATIENT ACQUISITION EFFICIENCY
A35: Metric | B35: Y1 | C35: Y2 | D35: Y3 | E35: Y4 | F35: Y5 | G35: Y6 | H35: Y7 | I35: Y8 | J35: Y9 | K35: Y10
A36: Organic Revenue (cohort + referral) | B36: =Revenue!B13*Assumptions!B243 -> 3025904.5 | C36: =Revenue!C13*Assumptions!C243 -> 8484197 | D36: =Revenue!D13*Assumptions!D243 -> 12126220 | E36: =Revenue!E13*Assumptions!E243 -> 16256968 | F36: =Revenue!F13*Assumptions!F243 -> 18886095 | G36: =Revenue!G13*Assumptions!G243 -> 21709966 | H36: =Revenue!H13*Assumptions!H243 -> 24707872 | I36: =Revenue!I13*Assumptions!I243 -> 27841719 | ... K36: =Revenue!K13*Assumptions!K243 -> 31977613
A37: Full Capacity Revenue | B37: =B18 -> 25484000 | C37: =C18 -> 18799392 | D37: =D18 -> 20445674 | E37: =E18 -> 25566803 | F37: =F18 -> 29063850 | G37: =G18 -> 32023341 | H37: =H18 -> 36216351 | I37: =I18 -> 38701657 | ... K37: =K18 -> 41859712
A38: Revenue GAP to Full Capacity | B38: =B37-B36 -> 22458096 | C38: =C37-C36 -> 10315195 | D38: =D37-D36 -> 8319453.9 | E38: =E37-E36 -> 9309834.7 | F38: =F37-F36 -> 10177755 | G38: =G37-G36 -> 10313374 | H38: =H37-H36 -> 11508479 | I38: =I37-I36 -> 10859938 | ... K38: =K37-K36 -> 9882098.6
A39: GAP as % of Full Capacity | B39: =IF(B37<>0,B38/B37,0) -> 0.88126258 | C39: =IF(C37<>0,C38/C37,0) -> 0.54869832 | D39: =IF(D37<>0,D38/D37,0) -> 0.40690534 | E39: =IF(E37<>0,E38/E37,0) -> 0.36413762 | F39: =IF(F37<>0,F38/F37,0) -> 0.35018605 | G39: =IF(G37<>0,G38/G37,0) -> 0.32205804 | H39: =IF(H37<>0,H38/H37,0) -> 0.31777024 | I39: =IF(I37<>0,I38/I37,0) -> 0.28060653 | ... K39: =IF(K37<>0,K38/K37,0) -> 0.2360766
A40: Marketing Spend (from PA) | B40: ='Patient Acquisition'!B95 -> 1529040 | C40: ='Patient Acquisition'!C95 -> 1989935.4 | D40: ='Patient Acquisition'!D95 -> 2585251.6 | E40: ='Patient Acquisition'!E95 -> 2297361.9 | F40: ='Patient Acquisition'!F95 -> 2437952.6 | G40: ='Patient Acquisition'!G95 -> 2774128.7 | H40: ='Patient Acquisition'!H95 -> 3001678.3 | I40: ='Patient Acquisition'!I95 -> 2537580.1 | ... K40: ='Patient Acquisition'!K95 -> 2186690
A41: Marketing ROI (GAP Revenue ÷ Mkt Spend) | B41: =IF(B40>0,B38/B40,0) -> 14.68771 | C41: =IF(C40>0,C38/C40,0) -> 5.1836832 | D41: =IF(D40>0,D38/D40,0) -> 3.2180441 | E41: =IF(E40>0,E38/E40,0) -> 4.0524023 | F41: =IF(F40>0,F38/F40,0) -> 4.174714 | G41: =IF(G40>0,G38/G40,0) -> 3.7176986 | H41: =IF(H40>0,H38/H40,0) -> 3.8340147 | I41: =IF(I40>0,I38/I40,0) -> 4.2796433 | ... K41: =IF(K40>0,K38/K40,0) -> 4.5192043

Sheet Staffing Detail
A1: STAFFING DETAIL — Revenue Sharing Model
A3: Department | B3: Y1 | C3: Y2 | D3: Y3 | E3: Y4 | F3: Y5 | G3: Y6 | H3: Y7 | I3: Y8 | J3: Y9 | K3: Y10 | L3: Share %
A4: REVENUE SHARING RATES (% of department revenue)
A5: Physio Clinic | B5: =-(Assumptions!$B$54+Assumptions!$B$59*MAX(0,1-(1-1)/Assumptions!$B$60))*Revenue!B8 -> -1304820 | C5: =-(Assumptions!$B$54+Assumptions!$B$59*MAX(0,1-(2-1)/Assumptions!$B$60))*Revenue!C8 -> -2384512 | D5: =-(Assumptions!$B$54+Assumptions!$B$59*MAX(0,1-(3-1)/Assumptions!$B$60))*Revenue!D8 -> -3737274.1 | E5: =-(Assumptions!$B$54+Assumptions!$B$59*MAX(0,1-(4-1)/Assumptions!$B$60))*Revenue!E8 -> -4727938.4 | F5: =-(Assumptions!$B$54+Assumptions!$B$59*MAX(0,1-(5-1)/Assumptions!$B$60))*Revenue!F8 -> -5421873.3 | G5: =-(Assumptions!$B$54+Assumptions!$B$59*MAX(0,1-(6-1)/Assumptions!$B$60))*Revenue!G8 -> -6353848.1 | H5: =-(Assumptions!$B$54+Assumptions!$B$59*MAX(0,1-(7-1)/Assumptions!$B$60))*Revenue!H8 -> -7335914.8 | I5: =-(Assumptions!$B$54+Assumptions!$B$59*MAX(0,1-(8-1)/Assumptions!$B$60))*Revenue!I8 -> -7629351.4 | J5: =-(Assumptions!$B$54+Assumptions!$B$59*MAX(0,1-(9-1)/Assumptions!$B$60))*Revenue!J8 -> -7934525.4 | K5: =-(Assumptions!$B$54+Assumptions!$B$59*MAX(0,1-(10-1)/Assumptions!$B$60))*Revenue!K8 -> -8251906.4 | L5: =Assumptions!$B54 -> 0.4
A6: Dental Clinic | B6: =-(Assumptions!$B$55+Assumptions!$B$59*MAX(0,1-(1-1)/Assumptions!$B$60))*Revenue!B9 -> -351900 | C6: =-(Assumptions!$B$55+Assumptions!$B$59*MAX(0,1-(2-1)/Assumptions!$B$60))*Revenue!C9 -> -629408 | D6: =-(Assumptions!$B$55+Assumptions!$B$59*MAX(0,1-(3-1)/Assumptions!$B$60))*Revenue!D9 -> -982741.76 | E6: =-(Assumptions!$B$55+Assumptions!$B$59*MAX(0,1-(4-1)/Assumptions!$B$60))*Revenue!E9 -> -1261017.5 | F6: =-(Assumptions!$B$55+Assumptions!$B$59*MAX(0,1-(5-1)/Assumptions!$B$60))*Revenue!F9 -> -1429380 | G6: =-(Assumptions!$B$55+Assumptions!$B$59*MAX(0,1-(6-1)/Assumptions!$B$60))*Revenue!G9 -> -1685696.9 | H6: =-(Assumptions!$B$55+Assumptions!$B$59*MAX(0,1-(7-1)/Assumptions!$B$60))*Revenue!H9 -> -1876113.8 | I6: =-(Assumptions!$B$55+Assumptions!$B$59*MAX(0,1-(8-1)/Assumptions!$B$60))*Revenue!I9 -> -1951158.4 | J6: =-(Assumptions!$B$55+Assumptions!$B$59*MAX(0,1-(9-1)/Assumptions!$B$60))*Revenue!J9 -> -2029204.7 | K6: =-(Assumptions!$B$55+Assumptions!$B$59*MAX(0,1-(10-1)/Assumptions!$B$60))*Revenue!K9 -> -2110372.9 | L6: =Assumptions!$B55 -> 0.4
A7: Polyclinic (GP+Gynecologist) | B7: =-(Assumptions!$B$57+Assumptions!$B$59*MAX(0,1-(1-1)/Assumptions!$B$60))*Revenue!B10 -> -244800 | C7: =-(Assumptions!$B$57+Assumptions!$B$59*MAX(0,1-(2-1)/Assumptions!$B$60))*Revenue!C10 -> -444704 | D7: =-(Assumptions!$B$57+Assumptions!$B$59*MAX(0,1-(3-1)/Assumptions!$B$60))*Revenue!D10 -> -701958.4 | E7: =-(Assumptions!$B$57+Assumptions!$B$59*MAX(0,1-(4-1)/Assumptions!$B$60))*Revenue!E10 -> -884953.01 | F7: =-(Assumptions!$B$57+Assumptions!$B$59*MAX(0,1-(5-1)/Assumptions!$B$60))*Revenue!F10 -> -1014688.5 | G7: =-(Assumptions!$B$57+Assumptions!$B$59*MAX(0,1-(6-1)/Assumptions!$B$60))*Revenue!G10 -> -1191346.5 | H7: =-(Assumptions!$B$57+Assumptions!$B$59*MAX(0,1-(7-1)/Assumptions!$B$60))*Revenue!H10 -> -1373832.8 | I7: =-(Assumptions!$B$57+Assumptions!$B$59*MAX(0,1-(8-1)/Assumptions!$B$60))*Revenue!I10 -> -1428786.1 | J7: =-(Assumptions!$B$57+Assumptions!$B$59*MAX(0,1-(9-1)/Assumptions!$B$60))*Revenue!J10 -> -1485937.5 | K7: =-(Assumptions!$B$57+Assumptions!$B$59*MAX(0,1-(10-1)/Assumptions!$B$60))*Revenue!K10 -> -1545375 | L7: =Assumptions!$B57 -> 0.4
A8: Cosmetology / Beauty | B8: =-(Assumptions!$B$56+Assumptions!$B$59*MAX(0,1-(1-1)/Assumptions!$B$60))*Revenue!B11 -> -392040 | C8: =-(Assumptions!$B$56+Assumptions!$B$59*MAX(0,1-(2-1)/Assumptions!$B$60))*Revenue!C11 -> -716976 | D8: =-(Assumptions!$B$56+Assumptions!$B$59*MAX(0,1-(3-1)/Assumptions!$B$60))*Revenue!D11 -> -1124323.2 | E8: =-(Assumptions!$B$56+Assumptions!$B$59*MAX(0,1-(4-1)/Assumptions!$B$60))*Revenue!E11 -> -1421378.2 | F8: =-(Assumptions!$B$56+Assumptions!$B$59*MAX(0,1-(5-1)/Assumptions!$B$60))*Revenue!F11 -> -1629846.9 | G8: =-(Assumptions!$B$56+Assumptions!$B$59*MAX(0,1-(6-1)/Assumptions!$B$60))*Revenue!G11 -> -1829067.3 | H8: =-(Assumptions!$B$56+Assumptions!$B$59*MAX(0,1-(7-1)/Assumptions!$B$60))*Revenue!H11 -> -1902230 | I8: =-(Assumptions!$B$56+Assumptions!$B$59*MAX(0,1-(8-1)/Assumptions!$B$60))*Revenue!I11 -> -1978319.2 | J8: =-(Assumptions!$B$56+Assumptions!$B$59*MAX(0,1-(9-1)/Assumptions!$B$60))*Revenue!J11 -> -2057452 | K8: =-(Assumptions!$B$56+Assumptions!$B$59*MAX(0,1-(10-1)/Assumptions!$B$60))*Revenue!K11 -> -2139750 | L8: =Assumptions!$B56 -> 0.4
A9: TOTAL SALARY COST | B9: =SUM(B5:B8) -> -2293560 | C9: =SUM(C5:C8) -> -4175600 | D9: =SUM(D5:D8) -> -6546297.5 | E9: =SUM(E5:E8) -> -8295287.1 | F9: =SUM(F5:F8) -> -9495788.7 | G9: =SUM(G5:G8) -> -11059959 | H9: =SUM(H5:H8) -> -12488091 | I9: =SUM(I5:I8) -> -12987615 | ... K9: =SUM(K5:K8) -> -14047404
A11: Cross-check: OpEx salary total | B11: =OpEx!B25 -> -2293560 | C11: =OpEx!C25 -> -4175600 | D11: =OpEx!D25 -> -6546297.5 | E11: =OpEx!E25 -> -8295287.1 | F11: =OpEx!F25 -> -9495788.7 | G11: =OpEx!G25 -> -11059959 | H11: =OpEx!H25 -> -12488091 | I11: =OpEx!I25 -> -12987615 | ... K11: =OpEx!K25 -> -14047404
A12: Difference (should be 0) | B12: =B9-B11 -> 0 | C12: =C9-C11 -> 0 | D12: =D9-D11 -> 0 | E12: =E9-E11 -> 0 | F12: =F9-F11 -> 0 | G12: =G9-G11 -> 0 | H12: =H9-H11 -> 0 | I12: =I9-I11 -> 0 | ... K12: =K9-K11 -> 0
A14: SALARY AS % OF TOTAL REVENUE
A15: Salary / Revenue | B15: =IF(Revenue!B13<>0,B9/Revenue!B13,0) -> -0.3 | C15: =IF(Revenue!C13<>0,C9/Revenue!C13,0) -> -0.33333333 | D15: =IF(Revenue!D13<>0,D9/Revenue!D13,0) -> -0.36666667 | E15: =IF(Revenue!E13<>0,E9/Revenue!E13,0) -> -0.4 | F15: =IF(Revenue!F13<>0,F9/Revenue!F13,0) -> -0.4 | G15: =IF(Revenue!G13<>0,G9/Revenue!G13,0) -> -0.4 | H15: =IF(Revenue!H13<>0,H9/Revenue!H13,0) -> -0.4 | I15: =IF(Revenue!I13<>0,I9/Revenue!I13,0) -> -0.4 | ... K15: =IF(Revenue!K13<>0,K9/Revenue!K13,0) -> -0.4
A16: FIXED STAFF (Salaried — not volume-dependent)
A17: Position | B17: Y1 | C17: Y2 | D17: Y3 | E17: Y4 | F17: Y5 | G17: Y6 | H17: Y7 | I17: Y8 | J17: Y9 | K17: Y10 | L17: Monthly AED
A18: Clinic Manager | B18: =-Assumptions!E140*(1+Assumptions!$B$130)^0 -> -180000 | C18: =-Assumptions!E140*(1+Assumptions!$B$130)^1 -> -187200 | D18: =-Assumptions!E140*(1+Assumptions!$B$130)^2 -> -194688 | E18: =-Assumptions!E140*(1+Assumptions!$B$130)^3 -> -202475.52 | F18: =-Assumptions!E140*(1+Assumptions!$B$130)^4 -> -210574.54 | G18: =-Assumptions!E140*(1+Assumptions!$B$130)^5 -> -218997.52 | H18: =-Assumptions!E140*(1+Assumptions!$B$130)^6 -> -227757.42 | I18: =-Assumptions!E140*(1+Assumptions!$B$130)^7 -> -236867.72 | J18: =-Assumptions!E140*(1+Assumptions!$B$130)^8 -> -246342.43 | K18: =-Assumptions!E140*(1+Assumptions!$B$130)^9 -> -256196.13 | L18: =Assumptions!B140 -> 15000
A19: Admin / Receptionist (×2) | B19: =-Assumptions!E141*(1+Assumptions!$B$130)^0 -> -168000 | C19: =-Assumptions!E141*(1+Assumptions!$B$130)^1 -> -174720 | D19: =-Assumptions!E141*(1+Assumptions!$B$130)^2 -> -181708.8 | E19: =-Assumptions!E141*(1+Assumptions!$B$130)^3 -> -188977.15 | F19: =-Assumptions!E141*(1+Assumptions!$B$130)^4 -> -196536.24 | G19: =-Assumptions!E141*(1+Assumptions!$B$130)^5 -> -204397.69 | H19: =-Assumptions!E141*(1+Assumptions!$B$130)^6 -> -212573.6 | I19: =-Assumptions!E141*(1+Assumptions!$B$130)^7 -> -221076.54 | J19: =-Assumptions!E141*(1+Assumptions!$B$130)^8 -> -229919.6 | K19: =-Assumptions!E141*(1+Assumptions!$B$130)^9 -> -239116.38 | L19: =Assumptions!B141 -> 7000
A20: Nurse | B20: =-Assumptions!E142*(1+Assumptions!$B$130)^0 -> -120000 | C20: =-Assumptions!E142*(1+Assumptions!$B$130)^1 -> -124800 | D20: =-Assumptions!E142*(1+Assumptions!$B$130)^2 -> -129792 | E20: =-Assumptions!E142*(1+Assumptions!$B$130)^3 -> -134983.68 | F20: =-Assumptions!E142*(1+Assumptions!$B$130)^4 -> -140383.03 | G20: =-Assumptions!E142*(1+Assumptions!$B$130)^5 -> -145998.35 | H20: =-Assumptions!E142*(1+Assumptions!$B$130)^6 -> -151838.28 | I20: =-Assumptions!E142*(1+Assumptions!$B$130)^7 -> -157911.81 | J20: =-Assumptions!E142*(1+Assumptions!$B$130)^8 -> -164228.29 | K20: =-Assumptions!E142*(1+Assumptions!$B$130)^9 -> -170797.42 | L20: =Assumptions!B142 -> 10000
A21: Head of Dept 1 | B21: =-IF(1>=2,Assumptions!E143*(1+Assumptions!$B$130)^0,0) -> 0 | C21: =-IF(2>=2,Assumptions!E143*(1+Assumptions!$B$130)^1,0) -> -62400 | D21: =-IF(3>=2,Assumptions!E143*(1+Assumptions!$B$130)^2,0) -> -64896 | E21: =-IF(4>=2,Assumptions!E143*(1+Assumptions!$B$130)^3,0) -> -67491.84 | F21: =-IF(5>=2,Assumptions!E143*(1+Assumptions!$B$130)^4,0) -> -70191.514 | G21: =-IF(6>=2,Assumptions!E143*(1+Assumptions!$B$130)^5,0) -> -72999.174 | H21: =-IF(7>=2,Assumptions!E143*(1+Assumptions!$B$130)^6,0) -> -75919.141 | I21: =-IF(8>=2,Assumptions!E143*(1+Assumptions!$B$130)^7,0) -> -78955.907 | J21: =-IF(9>=2,Assumptions!E143*(1+Assumptions!$B$130)^8,0) -> -82114.143 | K21: =-IF(10>=2,Assumptions!E143*(1+Assumptions!$B$130)^9,0) -> -85398.709 | L21: =Assumptions!B143 -> 5000
A22: Head of Dept 2 | B22: =-IF(1>=2,Assumptions!E144*(1+Assumptions!$B$130)^0,0) -> 0 | C22: =-IF(2>=2,Assumptions!E144*(1+Assumptions!$B$130)^1,0) -> -62400 | D22: =-IF(3>=2,Assumptions!E144*(1+Assumptions!$B$130)^2,0) -> -64896 | E22: =-IF(4>=2,Assumptions!E144*(1+Assumptions!$B$130)^3,0) -> -67491.84 | F22: =-IF(5>=2,Assumptions!E144*(1+Assumptions!$B$130)^4,0) -> -70191.514 | G22: =-IF(6>=2,Assumptions!E144*(1+Assumptions!$B$130)^5,0) -> -72999.174 | H22: =-IF(7>=2,Assumptions!E144*(1+Assumptions!$B$130)^6,0) -> -75919.141 | I22: =-IF(8>=2,Assumptions!E144*(1+Assumptions!$B$130)^7,0) -> -78955.907 | J22: =-IF(9>=2,Assumptions!E144*(1+Assumptions!$B$130)^8,0) -> -82114.143 | K22: =-IF(10>=2,Assumptions!E144*(1+Assumptions!$B$130)^9,0) -> -85398.709 | L22: =Assumptions!B144 -> 5000
A23: Cleaning | B23: =-Assumptions!E145*(1+Assumptions!$B$130)^0 -> -60000 | C23: =-Assumptions!E145*(1+Assumptions!$B$130)^1 -> -62400 | D23: =-Assumptions!E145*(1+Assumptions!$B$130)^2 -> -64896 | E23: =-Assumptions!E145*(1+Assumptions!$B$130)^3 -> -67491.84 | F23: =-Assumptions!E145*(1+Assumptions!$B$130)^4 -> -70191.514 | G23: =-Assumptions!E145*(1+Assumptions!$B$130)^5 -> -72999.174 | H23: =-Assumptions!E145*(1+Assumptions!$B$130)^6 -> -75919.141 | I23: =-Assumptions!E145*(1+Assumptions!$B$130)^7 -> -78955.907 | J23: =-Assumptions!E145*(1+Assumptions!$B$130)^8 -> -82114.143 | K23: =-Assumptions!E145*(1+Assumptions!$B$130)^9 -> -85398.709 | L23: =Assumptions!B145 -> 5000
A24: TOTAL Fixed Staff Cost | B24: =SUM(B18:B23) -> -528000 | C24: =SUM(C18:C23) -> -673920 | D24: =SUM(D18:D23) -> -700876.8 | E24: =SUM(E18:E23) -> -728911.87 | F24: =SUM(F18:F23) -> -758068.35 | G24: =SUM(G18:G23) -> -788391.08 | H24: =SUM(H18:H23) -> -819926.72 | I24: =SUM(I18:I23) -> -852723.79 | ... K24: =SUM(K18:K23) -> -922306.05
A26: TOTAL STAFFING COST RECONCILIATION
A27: Revenue-Sharing Staff | B27: =B9 -> -2293560 | C27: =C9 -> -4175600 | D27: =D9 -> -6546297.5 | E27: =E9 -> -8295287.1 | F27: =F9 -> -9495788.7 | G27: =G9 -> -11059959 | H27: =H9 -> -12488091 | I27: =I9 -> -12987615 | ... K27: =K9 -> -14047404
A28: Fixed Salaried Staff | B28: =B24 -> -528000 | C28: =C24 -> -673920 | D28: =D24 -> -700876.8 | E28: =E24 -> -728911.87 | F28: =F24 -> -758068.35 | G28: =G24 -> -788391.08 | H28: =H24 -> -819926.72 | I28: =I24 -> -852723.79 | ... K28: =K24 -> -922306.05
A29: GRAND TOTAL Staff Cost | B29: =B27+B28 -> -2821560 | C29: =C27+C28 -> -4849520 | D29: =D27+D28 -> -7247174.3 | E29: =E27+E28 -> -9024198.9 | F29: =F27+F28 -> -10253857 | G29: =G27+G28 -> -11848350 | H29: =H27+H28 -> -13308018 | I29: =I27+I28 -> -13840339 | ... K29: =K27+K28 -> -14969710

Sheet OpEx
A1: OPERATING EXPENSES (10 YEARS)
A2: Salaries and Rent adjusted by inflation annually
A4: Item | B4: Year 1 | C4: Year 2 | D4: Year 3 | E4: Year 4 | F4: Year 5 | G4: Year 6 | H4: Year 7 | I4: Year 8 | J4: Year 9 | K4: Year 10
A5: Inflation Factor | B5: =Revenue!B5 -> 1 | C5: =Revenue!C5 -> 1.04 | D5: =Revenue!D5 -> 1.0816 | E5: =Revenue!E5 -> 1.124864 | F5: =Revenue!F5 -> 1.1698586 | G5: =Revenue!G5 -> 1.2166529 | H5: =Revenue!H5 -> 1.265319 | I5: =Revenue!I5 -> 1.3159318 | ... K5: =Revenue!K5 -> 1.4233118
A7: COGS
A8: COGS Direct Materials — Physio | B8: =-Assumptions!$B$63*Revenue!B8 -> -217470 | C8: =-Assumptions!$B$63*Revenue!C8 -> -357676.8 | D8: =-Assumptions!$B$63*Revenue!D8 -> -509628.29 | E8: =-Assumptions!$B$63*Revenue!E8 -> -590992.3 | F8: =-Assumptions!$B$63*Revenue!F8 -> -677734.16 | G8: =-Assumptions!$B$63*Revenue!G8 -> -794231.01 | H8: =-Assumptions!$B$63*Revenue!H8 -> -916989.35 | I8: =-Assumptions!$B$63*Revenue!I8 -> -953668.92 | ... K8: =-Assumptions!$B$63*Revenue!K8 -> -1031488.3
A9: COGS Direct Materials — Polyclinic | B9: =-Assumptions!$B$64*Revenue!B10 -> -97920 | C9: =-Assumptions!$B$64*Revenue!C10 -> -160093.44 | D9: =-Assumptions!$B$64*Revenue!D10 -> -229731.84 | E9: =-Assumptions!$B$64*Revenue!E10 -> -265485.9 | F9: =-Assumptions!$B$64*Revenue!F10 -> -304406.56 | G9: =-Assumptions!$B$64*Revenue!G10 -> -357403.96 | H9: =-Assumptions!$B$64*Revenue!H10 -> -412149.83 | I9: =-Assumptions!$B$64*Revenue!I10 -> -428635.83 | ... K9: =-Assumptions!$B$64*Revenue!K10 -> -463612.51
A10: COGS Direct Materials — Cosmetology | B10: =-Assumptions!$B$65*Revenue!B11 -> -261360 | C10: =-Assumptions!$B$65*Revenue!C11 -> -430185.6 | D10: =-Assumptions!$B$65*Revenue!D11 -> -613267.2 | E10: =-Assumptions!$B$65*Revenue!E11 -> -710689.08 | F10: =-Assumptions!$B$65*Revenue!F11 -> -814923.47 | G10: =-Assumptions!$B$65*Revenue!G11 -> -914533.65 | H10: =-Assumptions!$B$65*Revenue!H11 -> -951115 | I10: =-Assumptions!$B$65*Revenue!I11 -> -989159.6 | ... K10: =-Assumptions!$B$65*Revenue!K11 -> -1069875
A11: COGS Dental | B11: =-Assumptions!$B$62*Revenue!B9 -> -269790 | C11: =-Assumptions!$B$62*Revenue!C9 -> -434291.52 | D11: =-Assumptions!$B$62*Revenue!D9 -> -616447.1 | E11: =-Assumptions!$B$62*Revenue!E9 -> -725085.08 | F11: =-Assumptions!$B$62*Revenue!F9 -> -821893.49 | G11: =-Assumptions!$B$62*Revenue!G9 -> -969275.73 | H11: =-Assumptions!$B$62*Revenue!H9 -> -1078765.4 | I11: =-Assumptions!$B$62*Revenue!I9 -> -1121916.1 | ... K11: =-Assumptions!$B$62*Revenue!K9 -> -1213464.4
A12: COGS Orthotics | B12: =-Assumptions!$B$66*'Price List'!D10*12*'Price List'!C10*Revenue!B5*Revenue!B6 -> -12000 | C12: =-Assumptions!$B$66*'Price List'!E10*12*'Price List'!C10*Revenue!C5*Revenue!C6 -> -17472 | D12: =-Assumptions!$B$66*'Price List'!F10*12*'Price List'!C10*Revenue!D5*Revenue!D6 -> -25958.4 | E12: =-Assumptions!$B$66*'Price List'!G10*12*'Price List'!C10*Revenue!E5*Revenue!E6 -> -29696.41 | F12: =-Assumptions!$B$66*'Price List'!H10*12*'Price List'!C10*Revenue!F5*Revenue!F6 -> -33691.927 | G12: =-Assumptions!$B$66*'Price List'!I10*12*'Price List'!C10*Revenue!G5*Revenue!G6 -> -40879.538 | H12: =-Assumptions!$B$66*'Price List'!J10*12*'Price List'!C10*Revenue!H5*Revenue!H6 -> -48588.25 | I12: =-Assumptions!$B$66*'Price List'!K10*12*'Price List'!C10*Revenue!I5*Revenue!I6 -> -50531.78 | J12: =-Assumptions!$B$66*'Price List'!L10*12*'Price List'!C10*Revenue!J5*Revenue!J6 -> -52553.052 | K12: =-Assumptions!$B$66*'Price List'!M10*12*'Price List'!C10*Revenue!K5*Revenue!K6 -> -54655.174
A13: COGS Injections | B13: =-Assumptions!$B$67*'Price List'!D9*12*'Price List'!C9*Revenue!B5*Revenue!B6 -> -18900 | C13: =-Assumptions!$B$67*'Price List'!E9*12*'Price List'!C9*Revenue!C5*Revenue!C6 -> -32760 | D13: =-Assumptions!$B$67*'Price List'!F9*12*'Price List'!C9*Revenue!D5*Revenue!D6 -> -45427.2 | E13: =-Assumptions!$B$67*'Price List'!G9*12*'Price List'!C9*Revenue!E5*Revenue!E6 -> -54330.931 | F13: =-Assumptions!$B$67*'Price List'!H9*12*'Price List'!C9*Revenue!F5*Revenue!F6 -> -61417.574 | G13: =-Assumptions!$B$67*'Price List'!I9*12*'Price List'!C9*Revenue!G5*Revenue!G6 -> -71539.191 | H13: =-Assumptions!$B$67*'Price List'!J9*12*'Price List'!C9*Revenue!H5*Revenue!H6 -> -82372.268 | I13: =-Assumptions!$B$67*'Price List'!K9*12*'Price List'!C9*Revenue!I5*Revenue!I6 -> -85667.159 | J13: =-Assumptions!$B$67*'Price List'!L9*12*'Price List'!C9*Revenue!J5*Revenue!J6 -> -89093.845 | K13: =-Assumptions!$B$67*'Price List'!M9*12*'Price List'!C9*Revenue!K5*Revenue!K6 -> -92657.599
A14: COGS Selling (Acquiring) | B14: =-Assumptions!$B$68*Revenue!B13 -> -152904 | C14: =-Assumptions!$B$68*Revenue!C13 -> -250536 | D14: =-Assumptions!$B$68*Revenue!D13 -> -357070.77 | E14: =-Assumptions!$B$68*Revenue!E13 -> -414764.35 | F14: =-Assumptions!$B$68*Revenue!F13 -> -474789.44 | G14: =-Assumptions!$B$68*Revenue!G13 -> -552997.94 | H14: =-Assumptions!$B$68*Revenue!H13 -> -624404.57 | I14: =-Assumptions!$B$68*Revenue!I13 -> -649380.75 | ... K14: =-Assumptions!$B$68*Revenue!K13 -> -702370.22
A15: COGS Selling (Returns) | B15: =-Assumptions!$B$69*Revenue!B13 -> -76452 | C15: =-Assumptions!$B$69*Revenue!C13 -> -125268 | D15: =-Assumptions!$B$69*Revenue!D13 -> -178535.39 | E15: =-Assumptions!$B$69*Revenue!E13 -> -207382.18 | F15: =-Assumptions!$B$69*Revenue!F13 -> -237394.72 | G15: =-Assumptions!$B$69*Revenue!G13 -> -276498.97 | H15: =-Assumptions!$B$69*Revenue!H13 -> -312202.28 | I15: =-Assumptions!$B$69*Revenue!I13 -> -324690.38 | ... K15: =-Assumptions!$B$69*Revenue!K13 -> -351185.11
A16: TOTAL COGS | B16: =SUM(B8:B15) -> -1106796 | C16: =SUM(C8:C15) -> -1808283.4 | D16: =SUM(D8:D15) -> -2576066.2 | E16: =SUM(E8:E15) -> -2998426.2 | F16: =SUM(F8:F15) -> -3426251.3 | G16: =SUM(G8:G15) -> -3977360 | H16: =SUM(H8:H15) -> -4426587 | I16: =SUM(I8:I15) -> -4603650.5 | ... K16: =SUM(K8:K15) -> -4979308.4
A18: Marketing | B18: =IF(Assumptions!$B$126=1,-'Patient Acquisition'!B95,-Assumptions!$B$71*Revenue!B13) -> -1529040 | C18: =IF(Assumptions!$B$126=1,-'Patient Acquisition'!C95,-Assumptions!$B$71*Revenue!C13) -> -1989935.4 | D18: =IF(Assumptions!$B$126=1,-'Patient Acquisition'!D95,-Assumptions!$B$71*Revenue!D13) -> -2585251.6 | E18: =IF(Assumptions!$B$126=1,-'Patient Acquisition'!E95,-Assumptions!$B$71*Revenue!E13) -> -2297361.9 | F18: =IF(Assumptions!$B$126=1,-'Patient Acquisition'!F95,-Assumptions!$B$71*Revenue!F13) -> -2437952.6 | G18: =IF(Assumptions!$B$126=1,-'Patient Acquisition'!G95,-Assumptions!$B$71*Revenue!G13) -> -2774128.7 | H18: =IF(Assumptions!$B$126=1,-'Patient Acquisition'!H95,-Assumptions!$B$71*Revenue!H13) -> -3001678.3 | I18: =IF(Assumptions!$B$126=1,-'Patient Acquisition'!I95,-Assumptions!$B$71*Revenue!I13) -> -2537580.1 | ... K18: =IF(Assumptions!$B$126=1,-'Patient Acquisition'!K95,-Assumptions!$B$71*Revenue!K13) -> -2186690
A19: ↳ PA model: GAP fill coverage (%) | B19: =IF(SUM(Assumptions!B234:M234)>0,ABS(B18)/SUM(Assumptions!B234:M234),1) -> 3.8229186 | C19: =IF(B19>0,B19*Assumptions!C242/Assumptions!B242,1) -> 8.4912209 | D19: =IF(B19>0,B19*Assumptions!D242/Assumptions!B242,1) -> 11.127476 | E19: =IF(B19>0,B19*Assumptions!E242/Assumptions!B242,1) -> 10.336388 | F19: =IF(B19>0,B19*Assumptions!F242/Assumptions!B242,1) -> 10.408585 | G19: =IF(B19>0,B19*Assumptions!G242/Assumptions!B242,1) -> 11.002736 | H19: =IF(B19>0,B19*Assumptions!H242/Assumptions!B242,1) -> 10.985129 | I19: =IF(B19>0,B19*Assumptions!I242/Assumptions!B242,1) -> 10.690885 | J19: =IF(B19>0,B19*Assumptions!J242/Assumptions!B242,1) -> 10.690885 | K19: =IF(B19>0,B19*Assumptions!K242/Assumptions!B242,1) -> 10.690885
A20: ↳ PA model: full GAP budget (AED) | B20: =-SUM(Assumptions!B234:M234) -> -399966.67 | C20: =B20*Assumptions!C242/Assumptions!B242*(1+Assumptions!$B$47)^1 -> -923915.45 | D20: =B20*Assumptions!D242/Assumptions!B242*(1+Assumptions!$B$47)^2 -> -1259192.4 | E20: =B20*Assumptions!E242/Assumptions!B242*(1+Assumptions!$B$47)^3 -> -1216459.3 | F20: =B20*Assumptions!F242/Assumptions!B242*(1+Assumptions!$B$47)^4 -> -1273954.2 | G20: =B20*Assumptions!G242/Assumptions!B242*(1+Assumptions!$B$47)^5 -> -1400542 | H20: =B20*Assumptions!H242/Assumptions!B242*(1+Assumptions!$B$47)^6 -> -1454232.9 | I20: =B20*Assumptions!I242/Assumptions!B242*(1+Assumptions!$B$47)^7 -> -1471891.4 | J20: =B20*Assumptions!J242/Assumptions!B242*(1+Assumptions!$B$47)^8 -> -1530767.1 | K20: =B20*Assumptions!K242/Assumptions!B242*(1+Assumptions!$B$47)^9 -> -1591997.8
A21: Physio Clinic | B21: =-(Assumptions!$B$54+Assumptions!$B$59*MAX(0,1-(1-1)/Assumptions!$B$60))*Revenue!B8 -> -1304820 | C21: =-(Assumptions!$B$54+Assumptions!$B$59*MAX(0,1-(2-1)/Assumptions!$B$60))*Revenue!C8 -> -2384512 | D21: =-(Assumptions!$B$54+Assumptions!$B$59*MAX(0,1-(3-1)/Assumptions!$B$60))*Revenue!D8 -> -3737274.1 | E21: =-(Assumptions!$B$54+Assumptions!$B$59*MAX(0,1-(4-1)/Assumptions!$B$60))*Revenue!E8 -> -4727938.4 | F21: =-(Assumptions!$B$54+Assumptions!$B$59*MAX(0,1-(5-1)/Assumptions!$B$60))*Revenue!F8 -> -5421873.3 | G21: =-(Assumptions!$B$54+Assumptions!$B$59*MAX(0,1-(6-1)/Assumptions!$B$60))*Revenue!G8 -> -6353848.1 | H21: =-(Assumptions!$B$54+Assumptions!$B$59*MAX(0,1-(7-1)/Assumptions!$B$60))*Revenue!H8 -> -7335914.8 | I21: =-(Assumptions!$B$54+Assumptions!$B$59*MAX(0,1-(8-1)/Assumptions!$B$60))*Revenue!I8 -> -7629351.4 | J21: =-(Assumptions!$B$54+Assumptions!$B$59*MAX(0,1-(9-1)/Assumptions!$B$60))*Revenue!J8 -> -7934525.4 | K21: =-(Assumptions!$B$54+Assumptions!$B$59*MAX(0,1-(10-1)/Assumptions!$B$60))*Revenue!K8 -> -8251906.4
A22: Dental Clinic | B22: =-(Assumptions!$B$55+Assumptions!$B$59*MAX(0,1-(1-1)/Assumptions!$B$60))*Revenue!B9 -> -351900 | C22: =-(Assumptions!$B$55+Assumptions!$B$59*MAX(0,1-(2-1)/Assumptions!$B$60))*Revenue!C9 -> -629408 | D22: =-(Assumptions!$B$55+Assumptions!$B$59*MAX(0,1-(3-1)/Assumptions!$B$60))*Revenue!D9 -> -982741.76 | E22: =-(Assumptions!$B$55+Assumptions!$B$59*MAX(0,1-(4-1)/Assumptions!$B$60))*Revenue!E9 -> -1261017.5 | F22: =-(Assumptions!$B$55+Assumptions!$B$59*MAX(0,1-(5-1)/Assumptions!$B$60))*Revenue!F9 -> -1429380 | G22: =-(Assumptions!$B$55+Assumptions!$B$59*MAX(0,1-(6-1)/Assumptions!$B$60))*Revenue!G9 -> -1685696.9 | H22: =-(Assumptions!$B$55+Assumptions!$B$59*MAX(0,1-(7-1)/Assumptions!$B$60))*Revenue!H9 -> -1876113.8 | I22: =-(Assumptions!$B$55+Assumptions!$B$59*MAX(0,1-(8-1)/Assumptions!$B$60))*Revenue!I9 -> -1951158.4 | J22: =-(Assumptions!$B$55+Assumptions!$B$59*MAX(0,1-(9-1)/Assumptions!$B$60))*Revenue!J9 -> -2029204.7 | K22: =-(Assumptions!$B$55+Assumptions!$B$59*MAX(0,1-(10-1)/Assumptions!$B$60))*Revenue!K9 -> -2110372.9
A23: Polyclinic | B23: =-(Assumptions!$B$57+Assumptions!$B$59*MAX(0,1-(1-1)/Assumptions!$B$60))*Revenue!B10 -> -244800 | C23: =-(Assumptions!$B$57+Assumptions!$B$59*MAX(0,1-(2-1)/Assumptions!$B$60))*Revenue!C10 -> -444704 | D23: =-(Assumptions!$B$57+Assumptions!$B$59*MAX(0,1-(3-1)/Assumptions!$B$60))*Revenue!D10 -> -701958.4 | E23: =-(Assumptions!$B$57+Assumptions!$B$59*MAX(0,1-(4-1)/Assumptions!$B$60))*Revenue!E10 -> -884953.01 | F23: =-(Assumptions!$B$57+Assumptions!$B$59*MAX(0,1-(5-1)/Assumptions!$B$60))*Revenue!F10 -> -1014688.5 | G23: =-(Assumptions!$B$57+Assumptions!$B$59*MAX(0,1-(6-1)/Assumptions!$B$60))*Revenue!G10 -> -1191346.5 | H23: =-(Assumptions!$B$57+Assumptions!$B$59*MAX(0,1-(7-1)/Assumptions!$B$60))*Revenue!H10 -> -1373832.8 | I23: =-(Assumptions!$B$57+Assumptions!$B$59*MAX(0,1-(8-1)/Assumptions!$B$60))*Revenue!I10 -> -1428786.1 | J23: =-(Assumptions!$B$57+Assumptions!$B$59*MAX(0,1-(9-1)/Assumptions!$B$60))*Revenue!J10 -> -1485937.5 | K23: =-(Assumptions!$B$57+Assumptions!$B$59*MAX(0,1-(10-1)/Assumptions!$B$60))*Revenue!K10 -> -1545375
A24: Cosmetology / Beauty | B24: =-(Assumptions!$B$56+Assumptions!$B$59*MAX(0,1-(1-1)/Assumptions!$B$60))*Revenue!B11 -> -392040 | C24: =-(Assumptions!$B$56+Assumptions!$B$59*MAX(0,1-(2-1)/Assumptions!$B$60))*Revenue!C11 -> -716976 | D24: =-(Assumptions!$B$56+Assumptions!$B$59*MAX(0,1-(3-1)/Assumptions!$B$60))*Revenue!D11 -> -1124323.2 | E24: =-(Assumptions!$B$56+Assumptions!$B$59*MAX(0,1-(4-1)/Assumptions!$B$60))*Revenue!E11 -> -1421378.2 | F24: =-(Assumptions!$B$56+Assumptions!$B$59*MAX(0,1-(5-1)/Assumptions!$B$60))*Revenue!F11 -> -1629846.9 | G24: =-(Assumptions!$B$56+Assumptions!$B$59*MAX(0,1-(6-1)/Assumptions!$B$60))*Revenue!G11 -> -1829067.3 | H24: =-(Assumptions!$B$56+Assumptions!$B$59*MAX(0,1-(7-1)/Assumptions!$B$60))*Revenue!H11 -> -1902230 | I24: =-(Assumptions!$B$56+Assumptions!$B$59*MAX(0,1-(8-1)/Assumptions!$B$60))*Revenue!I11 -> -1978319.2 | J24: =-(Assumptions!$B$56+Assumptions!$B$59*MAX(0,1-(9-1)/Assumptions!$B$60))*Revenue!J11 -> -2057452 | K24: =-(Assumptions!$B$56+Assumptions!$B$59*MAX(0,1-(10-1)/Assumptions!$B$60))*Revenue!K11 -> -2139750
A25: TOTAL SALARY | B25: =SUM(B21:B24) -> -2293560 | C25: =SUM(C21:C24) -> -4175600 | D25: =SUM(D21:D24) -> -6546297.5 | E25: =SUM(E21:E24) -> -8295287.1 | F25: =SUM(F21:F24) -> -9495788.7 | G25: =SUM(G21:G24) -> -11059959 | H25: =SUM(H21:H24) -> -12488091 | I25: =SUM(I21:I24) -> -12987615 | ... K25: =SUM(K21:K24) -> -14047404
A26: Fixed Staff Salaries | B26: ='Staffing Detail'!B24 -> -528000 | C26: ='Staffing Detail'!C24 -> -673920 | D26: ='Staffing Detail'!D24 -> -700876.8 | E26: ='Staffing Detail'!E24 -> -728911.87 | F26: ='Staffing Detail'!F24 -> -758068.35 | G26: ='Staffing Detail'!G24 -> -788391.08 | H26: ='Staffing Detail'!H24 -> -819926.72 | I26: ='Staffing Detail'!I24 -> -852723.79 | ... K26: ='Staffing Detail'!K24 -> -922306.05
A27: Administrative | B27: =-Assumptions!$D$99*B5 -> -1538000 | C27: =-Assumptions!$D$99*C5 -> -1599520 | D27: =-Assumptions!$D$99*D5 -> -1663500.8 | E27: =-Assumptions!$D$99*E5 -> -1730040.8 | F27: =-Assumptions!$D$99*F5 -> -1799242.5 | G27: =-Assumptions!$D$99*G5 -> -1871212.2 | H27: =-Assumptions!$D$99*H5 -> -1946060.7 | I27: =-Assumptions!$D$99*I5 -> -2023903.1 | ... K27: =-Assumptions!$D$99*K5 -> -2189053.6
A28: R&D | B28: =-Assumptions!$B$73*Revenue!B13 -> -152904 | C28: =-Assumptions!$B$73*Revenue!C13 -> -250536 | D28: =-Assumptions!$B$73*Revenue!D13 -> -357070.77 | E28: =-Assumptions!$B$73*Revenue!E13 -> -414764.35 | F28: =-Assumptions!$B$73*Revenue!F13 -> -474789.44 | G28: =-Assumptions!$B$73*Revenue!G13 -> -552997.94 | H28: =-Assumptions!$B$73*Revenue!H13 -> -624404.57 | I28: =-Assumptions!$B$73*Revenue!I13 -> -649380.75 | ... K28: =-Assumptions!$B$73*Revenue!K13 -> -702370.22
A29: Rent | B29: =-Assumptions!$D$9*Assumptions!$D$12*B5 -> -818400 | C29: =-Assumptions!$D$9*Assumptions!$D$12*C5 -> -851136 | D29: =-Assumptions!$D$9*Assumptions!$D$12*D5 -> -885181.44 | E29: =-Assumptions!$D$9*Assumptions!$D$12*E5 -> -920588.7 | F29: =-Assumptions!$D$9*Assumptions!$D$12*F5 -> -957412.25 | G29: =-Assumptions!$D$9*Assumptions!$D$12*G5 -> -995708.74 | H29: =-Assumptions!$D$9*Assumptions!$D$12*H5 -> -1035537.1 | I29: =-Assumptions!$D$9*Assumptions!$D$12*I5 -> -1076958.6 | ... K29: =-Assumptions!$D$9*Assumptions!$D$12*K5 -> -1164838.4
A30: Management Fee (if external) | B30: =-IF(Assumptions!$B$6=2,Revenue!B13*Assumptions!$B$123*(1+Assumptions!$B$124)^0,0) -> 0 | C30: =-IF(Assumptions!$B$6=2,Revenue!C13*Assumptions!$B$123*(1+Assumptions!$B$124)^1,0) -> 0 | D30: =-IF(Assumptions!$B$6=2,Revenue!D13*Assumptions!$B$123*(1+Assumptions!$B$124)^2,0) -> 0 | E30: =-IF(Assumptions!$B$6=2,Revenue!E13*Assumptions!$B$123*(1+Assumptions!$B$124)^3,0) -> 0 | F30: =-IF(Assumptions!$B$6=2,Revenue!F13*Assumptions!$B$123*(1+Assumptions!$B$124)^4,0) -> 0 | G30: =-IF(Assumptions!$B$6=2,Revenue!G13*Assumptions!$B$123*(1+Assumptions!$B$124)^5,0) -> 0 | H30: =-IF(Assumptions!$B$6=2,Revenue!H13*Assumptions!$B$123*(1+Assumptions!$B$124)^6,0) -> 0 | I30: =-IF(Assumptions!$B$6=2,Revenue!I13*Assumptions!$B$123*(1+Assumptions!$B$124)^7,0) -> 0 | J30: =-IF(Assumptions!$B$6=2,Revenue!J13*Assumptions!$B$123*(1+Assumptions!$B$124)^8,0) -> 0 | K30: =-IF(Assumptions!$B$6=2,Revenue!K13*Assumptions!$B$123*(1+Assumptions!$B$124)^9,0) -> 0
A31: TOTAL OPERATING COSTS | B31: =B16+B18+B25+B26+B27+B28+B29+B30 -> -7966700 | C31: =C16+C18+C25+C26+C27+C28+C29+C30 -> -11348931 | D31: =D16+D18+D25+D26+D27+D28+D29+D30 -> -15314245 | E31: =E16+E18+E25+E26+E27+E28+E29+E30 -> -17385381 | F31: =F16+F18+F25+F26+F27+F28+F29+F30 -> -19349505 | G31: =G16+G18+G25+G26+G27+G28+G29+G30 -> -22019758 | H31: =H16+H18+H25+H26+H27+H28+H29+H30 -> -24342286 | I31: =I16+I18+I25+I26+I27+I28+I29+I30 -> -24731812 | ... K31: =K16+K18+K25+K26+K27+K28+K29+K30 -> -26191971
A32: % of Revenue | B32: =B31/Revenue!B13 -> -1.0420525 | C32: =C31/Revenue!C13 -> -0.90597206 | D32: =D31/Revenue!D13 -> -0.85777086 | E32: =E31/Revenue!E13 -> -0.83832571 | F32: =F31/Revenue!F13 -> -0.81507732 | G32: =G31/Revenue!G13 -> -0.79637756 | H32: =H31/Revenue!H13 -> -0.77969595 | I32: =I31/Revenue!I13 -> -0.76170449 | ... K32: =K31/Revenue!K13 -> -0.74581667

Sheet P&L
A1: PROFIT & LOSS (10 YEARS)
A3: Item | B3: Year 1 | C3: Year 2 | D3: Year 3 | E3: Year 4 | F3: Year 5 | G3: Year 6 | H3: Year 7 | I3: Year 8 | J3: Year 9 | K3: Year 10
A4: Revenue | B4: =Revenue!B13 -> 7645200 | C4: =Revenue!C13 -> 12526800 | D4: =Revenue!D13 -> 17853539 | E4: =Revenue!E13 -> 20738218 | F4: =Revenue!F13 -> 23739472 | G4: =Revenue!G13 -> 27649897 | H4: =Revenue!H13 -> 31220228 | I4: =Revenue!I13 -> 32469038 | ... K4: =Revenue!K13 -> 35118511
A5: COGS | B5: =OpEx!B16 -> -1106796 | C5: =OpEx!C16 -> -1808283.4 | D5: =OpEx!D16 -> -2576066.2 | E5: =OpEx!E16 -> -2998426.2 | F5: =OpEx!F16 -> -3426251.3 | G5: =OpEx!G16 -> -3977360 | H5: =OpEx!H16 -> -4426587 | I5: =OpEx!I16 -> -4603650.5 | ... K5: =OpEx!K16 -> -4979308.4
A7: GROSS PROFIT | B7: =B4+B5 -> 6538404 | C7: =C4+C5 -> 10718517 | D7: =D4+D5 -> 15277472 | E7: =E4+E5 -> 17739791 | F7: =F4+F5 -> 20313220 | G7: =G4+G5 -> 23672537 | H7: =H4+H5 -> 26793641 | I7: =I4+I5 -> 27865387 | ... K7: =K4+K5 -> 30139203
A8: Gross Margin | B8: =B7/B4 -> 0.85522995 | C8: =C7/C4 -> 0.85564682 | D8: =D7/D4 -> 0.85571117 | E8: =E7/E4 -> 0.85541543 | F8: =F7/F4 -> 0.85567281 | G8: =G7/G4 -> 0.85615281 | H8: =H7/H4 -> 0.85821414 | I8: =I7/I4 -> 0.85821414 | ... K8: =K7/K4 -> 0.85821414
A10: Marketing | B10: =OpEx!B18 -> -1529040 | C10: =OpEx!C18 -> -1989935.4 | D10: =OpEx!D18 -> -2585251.6 | E10: =OpEx!E18 -> -2297361.9 | F10: =OpEx!F18 -> -2437952.6 | G10: =OpEx!G18 -> -2774128.7 | H10: =OpEx!H18 -> -3001678.3 | I10: =OpEx!I18 -> -2537580.1 | ... K10: =OpEx!K18 -> -2186690
A11: Salary | B11: =OpEx!B25 -> -2293560 | C11: =OpEx!C25 -> -4175600 | D11: =OpEx!D25 -> -6546297.5 | E11: =OpEx!E25 -> -8295287.1 | F11: =OpEx!F25 -> -9495788.7 | G11: =OpEx!G25 -> -11059959 | H11: =OpEx!H25 -> -12488091 | I11: =OpEx!I25 -> -12987615 | ... K11: =OpEx!K25 -> -14047404
A12: Fixed Staff | B12: =OpEx!B26 -> -528000 | C12: =OpEx!C26 -> -673920 | D12: =OpEx!D26 -> -700876.8 | E12: =OpEx!E26 -> -728911.87 | F12: =OpEx!F26 -> -758068.35 | G12: =OpEx!G26 -> -788391.08 | H12: =OpEx!H26 -> -819926.72 | I12: =OpEx!I26 -> -852723.79 | ... K12: =OpEx!K26 -> -922306.05
A13: CONTRIBUTION PROFIT | B13: =B7+B10+B11+B12 -> 2187804 | C13: =C7+C10+C11+C12 -> 3879061.2 | D13: =D7+D10+D11+D12 -> 5445046.5 | E13: =E7+E10+E11+E12 -> 6418230.6 | F13: =F7+F10+F11+F12 -> 7621410.8 | G13: =G7+G10+G11+G12 -> 9050058.5 | H13: =H7+H10+H11+H12 -> 10483945 | I13: =I7+I10+I11+I12 -> 11487468 | ... K13: =K7+K10+K11+K12 -> 12982802
A14: Contribution Margin | B14: =B13/B4 -> 0.28616701 | C14: =C13/C4 -> 0.30966099 | D14: =D13/D4 -> 0.30498416 | E14: =E13/E4 -> 0.30948805 | F14: =F13/F4 -> 0.32104382 | G14: =G13/G4 -> 0.32730894 | H14: =H13/H4 -> 0.33580616 | I14: =I13/I4 -> 0.35379762 | ... K14: =K13/K4 -> 0.36968544
A16: Administrative | B16: =OpEx!B27 -> -1538000 | C16: =OpEx!C27 -> -1599520 | D16: =OpEx!D27 -> -1663500.8 | E16: =OpEx!E27 -> -1730040.8 | F16: =OpEx!F27 -> -1799242.5 | G16: =OpEx!G27 -> -1871212.2 | H16: =OpEx!H27 -> -1946060.7 | I16: =OpEx!I27 -> -2023903.1 | ... K16: =OpEx!K27 -> -2189053.6
A17: R&D | B17: =OpEx!B28 -> -152904 | C17: =OpEx!C28 -> -250536 | D17: =OpEx!D28 -> -357070.77 | E17: =OpEx!E28 -> -414764.35 | F17: =OpEx!F28 -> -474789.44 | G17: =OpEx!G28 -> -552997.94 | H17: =OpEx!H28 -> -624404.57 | I17: =OpEx!I28 -> -649380.75 | ... K17: =OpEx!K28 -> -702370.22
A18: Rent | B18: =OpEx!B29 -> -818400 | C18: =OpEx!C29 -> -851136 | D18: =OpEx!D29 -> -885181.44 | E18: =OpEx!E29 -> -920588.7 | F18: =OpEx!F29 -> -957412.25 | G18: =OpEx!G29 -> -995708.74 | H18: =OpEx!H29 -> -1035537.1 | I18: =OpEx!I29 -> -1076958.6 | ... K18: =OpEx!K29 -> -1164838.4
A19: Management Fee | B19: =OpEx!B30 -> 0 | C19: =OpEx!C30 -> 0 | D19: =OpEx!D30 -> 0 | E19: =OpEx!E30 -> 0 | F19: =OpEx!F30 -> 0 | G19: =OpEx!G30 -> 0 | H19: =OpEx!H30 -> 0 | I19: =OpEx!I30 -> 0 | ... K19: =OpEx!K30 -> 0
A20: EBITDA | B20: =B13+B16+B17+B18+B19 -> -321500 | C20: =C13+C16+C17+C18+C19 -> 1177869.2 | D20: =D13+D16+D17+D18+D19 -> 2539293.5 | E20: =E13+E16+E17+E18+E19 -> 3352836.7 | F20: =F13+F16+F17+F18+F19 -> 4389966.6 | G20: =G13+G16+G17+G18+G19 -> 5630139.7 | H20: =H13+H16+H17+H18+H19 -> 6877942.8 | I20: =I13+I16+I17+I18+I19 -> 7737225.8 | ... K20: =K13+K16+K17+K18+K19 -> 8926540.1
A21: EBITDA Margin | B21: =B20/B4 -> -0.04205253 | C21: =C20/C4 -> 0.094027943 | D21: =D20/D4 -> 0.14222914 | E21: =E20/E4 -> 0.16167429 | F21: =F20/F4 -> 0.18492268 | G21: =G20/G4 -> 0.20362244 | H21: =H20/H4 -> 0.22030405 | I21: =I20/I4 -> 0.23829551 | ... K21: =K20/K4 -> 0.25418333
A23: Depreciation | B23: =IF(1<=Assumptions!$D$26,CapEx!$D$59/Assumptions!$D$26,0) -> 673714.29 | C23: =IF(2<=Assumptions!$D$26,CapEx!$D$59/Assumptions!$D$26,0) -> 673714.29 | D23: =IF(3<=Assumptions!$D$26,CapEx!$D$59/Assumptions!$D$26,0) -> 673714.29 | E23: =IF(4<=Assumptions!$D$26,CapEx!$D$59/Assumptions!$D$26,0) -> 673714.29 | F23: =IF(5<=Assumptions!$D$26,CapEx!$D$59/Assumptions!$D$26,0) -> 673714.29 | G23: =IF(6<=Assumptions!$D$26,CapEx!$D$59/Assumptions!$D$26,0) -> 673714.29 | H23: =IF(7<=Assumptions!$D$26,CapEx!$D$59/Assumptions!$D$26,0) -> 673714.29 | I23: =IF(8<=Assumptions!$D$26,CapEx!$D$59/Assumptions!$D$26,0) -> 0 | J23: =IF(9<=Assumptions!$D$26,CapEx!$D$59/Assumptions!$D$26,0) -> 0 | K23: =IF(10<=Assumptions!$D$26,CapEx!$D$59/Assumptions!$D$26,0) -> 0
A25: EBIT | B25: =B20-B23 -> -995214.29 | C25: =C20-C23 -> 504154.96 | D25: =D20-D23 -> 1865579.2 | E25: =E20-E23 -> 2679122.4 | F25: =F20-F23 -> 3716252.4 | G25: =G20-G23 -> 4956425.4 | H25: =H20-H23 -> 6204228.5 | I25: =I20-I23 -> 7737225.8 | ... K25: =K20-K23 -> 8926540.1
A26: Corporate Tax | B26: =-IF(B25>Assumptions!$B$50,(B25-Assumptions!$B$50)*Assumptions!$B$49,0) -> 0 | C26: =-IF(C25>Assumptions!$B$50,(C25-Assumptions!$B$50)*Assumptions!$B$49,0) -> -11623.946 | D26: =-IF(D25>Assumptions!$B$50,(D25-Assumptions!$B$50)*Assumptions!$B$49,0) -> -134152.13 | E26: =-IF(E25>Assumptions!$B$50,(E25-Assumptions!$B$50)*Assumptions!$B$49,0) -> -207371.02 | F26: =-IF(F25>Assumptions!$B$50,(F25-Assumptions!$B$50)*Assumptions!$B$49,0) -> -300712.71 | G26: =-IF(G25>Assumptions!$B$50,(G25-Assumptions!$B$50)*Assumptions!$B$49,0) -> -412328.28 | H26: =-IF(H25>Assumptions!$B$50,(H25-Assumptions!$B$50)*Assumptions!$B$49,0) -> -524630.56 | I26: =-IF(I25>Assumptions!$B$50,(I25-Assumptions!$B$50)*Assumptions!$B$49,0) -> -662600.32 | ... K26: =-IF(K25>Assumptions!$B$50,(K25-Assumptions!$B$50)*Assumptions!$B$49,0) -> -769638.6
A28: NET PROFIT | B28: =B25+B26 -> -995214.29 | C28: =C25+C26 -> 492531.01 | D28: =D25+D26 -> 1731427 | E28: =E25+E26 -> 2471751.4 | F28: =F25+F26 -> 3415539.6 | G28: =G25+G26 -> 4544097.1 | H28: =H25+H26 -> 5679597.9 | I28: =I25+I26 -> 7074625.4 | ... K28: =K25+K26 -> 8156901.5
A29: Net Margin | B29: =B28/B4 -> -0.13017505 | C29: =C28/C4 -> 0.039318183 | D29: =D28/D4 -> 0.096979489 | E29: =E28/E4 -> 0.11918823 | F29: =F28/F4 -> 0.14387597 | G29: =G28/G4 -> 0.16434409 | H29: =H28/H4 -> 0.18192045 | I29: =I28/I4 -> 0.21788836 | ... K29: =K28/K4 -> 0.23226786
A31: Cash Earnings (Net Profit + Depr) | B31: =B28+B23 -> -321500 | C31: =C28+C23 -> 1166245.3 | D31: =D28+D23 -> 2405141.3 | E31: =E28+E23 -> 3145465.7 | F31: =F28+F23 -> 4089253.9 | G31: =G28+G23 -> 5217811.4 | H31: =H28+H23 -> 6353312.2 | I31: =I28+I23 -> 7074625.4 | ... K31: =K28+K23 -> 8156901.5

Sheet Monthly P&L
A1: MONTHLY P&L — YEAR 1 DETAIL + ANNUAL SUMMARY
A3: Item | B3: Jan | C3: Feb | D3: Mar | E3: Apr | F3: May | G3: Jun | H3: Jul | I3: Aug | J3: Sep | K3: Oct | L3: Nov | M3: Dec | N3: TOTAL Y1
A4: Ramp-up Factor (S-curve) | B4: =Assumptions!B233 -> 0.083333333 | C4: =Assumptions!C233 -> 0.16666667 | D4: =Assumptions!D233 -> 0.25 | E4: =Assumptions!E233 -> 0.33333333 | F4: =Assumptions!F233 -> 0.41666667 | G4: =Assumptions!G233 -> 0.5 | H4: =Assumptions!H233 -> 0.58333333 | I4: =Assumptions!I233 -> 0.66666667 | ... M4: =Assumptions!M233 -> 1 | N4: =AVERAGE(B4:M4) -> 0.54166667
A5: Seasonality Factor (Dubai) | B5: =Assumptions!B235 -> 1.134 | C5: =Assumptions!C235 -> 1.195 | D5: =Assumptions!D235 -> 1.016 | E5: =Assumptions!E235 -> 1.011 | F5: =Assumptions!F235 -> 0.937 | G5: =Assumptions!G235 -> 0.73 | H5: =Assumptions!H235 -> 0.786 | I5: =Assumptions!I235 -> 0.786 | ... M5: =Assumptions!M235 -> 1.239 | N5: =AVERAGE(B5:M5) -> 1.0000833
A6: Revenue | B6: ='P&L'!B4/12*(B4/N4)*B5 -> 111149.45 | C6: ='P&L'!B4/12*(C4/N4)*C5 -> 234256.77 | D6: ='P&L'!B4/12*(D4/N4)*D5 -> 298750.89 | E6: ='P&L'!B4/12*(E4/N4)*E5 -> 396374.22 | F6: ='P&L'!B4/12*(F4/N4)*F5 -> 459202.08 | G6: ='P&L'!B4/12*(G4/N4)*G5 -> 429307.38 | H6: ='P&L'!B4/12*(H4/N4)*H5 -> 539280.65 | I6: ='P&L'!B4/12*(I4/N4)*I5 -> 616320.74 | J6: ='P&L'!B4/12*(J4/N4)*J5 -> 780692.54 | K6: ='P&L'!B4/12*(K4/N4)*K5 -> 1083070 | L6: ='P&L'!B4/12*(L4/N4)*L5 -> 1269005.2 | M6: ='P&L'!B4/12*(M4/N4)*M5 -> 1457292.7 | N6: =SUM(B6:M6) -> 7674702.6
A7: COGS | B7: ='P&L'!B5/12*(B4/N4)*B5 -> -16091.111 | C7: ='P&L'!B5/12*(C4/N4)*C5 -> -33913.365 | D7: ='P&L'!B5/12*(D4/N4)*D5 -> -43250.182 | E7: ='P&L'!B5/12*(E4/N4)*E5 -> -57383.116 | F7: ='P&L'!B5/12*(F4/N4)*F5 -> -66478.708 | G7: ='P&L'!B5/12*(G4/N4)*G5 -> -62150.852 | H7: ='P&L'!B5/12*(H4/N4)*H5 -> -78071.687 | I7: ='P&L'!B5/12*(I4/N4)*I5 -> -89224.785 | J7: ='P&L'!B5/12*(J4/N4)*J5 -> -113020.9 | K7: ='P&L'!B5/12*(K4/N4)*K5 -> -156796.1 | L7: ='P&L'!B5/12*(L4/N4)*L5 -> -183713.95 | M7: ='P&L'!B5/12*(M4/N4)*M5 -> -210972.35 | N7: =SUM(B7:M7) -> -1111067.1
A8: Marketing Redistribution | B8: =Assumptions!B236 -> 1.196 | C8: =Assumptions!C236 -> 1.26 | D8: =Assumptions!D236 -> 1.02 | E8: =Assumptions!E236 -> 1.015 | F8: =Assumptions!F236 -> 0.941 | G8: =Assumptions!G236 -> 0.623 | H8: =Assumptions!H236 -> 0.671 | I8: =Assumptions!I236 -> 0.671 | ... M8: =Assumptions!M236 -> 1.307 | N8: =AVERAGE(B8:M8) -> 0.99991667
A9: GROSS PROFIT | B9: =B6+B7 -> 95058.335 | C9: =C6+C7 -> 200343.4 | D9: =D6+D7 -> 255500.71 | E9: =E6+E7 -> 338991.1 | F9: =F6+F7 -> 392723.37 | G9: =G6+G7 -> 367156.53 | H9: =H6+H7 -> 461208.96 | I9: =I6+I7 -> 527095.95 | ... M9: =M6+M7 -> 1246320.4 | N9: =SUM(B9:M9) -> 6563635.5
A11: Marketing | B11: ='P&L'!B10/12*(B4/N4)*B8 -> -23445.28 | C11: ='P&L'!B10/12*(C4/N4)*C8 -> -49399.754 | D11: ='P&L'!B10/12*(D4/N4)*D8 -> -59985.415 | E11: ='P&L'!B10/12*(E4/N4)*E8 -> -79588.492 | F11: ='P&L'!B10/12*(F4/N4)*F8 -> -92232.477 | G11: ='P&L'!B10/12*(G4/N4)*G8 -> -73276.302 | H11: ='P&L'!B10/12*(H4/N4)*H8 -> -92075.652 | I11: ='P&L'!B10/12*(I4/N4)*I8 -> -105229.32 | J11: ='P&L'!B10/12*(J4/N4)*J8 -> -156844.22 | K11: ='P&L'!B10/12*(K4/N4)*K8 -> -228375.85 | L11: ='P&L'!B10/12*(L4/N4)*L8 -> -267601.6 | M11: ='P&L'!B10/12*(M4/N4)*M8 -> -307454.66 | N11: =SUM(B11:M11) -> -1535509
A12: Salary | B12: ='P&L'!B11/12*(B4/N4)*B5 -> -33344.834 | C12: ='P&L'!B11/12*(C4/N4)*C5 -> -70277.031 | D12: ='P&L'!B11/12*(D4/N4)*D5 -> -89625.268 | E12: ='P&L'!B11/12*(E4/N4)*E5 -> -118912.26 | F12: ='P&L'!B11/12*(F4/N4)*F5 -> -137760.62 | G12: ='P&L'!B11/12*(G4/N4)*G5 -> -128792.22 | H12: ='P&L'!B11/12*(H4/N4)*H5 -> -161784.19 | I12: ='P&L'!B11/12*(I4/N4)*I5 -> -184896.22 | J12: ='P&L'!B11/12*(J4/N4)*J5 -> -234207.76 | K12: ='P&L'!B11/12*(K4/N4)*K5 -> -324921 | L12: ='P&L'!B11/12*(L4/N4)*L5 -> -380701.56 | M12: ='P&L'!B11/12*(M4/N4)*M5 -> -437187.82 | N12: =SUM(B12:M12) -> -2302410.8
A13: Fixed Staff | B13: ='P&L'!B12/12 -> -44000 | C13: ='P&L'!B12/12 -> -44000 | D13: ='P&L'!B12/12 -> -44000 | E13: ='P&L'!B12/12 -> -44000 | F13: ='P&L'!B12/12 -> -44000 | G13: ='P&L'!B12/12 -> -44000 | H13: ='P&L'!B12/12 -> -44000 | I13: ='P&L'!B12/12 -> -44000 | J13: ='P&L'!B12/12 -> -44000 | K13: ='P&L'!B12/12 -> -44000 | L13: ='P&L'!B12/12 -> -44000 | M13: ='P&L'!B12/12 -> -44000 | N13: =SUM(B13:M13) -> -528000
A14: Administrative | B14: ='P&L'!B16/12 -> -128166.67 | C14: ='P&L'!B16/12 -> -128166.67 | D14: ='P&L'!B16/12 -> -128166.67 | E14: ='P&L'!B16/12 -> -128166.67 | F14: ='P&L'!B16/12 -> -128166.67 | G14: ='P&L'!B16/12 -> -128166.67 | H14: ='P&L'!B16/12 -> -128166.67 | I14: ='P&L'!B16/12 -> -128166.67 | J14: ='P&L'!B16/12 -> -128166.67 | K14: ='P&L'!B16/12 -> -128166.67 | L14: ='P&L'!B16/12 -> -128166.67 | M14: ='P&L'!B16/12 -> -128166.67 | N14: =SUM(B14:M14) -> -1538000
A15: R&D | B15: ='P&L'!B17/12*(B4/N4)*B5 -> -2222.9889 | C15: ='P&L'!B17/12*(C4/N4)*C5 -> -4685.1354 | D15: ='P&L'!B17/12*(D4/N4)*D5 -> -5975.0178 | E15: ='P&L'!B17/12*(E4/N4)*E5 -> -7927.4843 | F15: ='P&L'!B17/12*(F4/N4)*F5 -> -9184.0415 | G15: ='P&L'!B17/12*(G4/N4)*G5 -> -8586.1477 | H15: ='P&L'!B17/12*(H4/N4)*H5 -> -10785.613 | I15: ='P&L'!B17/12*(I4/N4)*I5 -> -12326.415 | J15: ='P&L'!B17/12*(J4/N4)*J5 -> -15613.851 | K15: ='P&L'!B17/12*(K4/N4)*K5 -> -21661.4 | L15: ='P&L'!B17/12*(L4/N4)*L5 -> -25380.104 | M15: ='P&L'!B17/12*(M4/N4)*M5 -> -29145.855 | N15: =SUM(B15:M15) -> -153494.05
A16: Rent | B16: ='P&L'!B18/12 -> -68200 | C16: ='P&L'!B18/12 -> -68200 | D16: ='P&L'!B18/12 -> -68200 | E16: ='P&L'!B18/12 -> -68200 | F16: ='P&L'!B18/12 -> -68200 | G16: ='P&L'!B18/12 -> -68200 | H16: ='P&L'!B18/12 -> -68200 | I16: ='P&L'!B18/12 -> -68200 | J16: ='P&L'!B18/12 -> -68200 | K16: ='P&L'!B18/12 -> -68200 | L16: ='P&L'!B18/12 -> -68200 | M16: ='P&L'!B18/12 -> -68200 | N16: =SUM(B16:M16) -> -818400
A18: EBITDA | B18: =B9+B11+B12+B13+B14+B15+B16 -> -204321.43 | C18: =C9+C11+C12+C13+C14+C15+C16 -> -164385.18 | D18: =D9+D11+D12+D13+D14+D15+D16 -> -140451.66 | E18: =E9+E11+E12+E13+E14+E15+E16 -> -107803.81 | F18: =F9+F11+F12+F13+F14+F15+F16 -> -86820.44 | G18: =G9+G11+G12+G13+G14+G15+G16 -> -83864.799 | H18: =H9+H11+H12+H13+H14+H15+H16 -> -43803.167 | I18: =I9+I11+I12+I13+I14+I15+I16 -> -15722.667 | ... M18: =M9+M11+M12+M13+M14+M15+M16 -> 232165.39 | N18: =SUM(B18:M18) -> -312178.32
A19: EBITDA Margin | B19: =IF(B6<>0,B18/B6,0) -> -1.8382587 | C19: =IF(C6<>0,C18/C6,0) -> -0.70173077 | D19: =IF(D6<>0,D18/D6,0) -> -0.47012967 | E19: =IF(E6<>0,E18/E6,0) -> -0.27197483 | F19: =IF(F6<>0,F18/F6,0) -> -0.18906805 | G19: =IF(G6<>0,G18/G6,0) -> -0.19534907 | H19: =IF(H6<>0,H18/H6,0) -> -0.081225178 | I19: =IF(I6<>0,I18/I6,0) -> -0.025510527 | ... N19: =IF(N6<>0,N18/N6,0) -> -0.040676276
A21: Depreciation | B21: ='P&L'!$B$23/12 -> 56142.857 | C21: ='P&L'!$B$23/12 -> 56142.857 | D21: ='P&L'!$B$23/12 -> 56142.857 | E21: ='P&L'!$B$23/12 -> 56142.857 | F21: ='P&L'!$B$23/12 -> 56142.857 | G21: ='P&L'!$B$23/12 -> 56142.857 | H21: ='P&L'!$B$23/12 -> 56142.857 | I21: ='P&L'!$B$23/12 -> 56142.857 | ... M21: ='P&L'!$B$23/12 -> 56142.857 | N21: =SUM(B21:M21) -> 673714.29
A23: EBIT | B23: =B18-B21 -> -260464.29 | C23: =C18-C21 -> -220528.04 | D23: =D18-D21 -> -196594.51 | E23: =E18-E21 -> -163946.67 | F23: =F18-F21 -> -142963.3 | G23: =G18-G21 -> -140007.66 | H23: =H18-H21 -> -99946.024 | I23: =I18-I21 -> -71865.524 | ... M23: =M18-M21 -> 176022.53 | N23: =SUM(B23:M23) -> -985892.61
A24: Corporate Tax | B24: =-IF(B23>Assumptions!$B$50/12,(B23-Assumptions!$B$50/12)*Assumptions!$B$49,0) -> 0 | C24: =-IF(C23>Assumptions!$B$50/12,(C23-Assumptions!$B$50/12)*Assumptions!$B$49,0) -> 0 | D24: =-IF(D23>Assumptions!$B$50/12,(D23-Assumptions!$B$50/12)*Assumptions!$B$49,0) -> 0 | E24: =-IF(E23>Assumptions!$B$50/12,(E23-Assumptions!$B$50/12)*Assumptions!$B$49,0) -> 0 | F24: =-IF(F23>Assumptions!$B$50/12,(F23-Assumptions!$B$50/12)*Assumptions!$B$49,0) -> 0 | G24: =-IF(G23>Assumptions!$B$50/12,(G23-Assumptions!$B$50/12)*Assumptions!$B$49,0) -> 0 | H24: =-IF(H23>Assumptions!$B$50/12,(H23-Assumptions!$B$50/12)*Assumptions!$B$49,0) -> 0 | I24: =-IF(I23>Assumptions!$B$50/12,(I23-Assumptions!$B$50/12)*Assumptions!$B$49,0) -> 0 | ... M24: =-IF(M23>Assumptions!$B$50/12,(M23-Assumptions!$B$50/12)*Assumptions!$B$49,0) -> -13029.528 | N24: =SUM(B24:M24) -> -22695.941
A26: NET PROFIT | B26: =B23+B24 -> -260464.29 | C26: =C23+C24 -> -220528.04 | D26: =D23+D24 -> -196594.51 | E26: =E23+E24 -> -163946.67 | F26: =F23+F24 -> -142963.3 | G26: =G23+G24 -> -140007.66 | H26: =H23+H24 -> -99946.024 | I26: =I23+I24 -> -71865.524 | ... M26: =M23+M24 -> 162993.01 | N26: =SUM(B26:M26) -> -1008588.6
A27: Net Margin | B27: =IF(B6<>0,B26/B6,0) -> -2.3433701 | C27: =IF(C6<>0,C26/C6,0) -> -0.94139452 | D27: =IF(D6<>0,D26/D6,0) -> -0.65805499 | E27: =IF(E6<>0,E26/E6,0) -> -0.41361587 | F27: =IF(F6<>0,F26/F6,0) -> -0.31132981 | G27: =IF(G6<>0,G26/G6,0) -> -0.3261245 | H27: =IF(H6<>0,H26/H6,0) -> -0.18533212 | I27: =IF(I6<>0,I26/I6,0) -> -0.1166041 | ... N27: =IF(N6<>0,N26/N6,0) -> -0.13141728
A28: Cash Earnings (NP + Depr) | B28: =B26+B21 -> -204321.43 | C28: =C26+C21 -> -164385.18 | D28: =D26+D21 -> -140451.66 | E28: =E26+E21 -> -107803.81 | F28: =F26+F21 -> -86820.44 | G28: =G26+G21 -> -83864.799 | H28: =H26+H21 -> -43803.167 | I28: =I26+I21 -> -15722.667 | ... M28: =M26+M21 -> 219135.86 | N28: =SUM(B28:M28) -> -334874.26
A29: Cumulative EBITDA | B29: =B18 -> -204321.43 | C29: =B29+C18 -> -368706.62 | D29: =C29+D18 -> -509158.27 | E29: =D29+E18 -> -616962.08 | F29: =E29+F18 -> -703782.52 | G29: =F29+G18 -> -787647.32 | H29: =G29+H18 -> -831450.49 | I29: =H29+I18 -> -847173.15 | J29: =I29+J18 -> -826534.01 | ... M29: =L29+M18 -> -312178.32
A30: Cumulative Net Profit | B30: =B26 -> -260464.29 | C30: =B30+C26 -> -480992.33 | D30: =C30+D26 -> -677586.85 | E30: =D30+E26 -> -841533.51 | F30: =E30+F26 -> -984496.81 | G30: =F30+G26 -> -1124504.5 | H30: =G30+H26 -> -1224450.5 | I30: =H30+I26 -> -1296316 | J30: =I30+J26 -> -1331819.7 | ... M30: =L30+M26 -> -1008588.6

Sheet CapEx
A1: CAPITAL EXPENDITURE
A3: Item | B3: 620 sqm | C3: 450 sqm | D3: Active (AED) | E3: Notes
A4: Rent Deposit (3 months) | B4: =Assumptions!B9*Assumptions!B12/12*Assumptions!B24 -> 204600 | C4: =Assumptions!C9*Assumptions!C12/12*Assumptions!C24 -> 148500 | D4: =IF(Assumptions!$B$5=1,B4,C4) -> 204600 | E4: 3 months advance
A5: Renovation & Fit-out | B5: =Assumptions!B9*4200 -> 2604000 | C5: =Assumptions!C9*4200 -> 1890000 | D5: =IF(Assumptions!$B$5=1,B5,C5) -> 2604000 | E5: AED 3,800/sqm
A7: Physio Equipment
A8: Pressotherapy | B8: 20000 | C8: 20000 | D8: =IF(Assumptions!$B$5=1,B8,C8) -> 20000
A9: Cryotherapy (Gameready) | B9: 150000 | C9: 150000 | D9: =IF(Assumptions!$B$5=1,B9,C9) -> 150000
A10: Shockwave Therapy (BTL) | B10: 130000 | C10: 130000 | D10: =IF(Assumptions!$B$5=1,B10,C10) -> 130000
A11: Magnetic Field (BTL) | B11: 130000 | C11: 130000 | D11: =IF(Assumptions!$B$5=1,B11,C11) -> 130000
A12: Laser Therapy (BTL) | B12: 130000 | C12: 130000 | D12: =IF(Assumptions!$B$5=1,B12,C12) -> 130000
A13: Other physio | B13: 50000 | C13: 50000 | D13: =IF(Assumptions!$B$5=1,B13,C13) -> 50000
A14: Physio Subtotal | B14: =SUM(B8:B13) -> 610000 | C14: =SUM(C8:C13) -> 610000 | D14: =IF(Assumptions!$B$5=1,B14,C14) -> 610000
A16: Assessment Equipment
A17: Postural Diagnosis (Diers) | B17: 20000 | C17: 20000 | D17: =IF(Assumptions!$B$5=1,B17,C17) -> 20000
A18: Plantograph (Sidas) | B18: 35000 | C18: 35000 | D18: =IF(Assumptions!$B$5=1,B18,C18) -> 35000
A19: Force Plates (Hawkins) | B19: 50000 | C19: 50000 | D19: =IF(Assumptions!$B$5=1,B19,C19) -> 50000
A20: Ultrasound | B20: 150000 | C20: 150000 | D20: =IF(Assumptions!$B$5=1,B20,C20) -> 150000
A21: Other assessment | B21: 15000 | C21: 15000 | D21: =IF(Assumptions!$B$5=1,B21,C21) -> 15000
A22: Assessment Subtotal | B22: =SUM(B17:B21) -> 270000 | C22: =SUM(C17:C21) -> 270000 | D22: =IF(Assumptions!$B$5=1,B22,C22) -> 270000
A24: Dental Clinic
A25: Dental chairs (×3) | B25: 240000 | C25: 240000 | D25: =IF(Assumptions!$B$5=1,B25,C25) -> 240000 | E25: 3 × 80K
A26: X-Ray (dental) | B26: 150000 | C26: 150000 | D26: =IF(Assumptions!$B$5=1,B26,C26) -> 150000
A27: Small dental equipment | B27: 100000 | C27: 100000 | D27: =IF(Assumptions!$B$5=1,B27,C27) -> 100000
A28: Dental Subtotal | B28: =SUM(B25:B27) -> 490000 | C28: =SUM(C25:C27) -> 490000 | D28: =IF(Assumptions!$B$5=1,B28,C28) -> 490000
A30: Laboratory & Medical Equipment | B30: 60000 | C30: 60000 | D30: =IF(Assumptions!$B$5=1,B30,C30) -> 60000 | E30: PRP, sterilization, fridge
A31: Cosmetology & Beauty | B31: 350000 | C31: 350000 | D31: =IF(Assumptions!$B$5=1,B31,C31) -> 350000
A33: Office & IT
A34: Furniture | B34: 40000 | C34: 40000 | D34: =IF(Assumptions!$B$5=1,B34,C34) -> 40000
A35: Medical Furniture (10 beds) | B35: 50000 | C35: 50000 | D35: =IF(Assumptions!$B$5=1,B35,C35) -> 50000
A36: PCs (×8) | B36: 32000 | C36: 32000 | D36: =IF(Assumptions!$B$5=1,B36,C36) -> 32000
A37: Printers | B37: 10000 | C37: 10000 | D37: =IF(Assumptions!$B$5=1,B37,C37) -> 10000
A38: PMS / CRM / Booking | B38: 80000 | C38: 80000 | D38: =IF(Assumptions!$B$5=1,B38,C38) -> 80000 | E38: Clinical software
A39: Office & IT Subtotal | B39: =SUM(B34:B38) -> 212000 | C39: =SUM(C34:C38) -> 212000 | D39: =IF(Assumptions!$B$5=1,B39,C39) -> 212000
A41: Pre-operational Planning
A42: Design / MEP / Engineering | B42: 120000 | C42: 120000 | D42: =IF(Assumptions!$B$5=1,B42,C42) -> 120000
A43: Licensing & Legal | B43: 200000 | C43: 150000 | D43: =IF(Assumptions!$B$5=1,B43,C43) -> 200000 | E43: MOCCAE, DM, DED
A44: HR Hiring Core Team | B44: 200000 | C44: 150000 | D44: =IF(Assumptions!$B$5=1,B44,C44) -> 200000
A45: Healthcare Licensing (DHA) | B45: 60000 | C45: 60000 | D45: =IF(Assumptions!$B$5=1,B45,C45) -> 60000
A46: Marketing Strategy (launch) | B46: 60000 | C46: 60000 | D46: =IF(Assumptions!$B$5=1,B46,C46) -> 60000 | E46: Branding, website
A47: Insurance DB Purchase | B47: 250000 | C47: 250000 | D47: =IF(Assumptions!$B$5=1,B47,C47) -> 250000
A48: Pre-operational Subtotal | B48: =SUM(B42:B47) -> 890000 | C48: =SUM(C42:C47) -> 790000 | D48: =IF(Assumptions!$B$5=1,B48,C48) -> 890000
A50: Initial Inventory | B50: 100000 | C50: 100000 | D50: =IF(Assumptions!$B$5=1,B50,C50) -> 100000 | E50: Medications, supplies
A51: Pre-opening Salaries (3 mo) | B51: =(Assumptions!C140*1+Assumptions!C141*2+Assumptions!C142*1+Assumptions!C145*1)/12*Assumptions!B24 -> 132000 | C51: =(Assumptions!C140*1+Assumptions!C141*1+Assumptions!C142*1+Assumptions!C145*1)/12*Assumptions!C24 -> 111000 | D51: =IF(Assumptions!$B$5=1,B51,C51) -> 132000 | E51: Core team × deposit months
A52: Working Capital | B52: =(Assumptions!B9*Assumptions!B12+Assumptions!C140*1+Assumptions!C141*2+Assumptions!C142*1+Assumptions!C145*1)/12*Assumptions!B24 -> 336600 | C52: =(Assumptions!C9*Assumptions!C12+Assumptions!C140*1+Assumptions!C141*1+Assumptions!C142*1+Assumptions!C145*1)/12*Assumptions!C24 -> 259500 | D52: =IF(Assumptions!$B$5=1,B52,C52) -> 336600 | E52: Rent + staff × deposit months
A54: SUBTOTAL | B54: =B4+B5+B14+B22+B28+B30+B31+B39+B48+B50+B51+B52 -> 6259200 | C54: =C4+C5+C14+C22+C28+C30+C31+C39+C48+C50+C51+C52 -> 5291000 | D54: =IF(Assumptions!$B$5=1,B54,C54) -> 6259200
A55: Contingency (5%) | B55: =B54*0.05 -> 312960 | C55: =C54*0.05 -> 264550 | D55: =IF(Assumptions!$B$5=1,B55,C55) -> 312960
A56: TOTAL CAPEX | B56: =B54+B55 -> 6572160 | C56: =C54+C55 -> 5555550 | D56: =IF(Assumptions!$B$5=1,B56,C56) -> 6572160
A58: DEPRECIATION SPLIT
A59: Depreciable Assets (fit-out + equipment + design) | B59: =B5+B14+B22+B28+B30+B31+B39+B42 -> 4716000 | C59: =C5+C14+C22+C28+C30+C31+C39+C42 -> 4002000 | D59: =IF(Assumptions!$B$5=1,B59,C59) -> 4716000 | E59: Renovation, equipment, design/MEP
A60: Non-depreciable (deposit, WC, inventory, salaries, mkt, licenses) | B60: =B56-B59 -> 1856160 | C60: =C56-C59 -> 1553550 | D60: =IF(Assumptions!$B$5=1,B60,C60) -> 1856160 | E60: Deposit, working capital, pre-op expenses
A61: CHECK (should = Total CapEx) | B61: =B59+B60-B56 -> 0 | C61: =C59+C60-C56 -> 0 | D61: =D59+D60-D56 -> 0

Sheet Cash Flow & DCF
A1: CASH FLOW & DCF ANALYSIS
A2: Date | B2: 45658 | C2: 46023 | D2: 46388 | E2: 46753 | F2: 47119 | G2: 47484 | H2: 47849 | I2: 48214 | J2: 48580 | K2: 48945 | L2: 49310
A3: Item | B3: Year 0 | C3: Year 1 | D3: Year 2 | E3: Year 3 | F3: Year 4 | G3: Year 5 | H3: Year 6 | I3: Year 7 | J3: Year 8 | K3: Year 9 | L3: Year 10
A4: Capital Investment | B4: =-CapEx!D56*Assumptions!$E$48 -> -6572160 | C4: 0 | D4: 0 | E4: 0 | F4: 0 | G4: 0 | H4: 0 | I4: 0 | J4: 0 | K4: 0 | L4: 0
A5: Operating Cash Flow | B5: 0 | C5: ='P&L'!B31*Assumptions!$E$47 -> -321500 | D5: ='P&L'!C31*Assumptions!$E$47 -> 1166245.3 | E5: ='P&L'!D31*Assumptions!$E$47 -> 2405141.3 | F5: ='P&L'!E31*Assumptions!$E$47 -> 3145465.7 | G5: ='P&L'!F31*Assumptions!$E$47 -> 4089253.9 | H5: ='P&L'!G31*Assumptions!$E$47 -> 5217811.4 | I5: ='P&L'!H31*Assumptions!$E$47 -> 6353312.2 | J5: ='P&L'!I31*Assumptions!$E$47 -> 7074625.4 | ... L5: ='P&L'!K31*Assumptions!$E$47 -> 8156901.5
A7: Net Cash Flow | B7: =B4+B5 -> -6572160 | C7: =C4+C5 -> -321500 | D7: =D4+D5 -> 1166245.3 | E7: =E4+E5 -> 2405141.3 | F7: =F4+F5 -> 3145465.7 | G7: =G4+G5 -> 4089253.9 | H7: =H4+H5 -> 5217811.4 | I7: =I4+I5 -> 6353312.2 | ... L7: =L4+L5 -> 8156901.5
A8: Cumulative Cash Flow | B8: =B7 -> -6572160 | C8: =B8+C7 -> -6893660 | D8: =C8+D7 -> -5727414.7 | E8: =D8+E7 -> -3322273.4 | F8: =E8+F7 -> -176807.68 | G8: =F8+G7 -> 3912446.2 | H8: =G8+H7 -> 9130257.6 | I8: =H8+I7 -> 15483570 | J8: =I8+J7 -> 22558195 | ... L8: =K8+L7 -> 38322063
A9: Exit Proceeds (net of tax) | G9: =IF('P&L'!F20*'Exit Valuation'!$B$5-(-B7)>375000,('P&L'!F20*'Exit Valuation'!$B$5)-(('P&L'!F20*'Exit Valuation'!$B$5-(-B7)-375000)*0.09),('P&L'!F20*'Exit Valuation'!$B$5)) -> 32584202 | L9: =IF('P&L'!K20*'Exit Valuation'!$B$5-(-B7)>375000,('P&L'!K20*'Exit Valuation'!$B$5)-(('P&L'!K20*'Exit Valuation'!$B$5-(-B7)-375000)*0.09),('P&L'!K20*'Exit Valuation'!$B$5)) -> 65610456
A10: CF + Exit (5Y) | B10: =B7 -> -6572160 | C10: =C7 -> -321500 | D10: =D7 -> 1166245.3 | E10: =E7 -> 2405141.3 | F10: =F7 -> 3145465.7 | G10: =G7+G9 -> 36673455
A11: CF + Exit (10Y) | B11: =B7 -> -6572160 | C11: =C7 -> -321500 | D11: =D7 -> 1166245.3 | E11: =E7 -> 2405141.3 | F11: =F7 -> 3145465.7 | G11: =G7 -> 4089253.9 | H11: =H7 -> 5217811.4 | I11: =I7 -> 6353312.2 | ... K11: =K7 -> 7606966.5 | L11: =L7+L9 -> 73767357
A13: Discount Factor | B13: 1 | C13: =1/(1+Assumptions!$B$48)^0.5 -> 0.94491118 | D13: =1/(1+Assumptions!$B$48)^1.5 -> 0.8436707 | E13: =1/(1+Assumptions!$B$48)^2.5 -> 0.75327741 | F13: =1/(1+Assumptions!$B$48)^3.5 -> 0.67256912 | G13: =1/(1+Assumptions!$B$48)^4.5 -> 0.60050814 | H13: =1/(1+Assumptions!$B$48)^5.5 -> 0.53616798 | I13: =1/(1+Assumptions!$B$48)^6.5 -> 0.47872141 | J13: =1/(1+Assumptions!$B$48)^7.5 -> 0.42742983 | K13: =1/(1+Assumptions!$B$48)^8.5 -> 0.38163378 | L13: =1/(1+Assumptions!$B$48)^9.5 -> 0.34074445
A14: Discounted Cash Flow | B14: =B7*B13 -> -6572160 | C14: =C7*C13 -> -303788.95 | D14: =D7*D13 -> 983926.98 | E14: =E7*E13 -> 1811738.6 | F14: =F7*F13 -> 2115543.1 | G14: =G7*G13 -> 2455630.3 | H14: =H7*H13 -> 2797623.4 | I14: =I7*I13 -> 3041466.6 | ... L14: =L7*L13 -> 2779418.9
A15: Cumulative DCF | B15: =B14 -> -6572160 | C15: =B15+C14 -> -6875948.9 | D15: =C15+D14 -> -5892022 | E15: =D15+E14 -> -4080283.3 | F15: =E15+F14 -> -1964740.3 | G15: =F15+G14 -> 490890.01 | H15: =G15+H14 -> 3288513.4 | I15: =H15+I14 -> 6329980 | J15: =I15+J14 -> 9353886 | ... L15: =K15+L14 -> 15036380
A18: KEY INVESTMENT METRICS
A19: Metric | B19: 5 Years | C19: 10 Years
A20: NPV (AED) | B20: =G15 -> 490890.01 | C20: =L15 -> 15036380
A21: XIRR (%) | B21: =XIRR(B7:G7,B2:G2) -> 0.12431843 | C21: =XIRR(B7:L7,B2:L2) -> 0.34484329
A22: Simple Payback (months) | B22: {=IF(COUNTIF(C8:L8,">0")=0,"N/A",(MATCH(1,INDEX((C8:L8>0)*1,,),0)-1)*12+(-INDEX(B8:K8,MATCH(1,INDEX((C8:L8>0)*1,,),0)))/(INDEX(C8:L8,MATCH(1,INDEX((C8:L8>0)*1,,),0))-INDEX(B8:K8,MATCH(1,INDEX((C8:L8>0)*1,,),0)))*12)} -> 48.518846
A23: Total Cash Generated | B23: =G8 -> 3912446.2 | C23: =L8 -> 38322063
A24: Equity Multiple (×) | B24: =(G8-B7)/-B7 -> 1.595306 | C24: =(L8-B7)/-B7 -> 6.8309693
A25: Profit-on-Cost (%) | B25: =(G8-B7)/-B7-1 -> 0.59530599 | C25: =(L8-B7)/-B7-1 -> 5.8309693
A27: WITH EXIT (Base 8× EBITDA)
A28: Metric | B28: 5 Years | C28: 10 Years
A29: Exit Value (net of 9% tax) | B29: ='Exit Valuation'!E21 -> 32584202 | C29: ='Exit Valuation'!E23 -> 65610456
A30: Total Return (Cash + Exit) | B30: =B23+B29 -> 36496648 | C30: =C23+C29 -> 1.0393252e+08
A31: NPV with Exit (AED) | B31: =B20+'Exit Valuation'!E21*'Cash Flow & DCF'!G13 -> 20057968 | C31: =C20+'Exit Valuation'!E23*'Cash Flow & DCF'!L13 -> 37392779
A32: IRR with Exit (%) | B32: =XIRR(B10:G10,B2:G2) -> 0.49443884 | C32: =XIRR(B11:L11,B2:L2) -> 0.42758073
A33: MOIC with Exit (×) | B33: =B30/-B7 -> 5.5532196 | C33: =C30/-B7 -> 15.814058
A34: MOIC Cash-only (×) | B34: =B24 -> 1.595306 | C34: =C24 -> 6.8309693
A35: Exit EBITDA Multiple | B35: ='Exit Valuation'!B5 -> 8 | C35: ='Exit Valuation'!B5 -> 8
A38: INVESTOR MODEL
A40: INVESTOR ASSUMPTIONS
A41: Total CapEx (AED) | B41: =CapEx!D56 -> 6572160 | C41: Investment Amount
A42: Working Capital (included in CapEx above, shown for reference) | B42: =CapEx!D52 -> 336600 | C42: Included in investment
A43: Total Investment | B43: =B41 -> 6572160 | C43: CapEx already includes WC (line 12 of CapEx breakdown)
A45: EQUITY MODEL ASSUMPTIONS
A46: Investor Equity Stake (%) | B46: 0.3 | C46: % of company acquired
A47: Dividend Payout Ratio (%) | B47: 0.8 | C47: % of Net Profit distributed
A48: Preferred Return (%) | B48: 0.08 | C48: Min return before founder dividends
A50: REVENUE SHARE MODEL ASSUMPTIONS
A51: Revenue Share Rate (%) | B51: 0.1 | C51: % of monthly revenue to investor
A52: Target Return Multiple (×) | B52: 2.5 | C52: Total return cap on investment
A53: Grace Period (months) | B53: 6 | C53: No payments during ramp-up
A55: EQUITY MODEL — INVESTOR RETURNS
B56: Year 0 | C56: Year 1 | D56: Year 2 | E56: Year 3 | F56: Year 4 | G56: Year 5 | H56: Year 6 | I56: Year 7 | J56: Year 8 | K56: Year 9 | L56: Year 10
A57: Investor Capital Outflow | B57: =-$B$43 -> -6572160 | C57: 0 | D57: 0 | E57: 0 | F57: 0 | G57: 0 | H57: 0 | I57: 0 | J57: 0 | K57: 0 | L57: 0
A58: Net Profit | B58: 0 | C58: ='P&L'!B28 -> -995214.29 | D58: ='P&L'!C28 -> 492531.01 | E58: ='P&L'!D28 -> 1731427 | F58: ='P&L'!E28 -> 2471751.4 | G58: ='P&L'!F28 -> 3415539.6 | H58: ='P&L'!G28 -> 4544097.1 | I58: ='P&L'!H28 -> 5679597.9 | J58: ='P&L'!I28 -> 7074625.4 | ... L58: ='P&L'!K28 -> 8156901.5
A59: Dividends (total) | B59: 0 | C59: =MAX(0,C58)*$B$47 -> 0 | D59: =MAX(0,D58)*$B$47 -> 394024.81 | E59: =MAX(0,E58)*$B$47 -> 1385141.6 | F59: =MAX(0,F58)*$B$47 -> 1977401.1 | G59: =MAX(0,G58)*$B$47 -> 2732431.7 | H59: =MAX(0,H58)*$B$47 -> 3635277.7 | I59: =MAX(0,I58)*$B$47 -> 4543678.3 | J59: =MAX(0,J58)*$B$47 -> 5659700.3 | ... L59: =MAX(0,L58)*$B$47 -> 6525521.2
A60: Investor Dividend Share | B60: 0 | C60: =C59*$B$46 -> 0 | D60: =D59*$B$46 -> 118207.44 | E60: =E59*$B$46 -> 415542.49 | F60: =F59*$B$46 -> 593220.34 | G60: =G59*$B$46 -> 819729.51 | H60: =H59*$B$46 -> 1090583.3 | I60: =I59*$B$46 -> 1363103.5 | J60: =J59*$B$46 -> 1697910.1 | ... L60: =L59*$B$46 -> 1957656.3
A62: Investor Net Cash Flow | B62: =B57+B60 -> -6572160 | C62: =C57+C60 -> 0 | D62: =D57+D60 -> 118207.44 | E62: =E57+E60 -> 415542.49 | F62: =F57+F60 -> 593220.34 | G62: =G57+G60 -> 819729.51 | H62: =H57+H60 -> 1090583.3 | I62: =I57+I60 -> 1363103.5 | ... L62: =L57+L60 -> 1957656.3
A63: Investor Cumulative CF | B63: =B62 -> -6572160 | C63: =B63+C62 -> -6572160 | D63: =C63+D62 -> -6453952.6 | E63: =D63+E62 -> -6038410.1 | F63: =E63+F62 -> -5445189.7 | G63: =F63+G62 -> -4625460.2 | H63: =G63+H62 -> -3534876.9 | I63: =H63+I62 -> -2171773.4 | J63: =I63+J62 -> -473863.31 | ... L63: =K63+L62 -> 3309465
A65: Exit Value (Base 8×) | G65: ='P&L'!F20*'Exit Valuation'!$B$5 -> 35119733 | L65: ='P&L'!K20*'Exit Valuation'!$B$5 -> 71412320
A66: Investor Exit Share | G66: =G65*$B$46 -> 10535920 | L66: =L65*$B$46 -> 21423696
A67: Tax on Exit Gain | G67: =-IF(G66-(-B62)>375000,(G66-(-B62)-375000)*Assumptions!$B$49,0) -> -322988.39 | L67: =-IF(L66-(-B62)>375000,(L66-(-B62)-375000)*Assumptions!$B$49,0) -> -1302888.3
A68: Investor Net Exit Proceeds | G68: =G66+G67 -> 10212932 | L68: =L66+L67 -> 20120808
A70: Total Return (CF + Exit) — 5Y | B70: =G63+G68 -> 5587471.3
A71: Total Return (CF + Exit) — 10Y | B71: =L63+L68 -> 23430273
A73: REVENUE SHARE MODEL — INVESTOR RETURNS
B74: Year 0 | C74: Year 1 | D74: Year 2 | E74: Year 3 | F74: Year 4 | G74: Year 5 | H74: Year 6 | I74: Year 7 | J74: Year 8 | K74: Year 9 | L74: Year 10
A75: Investor Capital Outflow | B75: =-$B$43 -> -6572160 | C75: 0 | D75: 0 | E75: 0 | F75: 0 | G75: 0 | H75: 0 | I75: 0 | J75: 0 | K75: 0 | L75: 0
A76: Revenue | B76: 0 | C76: =Revenue!B13 -> 7645200 | D76: =Revenue!C13 -> 12526800 | E76: =Revenue!D13 -> 17853539 | F76: =Revenue!E13 -> 20738218 | G76: =Revenue!F13 -> 23739472 | H76: =Revenue!G13 -> 27649897 | I76: =Revenue!H13 -> 31220228 | J76: =Revenue!I13 -> 32469038 | ... L76: =Revenue!K13 -> 35118511
A77: Revenue Share Payment | B77: 0 | C77: =C76*$B$51*MAX(0,MIN(12,1*12-$B$53))/12 -> 382260 | D77: =D76*$B$51*MAX(0,MIN(12,2*12-$B$53))/12 -> 1252680 | E77: =E76*$B$51*MAX(0,MIN(12,3*12-$B$53))/12 -> 1785353.9 | F77: =F76*$B$51*MAX(0,MIN(12,4*12-$B$53))/12 -> 2073821.8 | G77: =G76*$B$51*MAX(0,MIN(12,5*12-$B$53))/12 -> 2373947.2 | H77: =H76*$B$51*MAX(0,MIN(12,6*12-$B$53))/12 -> 2764989.7 | I77: =I76*$B$51*MAX(0,MIN(12,7*12-$B$53))/12 -> 3122022.8 | J77: =J76*$B$51*MAX(0,MIN(12,8*12-$B$53))/12 -> 3246903.8 | K77: =K76*$B$51*MAX(0,MIN(12,9*12-$B$53))/12 -> 3376779.9 | L77: =L76*$B$51*MAX(0,MIN(12,10*12-$B$53))/12 -> 3511851.1
A78: Cap Remaining | B78: =$B$43*$B$52 -> 16430400 | C78: =MAX(0,B78-B79) -> 16430400 | D78: =MAX(0,C78-C79) -> 16048140 | E78: =MAX(0,D78-D79) -> 14795460 | F78: =MAX(0,E78-E79) -> 13010106 | G78: =MAX(0,F78-F79) -> 10936284 | H78: =MAX(0,G78-G79) -> 8562337.2 | I78: =MAX(0,H78-H79) -> 5797347.5 | J78: =MAX(0,I78-I79) -> 2675324.6 | ... L78: =MAX(0,K78-K79) -> 0
A79: Payment (capped) | B79: 0 | C79: =MIN(C77,C78) -> 382260 | D79: =MIN(D77,D78) -> 1252680 | E79: =MIN(E77,E78) -> 1785353.9 | F79: =MIN(F77,F78) -> 2073821.8 | G79: =MIN(G77,G78) -> 2373947.2 | H79: =MIN(H77,H78) -> 2764989.7 | I79: =MIN(I77,I78) -> 3122022.8 | J79: =MIN(J77,J78) -> 2675324.6 | ... L79: =MIN(L77,L78) -> 0
A81: Investor Net Cash Flow | B81: =B75+B79 -> -6572160 | C81: =C75+C79 -> 382260 | D81: =D75+D79 -> 1252680 | E81: =E75+E79 -> 1785353.9 | F81: =F75+F79 -> 2073821.8 | G81: =G75+G79 -> 2373947.2 | H81: =H75+H79 -> 2764989.7 | I81: =I75+I79 -> 3122022.8 | ... L81: =L75+L79 -> 0
A82: Investor Cumulative CF | B82: =B81 -> -6572160 | C82: =B82+C81 -> -6189900 | D82: =C82+D81 -> -4937220 | E82: =D82+E81 -> -3151866.1 | F82: =E82+F81 -> -1078044.4 | G82: =F82+G81 -> 1295902.8 | H82: =G82+H81 -> 4060892.5 | I82: =H82+I81 -> 7182915.4 | J82: =I82+J81 -> 9858240 | ... L82: =K82+L81 -> 9858240
A84: Total Paid to Investor | B84: =L82-B81 -> 16430400
A85: Effective Cost to Company (% Rev) | B85: =IF(SUM(C76:L76)>0,SUM(C79:L79)/SUM(C76:L76),0) -> 0.067690388
A86: Months to Full Payback | B86: {=IF(COUNTIF(C82:L82,">0")=0,"N/A",(MATCH(1,INDEX((C82:L82>0)*1,,),0)-1)*12+(-INDEX(B82:K82,MATCH(1,INDEX((C82:L82>0)*1,,),0)))/(INDEX(C82:L82,MATCH(1,INDEX((C82:L82>0)*1,,),0))-INDEX(B82:K82,MATCH(1,INDEX((C82:L82>0)*1,,),0)))*12)} -> 53.449377
A88: COMPARISON: EQUITY vs REVENUE SHARE
A89: Metric | B89: Equity Model | C89: Revenue Share | D89: Winner
A90: Total Investment | B90: =$B$43 -> 6572160 | C90: =$B$43 -> 6572160
A91: Investor % Ownership | B91: =$B$46 -> 0.3 | C91: 0
A93: INVESTOR PERSPECTIVE
A94: Annual Cash Yield (Y3) | B94: =IF(E60>0,E60/$B$43,0) -> 0.063227689 | C94: =IF(E79>0,E79/$B$43,0) -> 0.27165405 | D94: =IF(B94>C94,"Equity",IF(C94>B94,"Rev Share","Tie")) -> Rev Share
A95: 5-Year Total Return (CF + Exit) | B95: =B70 -> 5587471.3 | C95: =G82 -> 1295902.8 | D95: =IF(B95>C95,"Equity",IF(C95>B95,"Rev Share","Tie")) -> Equity
A96: 10-Year Total Return (CF + Exit) | B96: =B71 -> 23430273 | C96: =L82 -> 9858240 | D96: =IF(B96>C96,"Equity",IF(C96>B96,"Rev Share","Tie")) -> Equity
A97: 5-Year MOIC | B97: =IF(-B62>0,B95/(-B62),0) -> 0.85017275 | C97: =IF(-B81>0,C95/(-B81),0) -> 0.19718065 | D97: =IF(B97>C97,"Equity",IF(C97>B97,"Rev Share","Tie")) -> Equity
A98: 10-Year MOIC | B98: =IF(-B62>0,B96/(-B62),0) -> 3.5650795 | C98: =IF(-B81>0,C96/(-B81),0) -> 1.5 | D98: =IF(B98>C98,"Equity",IF(C98>B98,"Rev Share","Tie")) -> Equity
A99: Payback Period (months) | B99: {=IF(COUNTIF(C63:L63,">0")=0,">120",(MATCH(1,INDEX((C63:L63>0)*1,,),0)-1)*12+(-INDEX(B63:K63,MATCH(1,INDEX((C63:L63>0)*1,,),0)))/(INDEX(C63:L63,MATCH(1,INDEX((C63:L63>0)*1,,),0))-INDEX(B63:K63,MATCH(1,INDEX((C63:L63>0)*1,,),0)))*12)} -> 99.114667 | C99: =B86 -> 53.449377
A101: COMPANY PERSPECTIVE
A102: Total Cash Paid to Investor (10Y) | B102: =SUM(C60:L60)+G68+L68 -> 40215364 | C102: =SUM(C79:L79) -> 16430400 | D102: =IF(B102<C102,"Equity cheaper",IF(C102<B102,"Rev Share cheaper","Tie")) -> Rev Share cheaper
A103: Retains 100% Ownership? | B103: No | C103: Yes
A104: FOUNDER PERSPECTIVE
A105: Ownership Retained | B105: =1-$B$46 -> 0.7 | C105: 1
A106: 10Y Salary Income | B106: =SUM(C119:L119) -> 8644397.1 | C106: =SUM(C128:L128) -> 8644397.1
A107: 10Y Dividend Income | B107: =SUM(C120:L120) -> 23057125 | C107: =SUM(C129:L129) -> 32938750
A108: 10Y Revenue Share Cost | B108: 0 | C108: =SUM(C130:L130) -> -16430400
A109: Exit Proceeds (10Y) | B109: =L123 -> 45927319 | C109: =L133 -> 65610456
A111: TOTAL 5Y Founder Return | B111: =B124 -> 31610993 | C111: =B134 -> 35464890
A112: TOTAL 10Y Founder Return | B112: =B125 -> 77988841 | C112: =B135 -> 91123203
A113: Revenue Share Advantage | C113: =C112-B112 -> 13134362
A115: FOUNDER RETURNS ANALYSIS
A116: Founder Salary CEO (AED/year) | B116: 720000
A118: ="EQUITY MODEL — Founder ("&TEXT(1-$B$46,"0%")&")" -> EQUITY MODEL — Founder (70%)
A119: Founder Salary | B119: =$B$116/2 -> 360000 | C119: =$B$116 -> 720000 | D119: =C119*(1+Assumptions!$B$47) -> 748800 | E119: =D119*(1+Assumptions!$B$47) -> 778752 | F119: =E119*(1+Assumptions!$B$47) -> 809902.08 | G119: =F119*(1+Assumptions!$B$47) -> 842298.16 | H119: =G119*(1+Assumptions!$B$47) -> 875990.09 | I119: =H119*(1+Assumptions!$B$47) -> 911029.69 | J119: =I119*(1+Assumptions!$B$47) -> 947470.88 | K119: =J119*(1+Assumptions!$B$47) -> 985369.72 | L119: =K119*(1+Assumptions!$B$47) -> 1024784.5
A120: =" Founder Dividends ("&TEXT(1-$B$46,"0%")&")" -> Founder Dividends (70%) | B120: 0 | C120: =C59*(1-$B$46) -> 0 | D120: =D59*(1-$B$46) -> 275817.37 | E120: =E59*(1-$B$46) -> 969599.15 | F120: =F59*(1-$B$46) -> 1384180.8 | G120: =G59*(1-$B$46) -> 1912702.2 | H120: =H59*(1-$B$46) -> 2544694.4 | I120: =I59*(1-$B$46) -> 3180574.8 | J120: =J59*(1-$B$46) -> 3961790.2 | ... L120: =L59*(1-$B$46) -> 4567864.8
A121: Founder Annual Cash | B121: =B119+B120 -> 360000 | C121: =C119+C120 -> 720000 | D121: =D119+D120 -> 1024617.4 | E121: =E119+E120 -> 1748351.1 | F121: =F119+F120 -> 2194082.9 | G121: =G119+G120 -> 2755000.4 | H121: =H119+H120 -> 3420684.5 | I121: =I119+I120 -> 4091604.5 | ... L121: =L119+L120 -> 5592649.3
A122: Cumulative Cash | B122: =B121 -> 360000 | C122: =B122+C121 -> 1080000 | D122: =C122+D121 -> 2104617.4 | E122: =D122+E121 -> 3852968.5 | F122: =E122+F121 -> 6047051.4 | G122: =F122+G121 -> 8802051.7 | H122: =G122+H121 -> 12222736 | I122: =H122+I121 -> 16314341 | J122: =I122+J121 -> 21223602 | ... L122: =K122+L121 -> 32061522
A123: =" Exit Equity ("&TEXT(1-$B$46,"0%")&")" -> Exit Equity (70%) | G123: ='Exit Valuation'!E21*(1-$B$46) -> 22808941 | L123: ='Exit Valuation'!E23*(1-$B$46) -> 45927319
...

Sheet Exit Valuation
A1: EXIT VALUATION & RETURN ANALYSIS (AED)
A3: EXIT ASSUMPTIONS
A4: Low multiple (conservative) | B4: 6
A5: Base multiple | B5: 8
A6: High multiple (premium) | B6: 10
A7: Terminal growth rate (DCF) | B7: 0.03
A8: Discount rate (WACC) | B8: =Assumptions!B48 -> 0.12
A9: Total CapEx (investment) | B9: =CapEx!D56 -> 6572160
A11: EBITDA MULTIPLE VALUATION
A12: Exit Year | B12: EBITDA | C12: EV (Low) | D12: EV (Base) | E12: EV (High) | F12: MOIC | G12: IRR
A13: Year 3 | B13: ='P&L'!D20 -> 2539293.5 | C13: =B13*$B$4 -> 15235761 | D13: =B13*$B$5 -> 20314348 | E13: =B13*$B$6 -> 25392935 | F13: =D13/$B$9 -> 3.0909697 | G13: =(D13/$B$9)^(1/3)-1 -> 0.45668255
A14: Year 5 | B14: ='P&L'!F20 -> 4389966.6 | C14: =B14*$B$4 -> 26339800 | D14: =B14*$B$5 -> 35119733 | E14: =B14*$B$6 -> 43899666 | F14: =D14/$B$9 -> 5.3437124 | G14: =(D14/$B$9)^(1/5)-1 -> 0.3981978
A15: Year 7 | B15: ='P&L'!H20 -> 6877942.8 | C15: =B15*$B$4 -> 41267657 | D15: =B15*$B$5 -> 55023542 | E15: =B15*$B$6 -> 68779428 | F15: =D15/$B$9 -> 8.3722158 | G15: =(D15/$B$9)^(1/7)-1 -> 0.3546726
A16: Year 10 | B16: ='P&L'!K20 -> 8926540.1 | C16: =B16*$B$4 -> 53559240 | D16: =B16*$B$5 -> 71412320 | E16: =B16*$B$6 -> 89265401 | F16: =D16/$B$9 -> 10.865883 | G16: =(D16/$B$9)^(1/10)-1 -> 0.26942341
A18: NET EXIT VALUE (9% tax on gain > 375K AED)
A19: Exit Year | B19: EV (Base) | C19: Gain | D19: Tax (9%) | E19: Net Proceeds
A20: Year 3 | B20: =D13 -> 20314348 | C20: =B20-$B$9 -> 13742188 | D20: =-IF(C20>375000,(C20-375000)*0.09,0) -> -1203046.9 | E20: =B20+D20 -> 19111301
A21: Year 5 | B21: =D14 -> 35119733 | C21: =B21-$B$9 -> 28547573 | D21: =-IF(C21>375000,(C21-375000)*0.09,0) -> -2535531.6 | E21: =B21+D21 -> 32584202
A22: Year 7 | B22: =D15 -> 55023542 | C22: =B22-$B$9 -> 48451382 | D22: =-IF(C22>375000,(C22-375000)*0.09,0) -> -4326874.4 | E22: =B22+D22 -> 50696668
A23: Year 10 | B23: =D16 -> 71412320 | C23: =B23-$B$9 -> 64840160 | D23: =-IF(C23>375000,(C23-375000)*0.09,0) -> -5801864.4 | E23: =B23+D23 -> 65610456
A25: IRR SENSITIVITY: EXIT YEAR × MULTIPLE
A26: Exit Year \ Multiple | B26: 6× | C26: 8× | D26: 10× | E26: 12× | F26: 15×
A27: Year 3 | B27: =(B13*6/$B$9)^(1/3)-1 -> 0.32348393 | C27: =(B13*8/$B$9)^(1/3)-1 -> 0.45668255 | D27: =(B13*10/$B$9)^(1/3)-1 -> 0.56916371 | E27: =(B13*12/$B$9)^(1/3)-1 -> 0.66748526 | F27: =(B13*15/$B$9)^(1/3)-1 -> 0.79624405
A28: Year 5 | B28: =(B14*6/$B$9)^(1/5)-1 -> 0.32002109 | C28: =(B14*8/$B$9)^(1/5)-1 -> 0.3981978 | D28: =(B14*10/$B$9)^(1/5)-1 -> 0.46201093 | E28: =(B14*12/$B$9)^(1/5)-1 -> 0.51630605 | F28: =(B14*15/$B$9)^(1/5)-1 -> 0.58550958
A29: Year 7 | B29: =(B15*6/$B$9)^(1/7)-1 -> 0.30012753 | C29: =(B15*8/$B$9)^(1/7)-1 -> 0.3546726 | D29: =(B15*10/$B$9)^(1/7)-1 -> 0.39855205 | E29: =(B15*12/$B$9)^(1/7)-1 -> 0.43545717 | F29: =(B15*15/$B$9)^(1/7)-1 -> 0.48195333
A30: Year 10 | B30: =(B16*6/$B$9)^(1/10)-1 -> 0.23342466 | C30: =(B16*8/$B$9)^(1/10)-1 -> 0.26942341 | D30: =(B16*10/$B$9)^(1/10)-1 -> 0.29806818 | E30: =(B16*12/$B$9)^(1/10)-1 -> 0.32195182 | F30: =(B16*15/$B$9)^(1/10)-1 -> 0.35178191
A32: EXIT STRATEGY COMPARISON
A33: Strategy | B33: Timeline | C33: Typical Multiple | D33: Pros | E33: Cons | F33: Likelihood
A34: Trade Sale (to operator) | B34: 3-7 years | C34: 6-10× | D34: Clean exit, synergies | E34: Lower multiples | F34: High
A35: PE / Fund Sale | B35: 5-7 years | C35: 8-12× | D35: Higher valuations | E35: Complex due diligence | F35: Medium
A36: Strategic (hospital group) | B36: 5-10 years | C36: 10-15× | D36: Premium pricing | E36: Long timeline | F36: Medium
A37: Management Buyout | B37: 3-5 years | C37: 5-8× | D37: Fast, known buyer | E37: Limited upside | F37: High
A38: Hold & Distribute | B38: Ongoing | C38: N/A | D38: Cash flow stream | E38: No liquidity event | F38: High
A40: CUMULATIVE CASH + EXIT VALUE (Base 8× EBITDA)
A41: Exit Year | B41: Cumul. Cash Flow | C41: Exit Value (8×) | D41: Total Value | E41: vs CapEx | F41: MOIC
A42: Year 1 | B42: ='Cash Flow & DCF'!B7 -> -6572160 | C42: ='P&L'!B20*$B$5 -> -2572000 | D42: =B42+C42 -> -9144160 | E42: =D42-$B$9 -> -15716320 | F42: =D42/$B$9 -> -1.3913477
A43: Year 2 | B43: =B42+'Cash Flow & DCF'!C7 -> -6893660 | C43: ='P&L'!C20*$B$5 -> 9422953.9 | D43: =B43+C43 -> 2529293.9 | E43: =D43-$B$9 -> -4042866.1 | F43: =D43/$B$9 -> 0.38484972
A44: Year 3 | B44: =B43+'Cash Flow & DCF'!D7 -> -5727414.7 | C44: ='P&L'!D20*$B$5 -> 20314348 | D44: =B44+C44 -> 14586933 | E44: =D44-$B$9 -> 8014773 | F44: =D44/$B$9 -> 2.2195036
A45: Year 4 | B45: =B44+'Cash Flow & DCF'!E7 -> -3322273.4 | C45: ='P&L'!E20*$B$5 -> 26822694 | D45: =B45+C45 -> 23500420 | E45: =D45-$B$9 -> 16928260 | F45: =D45/$B$9 -> 3.5757529
A46: Year 5 | B46: =B45+'Cash Flow & DCF'!F7 -> -176807.68 | C46: ='P&L'!F20*$B$5 -> 35119733 | D46: =B46+C46 -> 34942925 | E46: =D46-$B$9 -> 28370765 | F46: =D46/$B$9 -> 5.3168099
A47: Year 6 | B47: =B46+'Cash Flow & DCF'!G7 -> 3912446.2 | C47: ='P&L'!G20*$B$5 -> 45041117 | D47: =B47+C47 -> 48953564 | E47: =D47-$B$9 -> 42381404 | F47: =D47/$B$9 -> 7.4486263
A48: Year 7 | B48: =B47+'Cash Flow & DCF'!H7 -> 9130257.6 | C48: ='P&L'!H20*$B$5 -> 55023542 | D48: =B48+C48 -> 64153800 | E48: =D48-$B$9 -> 57581640 | F48: =D48/$B$9 -> 9.7614482
A49: Year 8 | B49: =B48+'Cash Flow & DCF'!I7 -> 15483570 | C49: ='P&L'!I20*$B$5 -> 61897806 | D49: =B49+C49 -> 77381376 | E49: =D49-$B$9 -> 70809216 | F49: =D49/$B$9 -> 11.774116
A50: Year 9 | B50: =B49+'Cash Flow & DCF'!J7 -> 22558195 | C50: ='P&L'!J20*$B$5 -> 66577727 | D50: =B50+C50 -> 89135923 | E50: =D50-$B$9 -> 82563763 | F50: =D50/$B$9 -> 13.562653
A51: Year 10 | B51: =B50+'Cash Flow & DCF'!K7 -> 30165162 | C51: ='P&L'!K20*$B$5 -> 71412320 | D51: =B51+C51 -> 1.0157748e+08 | E51: =D51-$B$9 -> 95005322 | F51: =D51/$B$9 -> 15.455723
A53: VALUATION GUIDELINES — Dubai Healthcare Market
A54: • Dubai private clinics typically trade at 6-10× EBITDA depending on specialization mix
A55: • Clinics with strong recurring patient base (physio/dental) command premium multiples
A56: • DHA license, brand value, and location significantly impact exit valuations
A57: • Revenue-sharing model reduces fixed cost risk → attractive to acquirers
A58: • Healthcare M&A in GCC has been growing 15-20% annually (2022-2025)
A59: • Typical PE holding period: 5-7 years with 2.5-3.5× MOIC target

Sheet Sensitivity Analysis
A1: SENSITIVITY ANALYSIS
A3: BASE CASE REFERENCES
A4: Total CapEx | B4: =CapEx!D56 -> 6572160
A5: Y5 EBITDA | B5: ='P&L'!F20 -> 4389966.6
A6: Y10 EBITDA | B6: ='P&L'!K20 -> 8926540.1
A7: Y5 Revenue | B7: =Revenue!F13 -> 23739472
A9: 1. REVENUE SENSITIVITY (±30%)
A10: Scenario | B10: Rev Adj | C10: Y5 Revenue | D10: Y5 EBITDA | E10: Y5 Margin | F10: Y10 Revenue | G10: Y10 EBITDA | H10: Y10 Margin
A11: Severe Downside | B11: -0.3 | C11: =$B$7*(1+B11) -> 16617630 | D11: =$B$5+$B$7*B11*0.5 -> 829045.86 | E11: =IF(C11<>0,D11/C11,0) -> 0.049889536 | F11: =Revenue!K13*(1+B11) -> 24582958 | G11: =$B$6+Revenue!K13*B11*0.5 -> 3658763.4 | H11: =IF(F11<>0,G11/F11,0) -> 0.14883333
A12: Downside | B12: -0.2 | C12: =$B$7*(1+B12) -> 18991577 | D12: =$B$5+$B$7*B12*0.5 -> 2016019.5 | E12: =IF(C12<>0,D12/C12,0) -> 0.10615334 | F12: =Revenue!K13*(1+B12) -> 28094809 | G12: =$B$6+Revenue!K13*B12*0.5 -> 5414689 | H12: =IF(F12<>0,G12/F12,0) -> 0.19272916
A13: Mild Downside | B13: -0.1 | C13: =$B$7*(1+B13) -> 21365525 | D13: =$B$5+$B$7*B13*0.5 -> 3202993 | E13: =IF(C13<>0,D13/C13,0) -> 0.14991408 | F13: =Revenue!K13*(1+B13) -> 31606660 | G13: =$B$6+Revenue!K13*B13*0.5 -> 7170614.5 | H13: =IF(F13<>0,G13/F13,0) -> 0.22687037
A14: BASE CASE | B14: 0 | C14: =$B$7*(1+B14) -> 23739472 | D14: =$B$5+$B$7*B14*0.5 -> 4389966.6 | E14: =IF(C14<>0,D14/C14,0) -> 0.18492268 | F14: =Revenue!K13*(1+B14) -> 35118511 | G14: =$B$6+Revenue!K13*B14*0.5 -> 8926540.1 | H14: =IF(F14<>0,G14/F14,0) -> 0.25418333
A15: Mild Upside | B15: 0.1 | C15: =$B$7*(1+B15) -> 26113419 | D15: =$B$5+$B$7*B15*0.5 -> 5576940.2 | E15: =IF(C15<>0,D15/C15,0) -> 0.21356607 | F15: =Revenue!K13*(1+B15) -> 38630362 | G15: =$B$6+Revenue!K13*B15*0.5 -> 10682466 | H15: =IF(F15<>0,G15/F15,0) -> 0.2765303
A16: Upside | B16: 0.2 | C16: =$B$7*(1+B16) -> 28487366 | D16: =$B$5+$B$7*B16*0.5 -> 6763913.8 | E16: =IF(C16<>0,D16/C16,0) -> 0.23743556 | F16: =Revenue!K13*(1+B16) -> 42142213 | G16: =$B$6+Revenue!K13*B16*0.5 -> 12438391 | H16: =IF(F16<>0,G16/F16,0) -> 0.29515277
A17: Strong Upside | B17: 0.3 | C17: =$B$7*(1+B17) -> 30861313 | D17: =$B$5+$B$7*B17*0.5 -> 7950887.4 | E17: =IF(C17<>0,D17/C17,0) -> 0.25763283 | F17: =Revenue!K13*(1+B17) -> 45654064 | G17: =$B$6+Revenue!K13*B17*0.5 -> 14194317 | H17: =IF(F17<>0,G17/F17,0) -> 0.31091025
A19: 2. CAPEX SENSITIVITY (±30%)
A20: Scenario | B20: CapEx Adj | C20: Adjusted CapEx | D20: Payback Factor | E20: 10Y NPV Impact
A21: CapEx -30% | B21: -0.3 | C21: =$B$4*(1+B21) -> 4600512 | D21: =1+B21 -> 0.7 | E21: ='Cash Flow & DCF'!L15+$B$4*B21 -> 13064732
A22: CapEx -20% | B22: -0.2 | C22: =$B$4*(1+B22) -> 5257728 | D22: =1+B22 -> 0.8 | E22: ='Cash Flow & DCF'!L15+$B$4*B22 -> 13721948
A23: CapEx -10% | B23: -0.1 | C23: =$B$4*(1+B23) -> 5914944 | D23: =1+B23 -> 0.9 | E23: ='Cash Flow & DCF'!L15+$B$4*B23 -> 14379164
A24: BASE | B24: 0 | C24: =$B$4*(1+B24) -> 6572160 | D24: =1+B24 -> 1 | E24: ='Cash Flow & DCF'!L15+$B$4*B24 -> 15036380
A25: CapEx +10% | B25: 0.1 | C25: =$B$4*(1+B25) -> 7229376 | D25: =1+B25 -> 1.1 | E25: ='Cash Flow & DCF'!L15+$B$4*B25 -> 15693596
A26: CapEx +20% | B26: 0.2 | C26: =$B$4*(1+B26) -> 7886592 | D26: =1+B26 -> 1.2 | E26: ='Cash Flow & DCF'!L15+$B$4*B26 -> 16350812
A27: CapEx +30% | B27: 0.3 | C27: =$B$4*(1+B27) -> 8543808 | D27: =1+B27 -> 1.3 | E27: ='Cash Flow & DCF'!L15+$B$4*B27 -> 17008028
A29: 3. TWO-WAY: Y5 EBITDA at Revenue × Staff Cost
A30: Rev \ Staff Adj | B30: Staff -20% | C30: Staff -10% | D30: BASE | E30: Staff +10% | F30: Staff +20%
A31: Rev -20% | B31: =$B$5+$B$7*-0.2*0.5+OpEx!F25*-0.2 -> 3915177.2 | C31: =$B$5+$B$7*-0.2*0.5+OpEx!F25*-0.1 -> 2965598.3 | D31: =$B$5+$B$7*-0.2*0.5+OpEx!F25*0 -> 2016019.5 | E31: =$B$5+$B$7*-0.2*0.5+OpEx!F25*0.1 -> 1066440.6 | F31: =$B$5+$B$7*-0.2*0.5+OpEx!F25*0.2 -> 116861.71
A32: Rev -10% | B32: =$B$5+$B$7*-0.1*0.5+OpEx!F25*-0.2 -> 5102150.8 | C32: =$B$5+$B$7*-0.1*0.5+OpEx!F25*-0.1 -> 4152571.9 | D32: =$B$5+$B$7*-0.1*0.5+OpEx!F25*0 -> 3202993 | E32: =$B$5+$B$7*-0.1*0.5+OpEx!F25*0.1 -> 2253414.2 | F32: =$B$5+$B$7*-0.1*0.5+OpEx!F25*0.2 -> 1303835.3
A33: BASE | B33: =$B$5+$B$7*0*0.5+OpEx!F25*-0.2 -> 6289124.4 | C33: =$B$5+$B$7*0*0.5+OpEx!F25*-0.1 -> 5339545.5 | D33: =$B$5+$B$7*0*0.5+OpEx!F25*0 -> 4389966.6 | E33: =$B$5+$B$7*0*0.5+OpEx!F25*0.1 -> 3440387.8 | F33: =$B$5+$B$7*0*0.5+OpEx!F25*0.2 -> 2490808.9
A34: Rev +10% | B34: =$B$5+$B$7*0.1*0.5+OpEx!F25*-0.2 -> 7476098 | C34: =$B$5+$B$7*0.1*0.5+OpEx!F25*-0.1 -> 6526519.1 | D34: =$B$5+$B$7*0.1*0.5+OpEx!F25*0 -> 5576940.2 | E34: =$B$5+$B$7*0.1*0.5+OpEx!F25*0.1 -> 4627361.4 | F34: =$B$5+$B$7*0.1*0.5+OpEx!F25*0.2 -> 3677782.5
A35: Rev +20% | B35: =$B$5+$B$7*0.2*0.5+OpEx!F25*-0.2 -> 8663071.6 | C35: =$B$5+$B$7*0.2*0.5+OpEx!F25*-0.1 -> 7713492.7 | D35: =$B$5+$B$7*0.2*0.5+OpEx!F25*0 -> 6763913.8 | E35: =$B$5+$B$7*0.2*0.5+OpEx!F25*0.1 -> 5814334.9 | F35: =$B$5+$B$7*0.2*0.5+OpEx!F25*0.2 -> 4864756.1
A37: Values = Y5 EBITDA (AED). Staff adj applies to total OpEx staff costs.
A38: 4. STAFFING COST SCENARIOS
A39: Scenario | B39: Rev-Share Adj | C39: Fixed Staff Adj | D39: Y3 EBITDA Impact | E39: Y5 EBITDA Impact | F39: Description
A40: Base Case | B40: 0% | C40: 0% | D40: 0 | E40: 0 | F40: Current model assumptions
A41: Higher Sharing Rates | B41: +5pp | C41: 0% | D41: =-'P&L'!D4*0.05 -> -892676.93 | E41: =-'P&L'!F4*0.05 -> -1186973.6 | F41: Specialist premium (demand-driven)
A42: Full Market Salaries | B42: 0% | C42: +25% | D42: ='P&L'!D12*0.25 -> -175219.2 | E42: ='P&L'!F12*0.25 -> -189517.09 | F42: All staff at market midpoint
A43: Staff Expansion (+2 FTE) | B43: 0% | C43: +240K | D43: -240000 | E43: -240000 | F43: Growth requires additional hires
A44: Efficiency Gain (-1 FTE) | B44: 0% | C44: -120K | D44: 120000 | E44: 120000 | F44: Process optimization / tech adoption
A45: 5. BREAKEVEN THRESHOLDS
A46: Metric | B46: Value | C46: Calculation | D46: Notes
A47: Monthly BE Revenue (AED) | B47: =-('P&L'!B16+'P&L'!B17+'P&L'!B18+'P&L'!B19)/'P&L'!B8/12 -> 244505.78 | C47: Fixed Costs ÷ Gross Margin | D47: Revenue needed to cover all fixed costs
A48: BE Visits / Month | B48: =B47/(Revenue!B13/(Assumptions!D35*Assumptions!B242)) -> 277.7948 | C48: BE Revenue ÷ Revenue per Visit | D48: Monthly patient count to break even
A49: Breakeven Utilization (%) | B49: =B48/(Assumptions!D35/12) -> 0.11513378 | C49: BE Patients ÷ Monthly Capacity | D49: Capacity needed to break even
A50: Months to Operational BE | B50: =IFERROR(MATCH(1,INDEX(('Monthly P&L'!B18:M18>0)*1,,),0),">12") -> 9 | C50: First month with positive EBITDA | D50: When cumulative monthly P&L turns positive
A51: Months to Investment Payback | B51: =IF(COUNTIF('Cash Flow & DCF'!C8:L8,">0")=0,"N/A",(MATCH(1,INDEX(('Cash Flow & DCF'!C8:L8>0)*1,,),0)-1)*12+(-INDEX('Cash Flow & DCF'!B8:K8,MATCH(1,INDEX(('Cash Flow & DCF'!C8:L8>0)*1,,),0)))/(INDEX('Cash Flow & DCF'!C8:L8,MATCH(1,INDEX(('Cash Flow & DCF'!C8:L8>0)*1,,),0))-INDEX('Cash Flow & DCF'!B8:K8,MATCH(1,INDEX(('Cash Flow & DCF'!C8:L8>0)*1,,),0)))*12) -> 48.518846 | C51: Interpolated from annual cumulative CF | D51: Time to recover initial investment
A53: 6. MANAGEMENT MODE IMPACT
A54: Metric | B54: Self-Managed | C54: External (7%) | D54: Difference | E54: Notes
A55: Y1 Management Fee | B55: 0 | C55: =Revenue!B13*Assumptions!$B$123 -> 535164 | D55: =B55-C55 -> -535164 | E55: Annual cost of brand
A56: Y5 Management Fee | B56: 0 | C56: =Revenue!F13*Assumptions!$B$123*(1+Assumptions!$B$124)^4 -> 1695248.4 | D56: =B56-C56 -> -1695248.4 | E56: With escalation
A57: Y1 EBITDA Impact | B57: 0 | C57: =-C55 -> -535164 | D57: =B57-C57 -> 535164 | E57: Direct EBITDA reduction
A58: 10Y Cumulative Fee | B58: 0 | C58: =SUM(Revenue!B13:K13)*Assumptions!$B$123*1.025 -> 17415784 | D58: =B58-C58 -> -17415784 | E58: Approx cumulative

Sheet Patient Acquisition
A1: PATIENT ACQUISITION — COHORT + STEP-FUNCTION MODEL
A3: YEAR 1 MONTHLY PATIENT TRAFFIC
A4: Metric | B4: M1 | C4: M2 | D4: M3 | E4: M4 | F4: M5 | G4: M6 | H4: M7 | I4: M8 | J4: M9 | K4: M10 | L4: M11 | M4: M12
A5: Monthly Capacity (slots) | B5: =Assumptions!$D$35/12 -> 2412.8 | C5: =Assumptions!$D$35/12 -> 2412.8 | D5: =Assumptions!$D$35/12 -> 2412.8 | E5: =Assumptions!$D$35/12 -> 2412.8 | F5: =Assumptions!$D$35/12 -> 2412.8 | G5: =Assumptions!$D$35/12 -> 2412.8 | H5: =Assumptions!$D$35/12 -> 2412.8 | I5: =Assumptions!$D$35/12 -> 2412.8 | ... M5: =Assumptions!$D$35/12 -> 2412.8
A6: Patients (launch ramp) | B6: =B5*Assumptions!$B$155*1/12 -> 60.32 | C6: =C5*Assumptions!$B$155*2/12 -> 120.64 | D6: =D5*Assumptions!$B$155*3/12 -> 180.96 | E6: =E5*Assumptions!$B$155*4/12 -> 241.28 | F6: =F5*Assumptions!$B$155*5/12 -> 301.6 | G6: =G5*Assumptions!$B$155*6/12 -> 361.92 | H6: =H5*Assumptions!$B$155*7/12 -> 422.24 | I6: =I5*Assumptions!$B$155*8/12 -> 482.56 | J6: =J5*Assumptions!$B$155*9/12 -> 542.88 | K6: =K5*Assumptions!$B$155*10/12 -> 603.2 | L6: =L5*Assumptions!$B$155*11/12 -> 663.52 | M6: =M5*Assumptions!$B$155*12/12 -> 723.84
A7: Target (= launch ramp, no monthly GAP) | B7: =B6 -> 60.32 | C7: =C6 -> 120.64 | D7: =D6 -> 180.96 | E7: =E6 -> 241.28 | F7: =F6 -> 301.6 | G7: =G6 -> 361.92 | H7: =H6 -> 422.24 | I7: =I6 -> 482.56 | ... M7: =M6 -> 723.84
A8: GAP Patients (marketing-driven) | B8: =MAX(0,B7-B6) -> 0 | C8: =MAX(0,C7-C6) -> 0 | D8: =MAX(0,D7-D6) -> 0 | E8: =MAX(0,E7-E6) -> 0 | F8: =MAX(0,F7-F6) -> 0 | G8: =MAX(0,G7-G6) -> 0 | H8: =MAX(0,H7-H6) -> 0 | I8: =MAX(0,I7-I6) -> 0 | ... M8: =MAX(0,M7-M6) -> 0
A9: TOTAL Patients | B9: =B6+B8 -> 60.32 | C9: =C6+C8 -> 120.64 | D9: =D6+D8 -> 180.96 | E9: =E6+E8 -> 241.28 | F9: =F6+F8 -> 301.6 | G9: =G6+G8 -> 361.92 | H9: =H6+H8 -> 422.24 | I9: =I6+I8 -> 482.56 | ... M9: =M6+M8 -> 723.84
A10: Utilization Rate | B10: =B9/B5 -> 0.025 | C10: =C9/C5 -> 0.05 | D10: =D9/D5 -> 0.075 | E10: =E9/E5 -> 0.1 | F10: =F9/F5 -> 0.125 | G10: =G9/G5 -> 0.15 | H10: =H9/H5 -> 0.175 | I10: =I9/I5 -> 0.2 | ... M10: =M9/M5 -> 0.3
A12: MARKETING BUDGET TO FILL GAP (Year 1)
A13: Metric | B13: M1 | C13: M2 | D13: M3 | E13: M4 | F13: M5 | G13: M6 | H13: M7 | I13: M8 | J13: M9 | K13: M10 | L13: M11 | M13: M12
A14: Cost per Incremental Patient (AED) | B14: =1000/Assumptions!$B$153 -> 1250 | C14: =1000/Assumptions!$B$153 -> 1250 | D14: =1000/Assumptions!$B$153 -> 1250 | E14: =1000/Assumptions!$B$153 -> 1250 | F14: =1000/Assumptions!$B$153 -> 1250 | G14: =1000/Assumptions!$B$153 -> 1250 | H14: =1000/Assumptions!$B$153 -> 1250 | I14: =1000/Assumptions!$B$153 -> 1250 | ... M14: =1000/Assumptions!$B$153 -> 1250
A15: Marketing Spend to Fill GAP | B15: =B8*B14 -> 0 | C15: =C8*C14 -> 0 | D15: =D8*D14 -> 0 | E15: =E8*E14 -> 0 | F15: =F8*F14 -> 0 | G15: =G8*G14 -> 0 | H15: =H8*H14 -> 0 | I15: =I8*I14 -> 0 | ... M15: =M8*M14 -> 0
A16: Base Marketing (brand/agency) | B16: =Assumptions!$B$91/12 -> 36000 | C16: =Assumptions!$B$91/12 -> 36000 | D16: =Assumptions!$B$91/12 -> 36000 | E16: =Assumptions!$B$91/12 -> 36000 | F16: =Assumptions!$B$91/12 -> 36000 | G16: =Assumptions!$B$91/12 -> 36000 | H16: =Assumptions!$B$91/12 -> 36000 | I16: =Assumptions!$B$91/12 -> 36000 | ... M16: =Assumptions!$B$91/12 -> 36000
A17: TOTAL Marketing Budget | B17: =B15+B16 -> 36000 | C17: =C15+C16 -> 36000 | D17: =D15+D16 -> 36000 | E17: =E15+E16 -> 36000 | F17: =F15+F16 -> 36000 | G17: =G15+G16 -> 36000 | H17: =H15+H16 -> 36000 | I17: =I15+I16 -> 36000 | ... M17: =M15+M16 -> 36000
A18: Note: Uncapped GAP spend above. Annual cap applied in row 31 (Assumptions!B146)
A19: ANNUAL COHORT MODEL (10 Years)
A20: Metric | B20: Y1 | C20: Y2 | D20: Y3 | E20: Y4 | F20: Y5 | G20: Y6 | H20: Y7 | I20: Y8 | J20: Y9 | K20: Y10
A21: Annual Visit Capacity | B21: =Assumptions!B190 -> 28953.6 | C21: =Assumptions!C190 -> 30310.8 | D21: =Assumptions!D190 -> 31668 | E21: =Assumptions!E190 -> 38001.6 | F21: =Assumptions!F190 -> 41620.8 | G21: =Assumptions!G190 -> 44335.2 | H21: =Assumptions!H190 -> 49311.6 | I21: =Assumptions!I190 -> 50668.8 | ... K21: =Assumptions!K190 -> 50668.8
A22: Total Visits (cohort-derived) | B22: =Assumptions!B231 -> 12741.56 | C22: =Assumptions!C231 -> 20197.32 | D22: =Assumptions!D231 -> 27653.08 | E22: =Assumptions!E231 -> 30824.56 | F22: =Assumptions!F231 -> 33996.04 | G22: =Assumptions!G231 -> 38280.32 | H22: =Assumptions!H231 -> 42508.96 | I22: =Assumptions!I231 -> 42508.96 | ... K22: =Assumptions!K231 -> 42508.96
A23: Utilization (%) | B23: =B22/B21 -> 0.44006825 | C23: =C22/C21 -> 0.66634071 | D23: =D22/D21 -> 0.87321839 | E23: =E22/E21 -> 0.81113848 | F23: =F22/F21 -> 0.8168041 | G23: =G22/G21 -> 0.86342951 | H23: =H22/H21 -> 0.86204788 | I23: =I22/I21 -> 0.83895731 | ... K23: =K22/K21 -> 0.83895731
A25: UNIQUE PATIENTS
A26: Total Unique Patients | B26: =Assumptions!B230 -> 2071.7984 | C26: =Assumptions!C230 -> 3284.1171 | D26: =Assumptions!D230 -> 4496.4358 | E26: =Assumptions!E230 -> 5012.1236 | F26: =Assumptions!F230 -> 5527.8114 | G26: =Assumptions!G230 -> 6224.4423 | H26: =Assumptions!H230 -> 6912.026 | I26: =Assumptions!I230 -> 6912.026 | ... K26: =Assumptions!K230 -> 6912.026
A27: Retained from Prior Year | B27: =Assumptions!B226 -> 0 | C27: =Assumptions!C226 -> 907.44769 | D27: =Assumptions!D226 -> 1481.1368 | E27: =Assumptions!E226 -> 2086.3462 | F27: =Assumptions!F226 -> 2390.7829 | G27: =Assumptions!G226 -> 2708.6276 | H27: =Assumptions!H226 -> 3093.0205 | I27: =Assumptions!I226 -> 3382.4002 | ... K27: =Assumptions!K226 -> 3552.1558
A28: Referral (word-of-mouth) | B28: =Assumptions!B227 -> 0 | C28: =Assumptions!C227 -> 326.68117 | D28: =Assumptions!D227 -> 533.20925 | E28: =Assumptions!E227 -> 751.08463 | F28: =Assumptions!F227 -> 860.68186 | G28: =Assumptions!G227 -> 975.10593 | H28: =Assumptions!H227 -> 1113.4874 | I28: =Assumptions!I227 -> 1217.6641 | ... K28: =Assumptions!K227 -> 1278.7761
A29: Walk-in / Organic New | B29: =Assumptions!B228 -> 820 | C29: =Assumptions!C228 -> 990.15 | D29: =Assumptions!D228 -> 1039.6575 | E29: =Assumptions!E228 -> 1091.6404 | F29: =Assumptions!F228 -> 1146.2224 | G29: =Assumptions!G228 -> 1203.5335 | H29: =Assumptions!H228 -> 1263.7102 | I29: =Assumptions!I228 -> 1326.8957 | ... K29: =Assumptions!K228 -> 1462.9025
A30: Marketing (paid acquisition) | B30: =Assumptions!B229 -> 1251.7984 | C30: =Assumptions!C229 -> 1059.8382 | D30: =Assumptions!D229 -> 1442.4322 | E30: =Assumptions!E229 -> 1083.0524 | F30: =Assumptions!F229 -> 1130.1242 | G30: =Assumptions!G229 -> 1337.1753 | H30: =Assumptions!H229 -> 1441.808 | I30: =Assumptions!I229 -> 985.06606 | ... K30: =Assumptions!K229 -> 618.19158
A31: CHECK: Δ (should = 0) | B31: =B27+B28+B29+B30-B26 -> 0 | C31: =C27+C28+C29+C30-C26 -> 0 | D31: =D27+D28+D29+D30-D26 -> 0 | E31: =E27+E28+E29+E30-E26 -> 0 | F31: =F27+F28+F29+F30-F26 -> 0 | G31: =G27+G28+G29+G30-G26 -> 0 | H31: =H27+H28+H29+H30-H26 -> 0 | I31: =I27+I28+I29+I30-I26 -> 0 | ... K31: =K27+K28+K29+K30-K26 -> 0
A32: VISITS BY SOURCE
A33: Visits — Retained Patients | B33: =B27*Assumptions!$B$282 -> 0 | C33: =C27*Assumptions!$B$282 -> 5580.8033 | D33: =D27*Assumptions!$B$282 -> 9108.9913 | E33: =E27*Assumptions!$B$282 -> 12831.029 | F33: =F27*Assumptions!$B$282 -> 14703.315 | G33: =G27*Assumptions!$B$282 -> 16658.06 | H33: =H27*Assumptions!$B$282 -> 19022.076 | I33: =I27*Assumptions!$B$282 -> 20801.761 | ... K33: =K27*Assumptions!$B$282 -> 21845.758
A34: Visits — Referral + Walk-in | B34: =(B28+B29)*Assumptions!$B$282 -> 5043 | C34: =(C28+C29)*Assumptions!$B$282 -> 8098.5117 | D34: =(D28+D29)*Assumptions!$B$282 -> 9673.1305 | E34: =(E28+E29)*Assumptions!$B$282 -> 11332.759 | F34: =(F28+F29)*Assumptions!$B$282 -> 12342.461 | G34: =(G28+G29)*Assumptions!$B$282 -> 13398.633 | H34: =(H28+H29)*Assumptions!$B$282 -> 14619.765 | I34: =(I28+I29)*Assumptions!$B$282 -> 15649.043 | ... K34: =(K28+K29)*Assumptions!$B$282 -> 16861.323
A35: Visits — Marketing | B35: =B30*Assumptions!$B$282 -> 7698.56 | C35: =C30*Assumptions!$B$282 -> 6518.005 | D35: =D30*Assumptions!$B$282 -> 8870.9582 | E35: =E30*Assumptions!$B$282 -> 6660.7721 | F35: =F30*Assumptions!$B$282 -> 6950.2637 | G35: =G30*Assumptions!$B$282 -> 8223.6278 | H35: =H30*Assumptions!$B$282 -> 8867.1189 | I35: =I30*Assumptions!$B$282 -> 6058.1563 | ... K35: =K30*Assumptions!$B$282 -> 3801.8782
A36: Total (check = row 22) | B36: =B33+B34+B35 -> 12741.56 | C36: =C33+C34+C35 -> 20197.32 | D36: =D33+D34+D35 -> 27653.08 | E36: =E33+E34+E35 -> 30824.56 | F36: =F33+F34+F35 -> 33996.04 | G36: =G33+G34+G35 -> 38280.32 | H36: =H33+H34+H35 -> 42508.96 | I36: =I33+I34+I35 -> 42508.96 | ... K36: =K33+K34+K35 -> 42508.96
A38: UNIT ECONOMICS — COHORT-BASED
A39: Metric | B39: Y1 | C39: Y2 | D39: Y3 | E39: Y4 | F39: Y5 | G39: Y6 | H39: Y7 | I39: Y8 | J39: Y9 | K39: Y10
A40: Avg Revenue per Visit | B40: =IF(B22>0,Revenue!B13/B22,0) -> 600.02072 | C40: =IF(C22>0,Revenue!C13/C22,0) -> 620.2209 | D40: =IF(D22>0,Revenue!D13/D22,0) -> 645.62568 | E40: =IF(E22>0,Revenue!E13/E22,0) -> 672.78228 | F40: =IF(F22>0,Revenue!F13/F22,0) -> 698.30109 | G40: =IF(G22>0,Revenue!G13/G22,0) -> 722.30058 | H40: =IF(H22>0,Revenue!H13/H22,0) -> 734.43877 | I40: =IF(I22>0,Revenue!I13/I22,0) -> 763.81632 | ... K40: =IF(K22>0,Revenue!K13/K22,0) -> 826.14374
A41: Avg Revenue per Patient/yr | B41: =B40*Assumptions!$B$282 -> 3690.1274 | C41: =C40*Assumptions!$B$282 -> 3814.3585 | D41: =D40*Assumptions!$B$282 -> 3970.5979 | E41: =E40*Assumptions!$B$282 -> 4137.611 | F41: =F40*Assumptions!$B$282 -> 4294.5517 | G41: =G40*Assumptions!$B$282 -> 4442.1485 | H41: =H40*Assumptions!$B$282 -> 4516.7985 | I41: =I40*Assumptions!$B$282 -> 4697.4704 | ... K41: =K40*Assumptions!$B$282 -> 5080.784
A42: Annual Marketing Budget | B42: =B95 -> 1529040 | C42: =C95 -> 1989935.4 | D42: =D95 -> 2585251.6 | E42: =E95 -> 2297361.9 | F42: =F95 -> 2437952.6 | G42: =G95 -> 2774128.7 | H42: =H95 -> 3001678.3 | I42: =I95 -> 2537580.1 | ... K42: =K95 -> 2186690
A43: CAC per Marketing Patient (pure) | B43: =Assumptions!$B$262 -> 1200 | C43: =Assumptions!$B$262 -> 1200 | D43: =Assumptions!$B$262 -> 1200 | E43: =Assumptions!$B$262 -> 1200 | F43: =Assumptions!$B$262 -> 1200 | G43: =Assumptions!$B$262 -> 1200 | H43: =Assumptions!$B$262 -> 1200 | I43: =Assumptions!$B$262 -> 1200 | ... K43: =Assumptions!$B$262 -> 1200
A44: Blended Cost per Mkt Patient | B44: =IF(B30>0,B42/B30,0) -> 1221.4747 | C44: =IF(C30>0,C42/C30,0) -> 1877.5841 | D44: =IF(D30>0,D42/D30,0) -> 1792.2864 | E44: =IF(E30>0,E42/E30,0) -> 2121.1919 | F44: =IF(F30>0,F42/F30,0) -> 2157.2431 | G44: =IF(G30>0,G42/G30,0) -> 2074.6186 | H44: =IF(H30>0,H42/H30,0) -> 2081.8849 | I44: =IF(I30>0,I42/I30,0) -> 2576.0507 | ... K44: =IF(K30>0,K42/K30,0) -> 3537.2367
A45: Patient Lifetime (years) | B45: =1/(1-Assumptions!B250) -> 2.5 | C45: =1/(1-Assumptions!C250) -> 2.6315789 | D45: =1/(1-Assumptions!D250) -> 2.7777778 | E45: =1/(1-Assumptions!E250) -> 2.9411765 | F45: =1/(1-Assumptions!F250) -> 3.125 | G45: =1/(1-Assumptions!G250) -> 3.3333333 | H45: =1/(1-Assumptions!H250) -> 3.5714286 | I45: =1/(1-Assumptions!I250) -> 3.8461538 | ... K45: =1/(1-Assumptions!K250) -> 4.5454545
A46: Patient LTV (lifetime revenue) | B46: =B41*B45 -> 9225.3186 | C46: =C41*C45 -> 10037.786 | D46: =D41*D45 -> 11029.439 | E46: =E41*E45 -> 12169.444 | F46: =F41*F45 -> 13420.474 | G46: =G41*G45 -> 14807.162 | H46: =H41*H45 -> 16131.423 | I46: =I41*I45 -> 18067.194 | ... K46: =K41*K45 -> 23094.473
A47: LTV:CAC Ratio | B47: =IF(B43>0,B46/B43,0) -> 7.6877655 | C47: =IF(C43>0,C46/C43,0) -> 8.3648214 | D47: =IF(D43>0,D46/D43,0) -> 9.1911989 | E47: =IF(E43>0,E46/E43,0) -> 10.141203 | F47: =IF(F43>0,F46/F43,0) -> 11.183728 | G47: =IF(G43>0,G46/G43,0) -> 12.339302 | H47: =IF(H43>0,H46/H43,0) -> 13.442853 | I47: =IF(I43>0,I46/I43,0) -> 15.055995 | ... K47: =IF(K43>0,K46/K43,0) -> 19.245394
A48: CAC Payback (months) | B48: =IF(B41>0,B43/(B41/12),0) -> 3.9023043 | C48: =IF(C41>0,C43/(C41/12),0) -> 3.7752088 | D48: =IF(D41>0,D43/(D41/12),0) -> 3.6266578 | E48: =IF(E41>0,E43/(E41/12),0) -> 3.4802692 | F48: =IF(F41>0,F43/(F41/12),0) -> 3.3530857 | G48: =IF(G41>0,G43/(G41/12),0) -> 3.2416746 | H48: =IF(H41>0,H43/(H41/12),0) -> 3.1880989 | I48: =IF(I41>0,I43/(I41/12),0) -> 3.0654797 | ... K48: =IF(K41>0,K43/(K41/12),0) -> 2.8342083
A49: Blended CAC (all new patients) | B49: =IF((B28+B29+B30)>0,B42/(B28+B29+B30),0) -> 738.02549 | C49: =IF((C28+C29+C30)>0,C42/(C28+C29+C30),0) -> 837.27901 | D49: =IF((D28+D29+D30)>0,D42/(D28+D29+D30),0) -> 857.37821 | E49: =IF((E28+E29+E30)>0,E42/(E28+E29+E30),0) -> 785.21419 | F49: =IF((F28+F29+F30)>0,F42/(F28+F29+F30),0) -> 777.1535 | G49: =IF((G28+G29+G30)>0,G42/(G28+G29+G30),0) -> 789.04293 | H49: =IF((H28+H29+H30)>0,H42/(H28+H29+H30),0) -> 785.98427 | I49: =IF((I28+I29+I30)>0,I42/(I28+I29+I30),0) -> 718.93743 | ... K49: =IF((K28+K29+K30)>0,K42/(K28+K29+K30),0) -> 650.82573
A50: Cost per Marketing Visit | B50: =IF(B35>0,B42/B35,0) -> 198.61377 | C50: =IF(C35>0,C42/C35,0) -> 305.29823 | D50: =IF(D35>0,D42/D35,0) -> 291.42868 | E50: =IF(E35>0,E42/E35,0) -> 344.90925 | F50: =IF(F35>0,F42/F35,0) -> 350.77124 | G50: =IF(G35>0,G42/G35,0) -> 337.33637 | H50: =IF(H35>0,H42/H35,0) -> 338.51787 | I50: =IF(I35>0,I42/I35,0) -> 418.87003 | ... K50: =IF(K35>0,K42/K35,0) -> 575.16044
A51: ROMI (Return on Marketing Investment) | B51: =IF(B42>0,B35*B40/B42,0) -> 3.0210429 | C51: =IF(C42>0,C35*C40/C42,0) -> 2.0315247 | D51: =IF(D42>0,D35*D40/D42,0) -> 2.2153814 | E51: =IF(E42>0,E35*E40/E42,0) -> 1.9506066 | F51: =IF(F42>0,F35*F40/F42,0) -> 1.9907592 | G51: =IF(G42>0,G35*G40/G42,0) -> 2.141188 | H51: =IF(H42>0,H35*H40/H42,0) -> 2.1695716 | I51: =IF(I42>0,I35*I40/I42,0) -> 1.8235163 | ... K51: =IF(K42>0,K35*K40/K42,0) -> 1.4363709
A53: VISITS BY DEPARTMENT & CHANNEL
A54: Department | B54: Y1 | C54: Y2 | D54: Y3 | E54: Y4 | F54: Y5 | G54: Y6 | H54: Y7 | I54: Y8 | J54: Y9 | K54: Y10
A55: Physio Clinic | B55: =MIN(B22*Assumptions!$B$285,MIN(Assumptions!C186,Assumptions!$D$40)) -> 7251.2943 | C55: =MIN(C22*Assumptions!$B$285,MIN(Assumptions!D186,Assumptions!$D$40)) -> 11494.41 | D55: =MIN(D22*Assumptions!$B$285,MIN(Assumptions!E186,Assumptions!$D$40)) -> 15737.525 | E55: =MIN(E22*Assumptions!$B$285,MIN(Assumptions!F186,Assumptions!$D$40)) -> 17542.433 | F55: =MIN(F22*Assumptions!$B$285,MIN(Assumptions!G186,Assumptions!$D$40)) -> 19347.34 | G55: =MIN(G22*Assumptions!$B$285,MIN(Assumptions!H186,Assumptions!$D$40)) -> 21785.548 | H55: =MIN(H22*Assumptions!$B$285,MIN(Assumptions!I186,Assumptions!$D$40)) -> 24192.091 | I55: =MIN(I22*Assumptions!$B$285,MIN(Assumptions!J186,Assumptions!$D$40)) -> 24192.091 | ... K55: =MIN(K22*Assumptions!$B$285,MIN(Assumptions!L186,Assumptions!$D$40)) -> 24192.091
A56: Unique patients | B56: =B55/Assumptions!$B$254 -> 725.12943 | C56: =C55/Assumptions!$B$254 -> 1149.441 | D56: =D55/Assumptions!$B$254 -> 1573.7525 | E56: =E55/Assumptions!$B$254 -> 1754.2433 | F56: =F55/Assumptions!$B$254 -> 1934.734 | G56: =G55/Assumptions!$B$254 -> 2178.5548 | H56: =H55/Assumptions!$B$254 -> 2419.2091 | I56: =I55/Assumptions!$B$254 -> 2419.2091 | ... K56: =K55/Assumptions!$B$254 -> 2419.2091
A57: Retained visits | B57: =IF(B26>0,B55*B27/B26,0) -> 0 | C57: =IF(C26>0,C55*C27/C26,0) -> 3176.0669 | D57: =IF(D26>0,D55*D27/D26,0) -> 5183.9788 | E57: =IF(E26>0,E55*E27/E26,0) -> 7302.2117 | F57: =IF(F26>0,F55*F27/F26,0) -> 8367.7403 | G57: =IF(G26>0,G55*G27/G26,0) -> 9480.1965 | H57: =IF(H26>0,H55*H27/H26,0) -> 10825.572 | I57: =IF(I26>0,I55*I27/I26,0) -> 11838.401 | ... K57: =IF(K26>0,K55*K27/K26,0) -> 12432.545
A58: New Organic+Referral | B58: =IF(B26>0,B55*(B29+B28)/B26,0) -> 2870 | C58: =IF(C26>0,C55*(C29+C28)/C26,0) -> 4608.9091 | D58: =IF(D26>0,D55*(D29+D28)/D26,0) -> 5505.0336 | E58: =IF(E26>0,E55*(E29+E28)/E26,0) -> 6449.5375 | F58: =IF(F26>0,F55*(F29+F28)/F26,0) -> 7024.1649 | G58: =IF(G26>0,G55*(G29+G28)/G26,0) -> 7625.238 | H58: =IF(H26>0,H55*(H29+H28)/H26,0) -> 8320.1915 | I58: =IF(I26>0,I55*(I29+I28)/I26,0) -> 8905.9592 | ... K58: =IF(K26>0,K55*(K29+K28)/K26,0) -> 9595.8751
A59: New marketing | B59: =IF(B26>0,B55*B30/B26,0) -> 4381.2943 | C59: =IF(C26>0,C55*C30/C26,0) -> 3709.4338 | D59: =IF(D26>0,D55*D30/D26,0) -> 5048.5128 | E59: =IF(E26>0,E55*E30/E26,0) -> 3790.6833 | F59: =IF(F26>0,F55*F30/F26,0) -> 3955.4346 | G59: =IF(G26>0,G55*G30/G26,0) -> 4680.1134 | H59: =IF(H26>0,H55*H30/H26,0) -> 5046.3279 | I59: =IF(I26>0,I55*I30/I26,0) -> 3447.7312 | ... K59: =IF(K26>0,K55*K30/K26,0) -> 2163.6705
A61: Dental Clinic | B61: =MIN(B22*Assumptions!$B$286,MIN(Assumptions!C187,Assumptions!$D$41)) -> 1553.8488 | C61: =MIN(C22*Assumptions!$B$286,MIN(Assumptions!D187,Assumptions!$D$41)) -> 2463.0878 | D61: =MIN(D22*Assumptions!$B$286,MIN(Assumptions!E187,Assumptions!$D$41)) -> 3372.3268 | E61: =MIN(E22*Assumptions!$B$286,MIN(Assumptions!F187,Assumptions!$D$41)) -> 3759.0927 | F61: =MIN(F22*Assumptions!$B$286,MIN(Assumptions!G187,Assumptions!$D$41)) -> 4145.8585 | G61: =MIN(G22*Assumptions!$B$286,MIN(Assumptions!H187,Assumptions!$D$41)) -> 4668.3317 | H61: =MIN(H22*Assumptions!$B$286,MIN(Assumptions!I187,Assumptions!$D$41)) -> 5007.6 | I61: =MIN(I22*Assumptions!$B$286,MIN(Assumptions!J187,Assumptions!$D$41)) -> 5007.6 | ... K61: =MIN(K22*Assumptions!$B$286,MIN(Assumptions!L187,Assumptions!$D$41)) -> 5007.6
A62: Unique patients | B62: =B61/Assumptions!$B$255 -> 517.94959 | C62: =C61/Assumptions!$B$255 -> 821.02927 | D62: =D61/Assumptions!$B$255 -> 1124.1089 | E62: =E61/Assumptions!$B$255 -> 1253.0309 | F62: =F61/Assumptions!$B$255 -> 1381.9528 | G62: =G61/Assumptions!$B$255 -> 1556.1106 | H62: =H61/Assumptions!$B$255 -> 1669.2 | I62: =I61/Assumptions!$B$255 -> 1669.2 | ... K62: =K61/Assumptions!$B$255 -> 1669.2
A63: Retained visits | B63: =IF(B26>0,B61*B27/B26,0) -> 0 | C63: =IF(C26>0,C61*C27/C26,0) -> 680.58577 | D63: =IF(D26>0,D61*D27/D26,0) -> 1110.8526 | E63: =IF(E26>0,E61*E27/E26,0) -> 1564.7596 | F63: =IF(F26>0,F61*F27/F26,0) -> 1793.0872 | G63: =IF(G26>0,G61*G27/G26,0) -> 2031.4707 | H63: =IF(H26>0,H61*H27/H26,0) -> 2240.8205 | I63: =IF(I26>0,I61*I27/I26,0) -> 2450.4692 | ... K63: =IF(K26>0,K61*K27/K26,0) -> 2573.4532
A64: New Organic+Referral | B64: =IF(B26>0,B61*(B29+B28)/B26,0) -> 615 | C64: =IF(C26>0,C61*(C29+C28)/C26,0) -> 987.62338 | D64: =IF(D26>0,D61*(D29+D28)/D26,0) -> 1179.6501 | E64: =IF(E26>0,E61*(E29+E28)/E26,0) -> 1382.0438 | F64: =IF(F26>0,F61*(F29+F28)/F26,0) -> 1505.1782 | G64: =IF(G26>0,G61*(G29+G28)/G26,0) -> 1633.9796 | H64: =IF(H26>0,H61*(H29+H28)/H26,0) -> 1722.2236 | I64: =IF(I26>0,I61*(I29+I28)/I26,0) -> 1843.4736 | ... K64: =IF(K26>0,K61*(K29+K28)/K26,0) -> 1986.2816
A65: New marketing | B65: =IF(B26>0,B61*B30/B26,0) -> 938.84878 | C65: =IF(C26>0,C61*C30/C26,0) -> 794.87866 | D65: =IF(D26>0,D61*D30/D26,0) -> 1081.8242 | E65: =IF(E26>0,E61*E30/E26,0) -> 812.28928 | F65: =IF(F26>0,F61*F30/F26,0) -> 847.59314 | G65: =IF(G26>0,G61*G30/G26,0) -> 1002.8814 | H65: =IF(H26>0,H61*H30/H26,0) -> 1044.5559 | I65: =IF(I26>0,I61*I30/I26,0) -> 713.65715 | ... K65: =IF(K26>0,K61*K30/K26,0) -> 447.86524
A67: GP | B67: =MIN(B22*Assumptions!$B$287*Assumptions!$B$315,Assumptions!C189*Assumptions!$B$315,Assumptions!$D$43*Assumptions!$B$315) -> 517.94959 | C67: =MIN(C22*Assumptions!$B$287*Assumptions!$B$315,Assumptions!D189*Assumptions!$B$315,Assumptions!$D$43*Assumptions!$B$315) -> 821.02927 | D67: =MIN(D22*Assumptions!$B$287*Assumptions!$B$315,Assumptions!E189*Assumptions!$B$315,Assumptions!$D$43*Assumptions!$B$315) -> 1124.1089 | E67: =MIN(E22*Assumptions!$B$287*Assumptions!$B$315,Assumptions!F189*Assumptions!$B$315,Assumptions!$D$43*Assumptions!$B$315) -> 1253.0309 | F67: =MIN(F22*Assumptions!$B$287*Assumptions!$B$315,Assumptions!G189*Assumptions!$B$315,Assumptions!$D$43*Assumptions!$B$315) -> 1381.9528 | G67: =MIN(G22*Assumptions!$B$287*Assumptions!$B$315,Assumptions!H189*Assumptions!$B$315,Assumptions!$D$43*Assumptions!$B$315) -> 1556.1106 | H67: =MIN(H22*Assumptions!$B$287*Assumptions!$B$315,Assumptions!I189*Assumptions!$B$315,Assumptions!$D$43*Assumptions!$B$315) -> 1728.0065 | I67: =MIN(I22*Assumptions!$B$287*Assumptions!$B$315,Assumptions!J189*Assumptions!$B$315,Assumptions!$D$43*Assumptions!$B$315) -> 1728.0065 | ... K67: =MIN(K22*Assumptions!$B$287*Assumptions!$B$315,Assumptions!L189*Assumptions!$B$315,Assumptions!$D$43*Assumptions!$B$315) -> 1728.0065
A68: Unique patients | B68: =B67/Assumptions!$B$256 -> 207.17984 | C68: =C67/Assumptions!$B$256 -> 328.41171 | D68: =D67/Assumptions!$B$256 -> 449.64358 | E68: =E67/Assumptions!$B$256 -> 501.21236 | F68: =F67/Assumptions!$B$256 -> 552.78114 | G68: =G67/Assumptions!$B$256 -> 622.44423 | H68: =H67/Assumptions!$B$256 -> 691.2026 | I68: =I67/Assumptions!$B$256 -> 691.2026 | ... K68: =K67/Assumptions!$B$256 -> 691.2026
A69: Retained visits | B69: =IF(B26>0,B67*B27/B26,0) -> 0 | C69: =IF(C26>0,C67*C27/C26,0) -> 226.86192 | D69: =IF(D26>0,D67*D27/D26,0) -> 370.2842 | E69: =IF(E26>0,E67*E27/E26,0) -> 521.58655 | F69: =IF(F26>0,F67*F27/F26,0) -> 597.69574 | G69: =IF(G26>0,G67*G27/G26,0) -> 677.15689 | H69: =IF(H26>0,H67*H27/H26,0) -> 773.25512 | I69: =IF(I26>0,I67*I27/I26,0) -> 845.60005 | ... K69: =IF(K26>0,K67*K27/K26,0) -> 888.03896
A70: New Organic+Referral | B70: =IF(B26>0,B67*(B29+B28)/B26,0) -> 205 | C70: =IF(C26>0,C67*(C29+C28)/C26,0) -> 329.20779 | D70: =IF(D26>0,D67*(D29+D28)/D26,0) -> 393.21669 | E70: =IF(E26>0,E67*(E29+E28)/E26,0) -> 460.68125 | F70: =IF(F26>0,F67*(F29+F28)/F26,0) -> 501.72606 | G70: =IF(G26>0,G67*(G29+G28)/G26,0) -> 544.65986 | H70: =IF(H26>0,H67*(H29+H28)/H26,0) -> 594.29939 | I70: =IF(I26>0,I67*(I29+I28)/I26,0) -> 636.13994 | ... K70: =IF(K26>0,K67*(K29+K28)/K26,0) -> 685.41965
A71: New marketing | B71: =IF(B26>0,B67*B30/B26,0) -> 312.94959 | C71: =IF(C26>0,C67*C30/C26,0) -> 264.95955 | D71: =IF(D26>0,D67*D30/D26,0) -> 360.60806 | E71: =IF(E26>0,E67*E30/E26,0) -> 270.76309 | F71: =IF(F26>0,F67*F30/F26,0) -> 282.53105 | G71: =IF(G26>0,G67*G30/G26,0) -> 334.29381 | H71: =IF(H26>0,H67*H30/H26,0) -> 360.45199 | I71: =IF(I26>0,I67*I30/I26,0) -> 246.26651 | ... K71: =IF(K26>0,K67*K30/K26,0) -> 154.5479
A73: Gynecology | B73: =MIN(B22*Assumptions!$B$287*Assumptions!$B$316,Assumptions!C189*Assumptions!$B$316,Assumptions!$D$43*Assumptions!$B$316) -> 517.94959 | C73: =MIN(C22*Assumptions!$B$287*Assumptions!$B$316,Assumptions!D189*Assumptions!$B$316,Assumptions!$D$43*Assumptions!$B$316) -> 821.02927 | D73: =MIN(D22*Assumptions!$B$287*Assumptions!$B$316,Assumptions!E189*Assumptions!$B$316,Assumptions!$D$43*Assumptions!$B$316) -> 1124.1089 | E73: =MIN(E22*Assumptions!$B$287*Assumptions!$B$316,Assumptions!F189*Assumptions!$B$316,Assumptions!$D$43*Assumptions!$B$316) -> 1253.0309 | F73: =MIN(F22*Assumptions!$B$287*Assumptions!$B$316,Assumptions!G189*Assumptions!$B$316,Assumptions!$D$43*Assumptions!$B$316) -> 1381.9528 | G73: =MIN(G22*Assumptions!$B$287*Assumptions!$B$316,Assumptions!H189*Assumptions!$B$316,Assumptions!$D$43*Assumptions!$B$316) -> 1556.1106 | H73: =MIN(H22*Assumptions!$B$287*Assumptions!$B$316,Assumptions!I189*Assumptions!$B$316,Assumptions!$D$43*Assumptions!$B$316) -> 1728.0065 | I73: =MIN(I22*Assumptions!$B$287*Assumptions!$B$316,Assumptions!J189*Assumptions!$B$316,Assumptions!$D$43*Assumptions!$B$316) -> 1728.0065 | ... K73: =MIN(K22*Assumptions!$B$287*Assumptions!$B$316,Assumptions!L189*Assumptions!$B$316,Assumptions!$D$43*Assumptions!$B$316) -> 1728.0065
A74: Unique patients | B74: =B73/Assumptions!$B$256 -> 207.17984 | C74: =C73/Assumptions!$B$256 -> 328.41171 | D74: =D73/Assumptions!$B$256 -> 449.64358 | E74: =E73/Assumptions!$B$256 -> 501.21236 | F74: =F73/Assumptions!$B$256 -> 552.78114 | G74: =G73/Assumptions!$B$256 -> 622.44423 | H74: =H73/Assumptions!$B$256 -> 691.2026 | I74: =I73/Assumptions!$B$256 -> 691.2026 | ... K74: =K73/Assumptions!$B$256 -> 691.2026
A75: Retained visits | B75: =IF(B26>0,B73*B27/B26,0) -> 0 | C75: =IF(C26>0,C73*C27/C26,0) -> 226.86192 | D75: =IF(D26>0,D73*D27/D26,0) -> 370.2842 | E75: =IF(E26>0,E73*E27/E26,0) -> 521.58655 | F75: =IF(F26>0,F73*F27/F26,0) -> 597.69574 | G75: =IF(G26>0,G73*G27/G26,0) -> 677.15689 | H75: =IF(H26>0,H73*H27/H26,0) -> 773.25512 | I75: =IF(I26>0,I73*I27/I26,0) -> 845.60005 | ... K75: =IF(K26>0,K73*K27/K26,0) -> 888.03896
A76: New Organic+Referral | B76: =IF(B26>0,B73*(B29+B28)/B26,0) -> 205 | C76: =IF(C26>0,C73*(C29+C28)/C26,0) -> 329.20779 | D76: =IF(D26>0,D73*(D29+D28)/D26,0) -> 393.21669 | E76: =IF(E26>0,E73*(E29+E28)/E26,0) -> 460.68125 | F76: =IF(F26>0,F73*(F29+F28)/F26,0) -> 501.72606 | G76: =IF(G26>0,G73*(G29+G28)/G26,0) -> 544.65986 | H76: =IF(H26>0,H73*(H29+H28)/H26,0) -> 594.29939 | I76: =IF(I26>0,I73*(I29+I28)/I26,0) -> 636.13994 | ... K76: =IF(K26>0,K73*(K29+K28)/K26,0) -> 685.41965
A77: New marketing | B77: =IF(B26>0,B73*B30/B26,0) -> 312.94959 | C77: =IF(C26>0,C73*C30/C26,0) -> 264.95955 | D77: =IF(D26>0,D73*D30/D26,0) -> 360.60806 | E77: =IF(E26>0,E73*E30/E26,0) -> 270.76309 | F77: =IF(F26>0,F73*F30/F26,0) -> 282.53105 | G77: =IF(G26>0,G73*G30/G26,0) -> 334.29381 | H77: =IF(H26>0,H73*H30/H26,0) -> 360.45199 | I77: =IF(I26>0,I73*I30/I26,0) -> 246.26651 | ... K77: =IF(K26>0,K73*K30/K26,0) -> 154.5479
A79: Cosmetology | B79: =MIN(B22*Assumptions!$B$288,MIN(Assumptions!C188,Assumptions!$D$42)) -> 2900.5177 | C79: =MIN(C22*Assumptions!$B$288,MIN(Assumptions!D188,Assumptions!$D$42)) -> 4597.7639 | D79: =MIN(D22*Assumptions!$B$288,MIN(Assumptions!E188,Assumptions!$D$42)) -> 6295.0101 | E79: =MIN(E22*Assumptions!$B$288,MIN(Assumptions!F188,Assumptions!$D$42)) -> 7016.973 | F79: =MIN(F22*Assumptions!$B$288,MIN(Assumptions!G188,Assumptions!$D$42)) -> 7738.9359 | G79: =MIN(G22*Assumptions!$B$288,MIN(Assumptions!H188,Assumptions!$D$42)) -> 8346 | H79: =MIN(H22*Assumptions!$B$288,MIN(Assumptions!I188,Assumptions!$D$42)) -> 8346 | I79: =MIN(I22*Assumptions!$B$288,MIN(Assumptions!J188,Assumptions!$D$42)) -> 8346 | ... K79: =MIN(K22*Assumptions!$B$288,MIN(Assumptions!L188,Assumptions!$D$42)) -> 8346
A80: Unique patients | B80: =B79/Assumptions!$B$257 -> 414.35967 | C80: =C79/Assumptions!$B$257 -> 656.82341 | D80: =D79/Assumptions!$B$257 -> 899.28715 | E80: =E79/Assumptions!$B$257 -> 1002.4247 | F80: =F79/Assumptions!$B$257 -> 1105.5623 | G80: =G79/Assumptions!$B$257 -> 1192.2857 | H80: =H79/Assumptions!$B$257 -> 1192.2857 | I80: =I79/Assumptions!$B$257 -> 1192.2857 | ... K80: =K79/Assumptions!$B$257 -> 1192.2857
A81: Retained visits | B81: =IF(B26>0,B79*B27/B26,0) -> 0 | C81: =IF(C26>0,C79*C27/C26,0) -> 1270.4268 | D81: =IF(D26>0,D79*D27/D26,0) -> 2073.5915 | E81: =IF(E26>0,E79*E27/E26,0) -> 2920.8847 | F81: =IF(F26>0,F79*F27/F26,0) -> 3347.0961 | G81: =IF(G26>0,G79*G27/G26,0) -> 3631.8444 | H81: =IF(H26>0,H79*H27/H26,0) -> 3734.7008 | I81: =IF(I26>0,I79*I27/I26,0) -> 4084.1154 | ... K81: =IF(K26>0,K79*K27/K26,0) -> 4289.0887
A82: New Organic+Referral | B82: =IF(B26>0,B79*(B29+B28)/B26,0) -> 1148 | C82: =IF(C26>0,C79*(C29+C28)/C26,0) -> 1843.5636 | D82: =IF(D26>0,D79*(D29+D28)/D26,0) -> 2202.0134 | E82: =IF(E26>0,E79*(E29+E28)/E26,0) -> 2579.815 | F82: =IF(F26>0,F79*(F29+F28)/F26,0) -> 2809.666 | G82: =IF(G26>0,G79*(G29+G28)/G26,0) -> 2921.2135 | H82: =IF(H26>0,H79*(H29+H28)/H26,0) -> 2870.3727 | I82: =IF(I26>0,I79*(I29+I28)/I26,0) -> 3072.456 | ... K82: =IF(K26>0,K79*(K29+K28)/K26,0) -> 3310.4693
A83: New marketing | B83: =IF(B26>0,B79*B30/B26,0) -> 1752.5177 | C83: =IF(C26>0,C79*C30/C26,0) -> 1483.7735 | D83: =IF(D26>0,D79*D30/D26,0) -> 2019.4051 | E83: =IF(E26>0,E79*E30/E26,0) -> 1516.2733 | F83: =IF(F26>0,F79*F30/F26,0) -> 1582.1739 | G83: =IF(G26>0,G79*G30/G26,0) -> 1792.9421 | H83: =IF(H26>0,H79*H30/H26,0) -> 1740.9265 | I83: =IF(I26>0,I79*I30/I26,0) -> 1189.4286 | ... K83: =IF(K26>0,K79*K30/K26,0) -> 746.44206
A85: GRAND TOTAL | B85: =B55+B61+B67+B73+B79 -> 12741.56 | C85: =C55+C61+C67+C73+C79 -> 20197.32 | D85: =D55+D61+D67+D73+D79 -> 27653.08 | E85: =E55+E61+E67+E73+E79 -> 30824.56 | F85: =F55+F61+F67+F73+F79 -> 33996.04 | G85: =G55+G61+G67+G73+G79 -> 37912.101 | H85: =H55+H61+H67+H73+H79 -> 41001.704 | I85: =I55+I61+I67+I73+I79 -> 41001.704 | ... K85: =K55+K61+K67+K73+K79 -> 41001.704
A86: Retained | B86: =B57+B63+B69+B75+B81 -> 0 | C86: =C57+C63+C69+C75+C81 -> 5580.8033 | D86: =D57+D63+D69+D75+D81 -> 9108.9913 | E86: =E57+E63+E69+E75+E81 -> 12831.029 | F86: =F57+F63+F69+F75+F81 -> 14703.315 | G86: =G57+G63+G69+G75+G81 -> 16497.825 | H86: =H57+H63+H69+H75+H81 -> 18347.603 | I86: =I57+I63+I69+I75+I81 -> 20064.185 | ... K86: =K57+K63+K69+K75+K81 -> 21071.165
A87: Organic | B87: =B58+B64+B70+B76+B82 -> 5043 | C87: =C58+C64+C70+C76+C82 -> 8098.5117 | D87: =D58+D64+D70+D76+D82 -> 9673.1305 | E87: =E58+E64+E70+E76+E82 -> 11332.759 | F87: =F58+F64+F70+F76+F82 -> 12342.461 | G87: =G58+G64+G70+G76+G82 -> 13269.751 | H87: =H58+H64+H70+H76+H82 -> 14101.387 | I87: =I58+I64+I70+I76+I82 -> 15094.169 | ... K87: =K58+K64+K70+K76+K82 -> 16263.465
A88: Marketing | B88: =B59+B65+B71+B77+B83 -> 7698.56 | C88: =C59+C65+C71+C77+C83 -> 6518.005 | D88: =D59+D65+D71+D77+D83 -> 8870.9582 | E88: =E59+E65+E71+E77+E83 -> 6660.7721 | F88: =F59+F65+F71+F77+F83 -> 6950.2637 | G88: =G59+G65+G71+G77+G83 -> 8144.5246 | H88: =H59+H65+H71+H77+H83 -> 8552.7142 | I88: =I59+I65+I71+I77+I83 -> 5843.35 | ... K88: =K59+K65+K71+K77+K83 -> 3667.0736
A90: COHORT-BASED MARKETING BUDGET
A91: Component | B91: Y1 | C91: Y2 | D91: Y3 | E91: Y4 | F91: Y5 | G91: Y6 | H91: Y7 | I91: Y8 | J91: Y9 | K91: Y10
A92: Acquisition (CAC × New Mkt Patients) | B92: =Assumptions!$B$262*B30 -> 1502158 | C92: =Assumptions!$B$262*C30 -> 1271805.9 | D92: =Assumptions!$B$262*D30 -> 1730918.7 | E92: =Assumptions!$B$262*E30 -> 1299662.8 | F92: =Assumptions!$B$262*F30 -> 1356149 | G92: =Assumptions!$B$262*G30 -> 1604610.3 | H92: =Assumptions!$B$262*H30 -> 1730169.6 | I92: =Assumptions!$B$262*I30 -> 1182079.3 | ... K92: =Assumptions!$B$262*K30 -> 741829.9
A93: Retention (cost × Retained Patients) | B93: =Assumptions!$B$263*B27 -> 0 | C93: =Assumptions!$B$263*C27 -> 181489.54 | D93: =Assumptions!$B$263*D27 -> 296227.36 | E93: =Assumptions!$B$263*E27 -> 417269.24 | F93: =Assumptions!$B$263*F27 -> 478156.59 | G93: =Assumptions!$B$263*G27 -> 541725.52 | H93: =Assumptions!$B$263*H27 -> 618604.1 | I93: =Assumptions!$B$263*I27 -> 676480.04 | ... K93: =Assumptions!$B$263*K27 -> 710431.17
A94: Base Brand (agency + SMM) | B94: =(Assumptions!$D$91+Assumptions!$D$92)*Revenue!B5 -> 516000 | C94: =(Assumptions!$D$91+Assumptions!$D$92)*Revenue!C5 -> 536640 | D94: =(Assumptions!$D$91+Assumptions!$D$92)*Revenue!D5 -> 558105.6 | E94: =(Assumptions!$D$91+Assumptions!$D$92)*Revenue!E5 -> 580429.82 | F94: =(Assumptions!$D$91+Assumptions!$D$92)*Revenue!F5 -> 603647.02 | G94: =(Assumptions!$D$91+Assumptions!$D$92)*Revenue!G5 -> 627792.9 | H94: =(Assumptions!$D$91+Assumptions!$D$92)*Revenue!H5 -> 652904.61 | I94: =(Assumptions!$D$91+Assumptions!$D$92)*Revenue!I5 -> 679020.8 | ... K94: =(Assumptions!$D$91+Assumptions!$D$92)*Revenue!K5 -> 734428.9
A95: TOTAL Marketing Budget | B95: =MIN(B92+B93+B94,Revenue!B13*Assumptions!$B$191) -> 1529040 | C95: =MIN(C92+C93+C94,Revenue!C13*Assumptions!$B$191) -> 1989935.4 | D95: =MIN(D92+D93+D94,Revenue!D13*Assumptions!$B$191) -> 2585251.6 | E95: =MIN(E92+E93+E94,Revenue!E13*Assumptions!$B$191) -> 2297361.9 | F95: =MIN(F92+F93+F94,Revenue!F13*Assumptions!$B$191) -> 2437952.6 | G95: =MIN(G92+G93+G94,Revenue!G13*Assumptions!$B$191) -> 2774128.7 | H95: =MIN(H92+H93+H94,Revenue!H13*Assumptions!$B$191) -> 3001678.3 | I95: =MIN(I92+I93+I94,Revenue!I13*Assumptions!$B$191) -> 2537580.1 | ... K95: =MIN(K92+K93+K94,Revenue!K13*Assumptions!$B$191) -> 2186690
A96: Marketing % of Revenue | B96: =IF(Revenue!B13>0,B95/Revenue!B13,0) -> 0.2 | C96: =IF(Revenue!C13>0,C95/Revenue!C13,0) -> 0.15885425 | D96: =IF(Revenue!D13>0,D95/Revenue!D13,0) -> 0.14480332 | E96: =IF(Revenue!E13>0,E95/Revenue!E13,0) -> 0.11077914 | F96: =IF(Revenue!F13>0,F95/Revenue!F13,0) -> 0.10269616 | G96: =IF(Revenue!G13>0,G95/Revenue!G13,0) -> 0.10033053 | H96: =IF(Revenue!H13>0,H95/Revenue!H13,0) -> 0.096145301 | I96: =IF(Revenue!I13>0,I95/Revenue!I13,0) -> 0.078153844 | ... K96: =IF(Revenue!K13>0,K95/Revenue!K13,0) -> 0.062266022
A97: Comparison: %-of-Revenue method | B97: =Assumptions!$B$71*Revenue!B13 -> 1146780 | C97: =Assumptions!$B$71*Revenue!C13 -> 1879020 | D97: =Assumptions!$B$71*Revenue!D13 -> 2678030.8 | E97: =Assumptions!$B$71*Revenue!E13 -> 3110732.7 | F97: =Assumptions!$B$71*Revenue!F13 -> 3560920.8 | G97: =Assumptions!$B$71*Revenue!G13 -> 4147484.6 | H97: =Assumptions!$B$71*Revenue!H13 -> 4683034.3 | I97: =Assumptions!$B$71*Revenue!I13 -> 4870355.6 | ... K97: =Assumptions!$B$71*Revenue!K13 -> 5267776.6
A99: STAFF UTILIZATION BY DEPARTMENT
A100: Department | B100: Metric | C100: Y1 | D100: Y2 | E100: Y3 | F100: Y4 | G100: Y5 | H100: Y6 | I100: Y7 | J100: Y8 | K100: Y9 | L100: Y10
A101: ── Utilization (%) ──
A102: Ortho/Neuro | B102: % of cap | C102: ="" | D102: ="" | E102: ="" | F102: ="" | G102: ="" | H102: ="" | I102: ="" | J102: ="" | ... L102: =""
A103: Physio | B103: % of cap | C103: =IFERROR(B55/Assumptions!C186,0) -> 0.59364822 | D103: =IFERROR(C55/Assumptions!D186,0) -> 0.94102317 | E103: =IFERROR(D55/Assumptions!E186,0) -> 0.96629858 | F103: =IFERROR(E55/Assumptions!F186,0) -> 0.99426605 | G103: =IFERROR(F55/Assumptions!G186,0) -> 0.95035563 | H103: =IFERROR(G55/Assumptions!H186,0) -> 0.94422548 | I103: =IFERROR(H55/Assumptions!I186,0) -> 0.99027782 | J103: =IFERROR(I55/Assumptions!J186,0) -> 0.99027782 | ... L103: =IFERROR(K55/Assumptions!L186,0) -> 0.93815794
A104: Dental | B104: % of cap | C104: =IFERROR(B61/Assumptions!C187,0) -> 0.5724465 | D104: =IFERROR(C61/Assumptions!D187,0) -> 0.90741519 | E104: =IFERROR(D61/Assumptions!E187,0) -> 0.93178792 | F104: =IFERROR(E61/Assumptions!F187,0) -> 0.83092234 | G104: =IFERROR(F61/Assumptions!G187,0) -> 0.91641435 | H104: =IFERROR(G61/Assumptions!H187,0) -> 0.85991963 | I104: =IFERROR(H61/Assumptions!I187,0) -> 0.92241379 | J104: =IFERROR(I61/Assumptions!J187,0) -> 0.92241379 | ... L104: =IFERROR(K61/Assumptions!L187,0) -> 0.92241379
